Workbook

Sheet STARTUPS
A1: No. | B1: Year | C1: Resolution No: | D1: TYPE | E1: Program | F1: Project Title | G1: Name of Proponent | H1: Contact Details | I1: Amount | J1: CLASS | K1: STATUS | L1: Promotional Assistance | M1: Revenue Growth (annual/cumulative) | N1: Jobs Created | O1: Investments Attracted (private co-investment, seed, VC, grants) | P1: Market Reach (local, regional, global) | Q1: High-tech Exports (export volume/value) if applicable | R1: Social Impact | S1: Next Possible Intervention
A2: 1 | B2: 2018 | C2: NA | D2: PAC | E2: TECHNICOM 1.0 | F2: Optimization of an Industry Grade Prototype of Po Lite Products | G2: Dr. Ria Liza Canlas | H2: riadear21@yahoo.com | I2: 4999045 | J2: STARTUP
A3: 2 | B3: 2018 | C3: NA | D3: PAC | E3: TECHNICOM 1.0 | F3: Pilot Testing of a Deepwater Operation 3D Visual Mapping and Inspection System (PD-DOMAINS) | G3: Mr. Francis James Corpuz ANTIPARA Exploration Inc. | H3: franciscorpuz@gmail.com | I3: 3058155.2 | J3: STARTUP
A4: 3 | B4: 2018 | C4: NA | D4: PAC | E4: TECHNICOM 1.0 | F4: Development of an Alternative Credit Scoring Model applying Machine Learning in Financing Farmers | G4: Mr. Ruel T. Amparo Cropital Enterprises Corporation | H4: ruel@cropital.com | I4: 3551018 | J4: STARTUP
A5: 4 | B5: 2019 | C5: NA | D5: PAC | E5: TECHNICOM 1.0 | F5: Product Design, Manufacturing and Field Scale Testing of StillFresh: Spoilage Monitoring Strip | G5: Mr. Joseph Christopher G. Doroja | H5: joseph.doroja@obf.ateneo.edu, etinhay@gmail.com | I5: 1636971 | J5: STARTUP
A6: 5 | B6: 2019 | C6: NA | D6: PAC | E6: TECHNICOM 1.0 | F6: Integration of Data Science and Scaling Up of Payruler, a comprehensive Human Resource Management System (HRMS) | G6: Mr. Warlito Pio S. De Jesus | H6: jojo@geniihut.com, jojo@payruler.com, timmy@geniihut.com, timmy@payruler.com | I6: 3258768 | J6: STARTUP
A7: 6 | B7: 2019 | C7: NA | D7: PAC | E7: TECHNICOM 1.0 | F7: Optimization of Virtual Reality Kit (VR Kit) for New Media Technology and Commercial Competitiveness | G7: Mr. Ryan Tan Yu | H7: ryan@mataverse.ph | I7: 4019382 | J7: STARTUP
A8: 7 | B8: 2019 | C8: NA | D8: PAC | E8: TECHNICOM 1.0 | F8: Enhancement of the Micab Cab Hailing Engine thru Big Data Analytics | G8: CONRADO D. CAMILON JR, Project Leader ALEXA’S ENGINEERING SERVICES | I8: 3135851.2 | J8: STARTUP
A9: 8 | B9: 2019 | C9: NA | D9: PAC | E9: TECHNICOM 1.0 | F9: Scale-up Manufacturing of Biotek-M Diagnostic Kits and Post Marketing for Third Party Evaluation | G9: Dr. Raul V. Destura Denise Lacuna | H9: rvdestura@up.edu.ph jadelacuna12@gmail.com | I9: 16926594 | J9: STARTUP
A10: 9 | B10: 2019 | C10: NA | D10: PAC | E10: TECHNICOM 1.0 | F10: Technology Enhancement and Commercialization of Exora Intellex as an Energy Analytics Machine Learning Platform for Industrial Smart Energy Management and Electricity Cost Reduction | G10: Mr. Sergius Angelo Santos Exora Technologies, Inc. | H10: sergius@exora.ph | I10: 4394800 | J10: STARTUP
A11: 10 | B11: 2019 | C11: 2019-54 | D11: APPROVAL | E11: VFP | F11: Application for Local and International Certifications of Manila Healthtek, Inc. as a Manufacturing Company for Molecular-Based Diagnostic kits | G11: Dr. Raul V. Destura President/CEO Manila Healthtek , Inc. | H11: rvdestura@up.edu.ph | I11: 3792164.9 | J11: STARTUP | K11: COMPLETED
A12: 11 | B12: 2020 | C12: 2020-07-memo | D12: APPROVAL | E12: IBED | F12: Pilot Production of " Snap On and Off Handle for a Five-Gallon Bottle Container" | G12: Mr. Carlos N. Detalo Jr. | H12: - | I12: 409314 | J12: STARTUP
A13: 12 | B13: 2021 | C13: 2021-46 | D13: APPROVAL | E13: IBED | F13: PIlot Scale Production of Cooked Balut in Shell with Commercially Acceptable Shelf-life for Feasibility and Marketing Testing | G13: Ambrocio Kerwin A. Perez | H13: - | I13: 349800 | J13: STARTUP
A14: 13 | B14: 2022 | C14: 2022-109 | D14: APPROVAL | E14: ITECH | F14: Commercialization of Maker-scope | G14: MR. JEREMY C. DE LEON | I14: 1083679 | J14: STARTUP | K14: WIDTHRAWN
A15: 14 | B15: 2022 | C15: 2022-109 | D15: PROMOTION | E15: ITECH | F15: Commercialization of Maker-scope | G15: MR. JEREMY C. DE LEON | H15: jeremycdeleon@gmail.com | I15: 1083679 | J15: STARTUP | K15: COMPLETED | L15: Marketing Assistance Program, SIIF
A16: 15 | B16: 2023 | C16: NA | D16: PROMOTION | E16: GALING | F16: Technology Validation of Pili Seal | G16: Engr. Mark Kennedy E. Bantugon | H16: markkennedy09bantugon@gmail.com | I16: 349799.56 | J16: STARTUP | K16: ONGOING | L16: Marketing Assistance Program, LUNDUYAN
A17: 16 | B17: 2023 | C17: NA | D17: PROMOTION | E17: GALING | F17: Improved KoolGear | G17: Mr. Ivan Brent Nara | H17: naraivanbrent@gmail.com | I17: 96107 | J17: STARTUP | L17: Marketing Assistance Program
A18: 17 | B18: 2023 | C18: NA | D18: PROMOTION | E18: GALING | F18: Foldable Water Tank with Zeramic Filter | G18: Ms. Eleanor M. Olegario | H18: lithos.opc.2021@gmail.com | I18: 191500 | J18: STARTUP | L18: Marketing Assistance Program, LUNDUYAN
A19: 18 | B19: 2025 | C19: 2025-17 | D19: APPROVAL | E19: GALING | F19: Fabrication, and Installation of a 50W LED Flood Light Post with Integration of Small-scale Savonius-Type Helical Vertical Axis Wind Turbine (VAWT) and Solar Panel | G19: Engr. Jose Luis L. Villalon | H19: louie.vdaliinnovations@gmail.com +63 915 126 5571 | I19: 358538 | J19: STARTUP | K19: ONGOING
A20: 19 | B20: 2025 | C20: NA | E20: EIPRAP | F20: Enhancement, Market Validation and Pilot Production of AI-Driven Farm Management Module (AID-FMM) | G20: Waste4good Research and Experimental Development in Engineering and Technology | H20: lurelynpablo@gmail.com lorilyn.daquioag@eee.upd.edu.ph 639385504997 | J20: STARTUP | K20: ONGOING
A21: 20 | B21: 2025 | C21: NA | E21: EIPRAP | F21: High-resolution 3D Geological Mapping with Ambient Electromagnetic Interferometry | G21: Emmanuel G. Ramos Mark Linus C. Ramos Rodolfo Alfonso R. Sabio | H21: - | J21: STARTUP | K21: ONGOING
A22: 21 | B22: 2025 | C22: NA | E22: EIPRAP | F22: A System and Method for Managing Healthcare Services and Networks | G22: SeeYouDoc Corporation | H22: noel@seeyoudoc.com | J22: STARTUP | K22: ONGOING
A23: 22 | B23: 2025 | C23: NA | D23: ISIPAG | E23: IPRAP | F23: A System and Method for Managing Healthcare Services and Networks (NPE - South Korea) | G23: SeeYouDoc Corporation | H23: noel@seeyoudoc.com | J23: STARTUP | K23: ONGOING
A24: 23 | B24: 2025 | C24: NA | D24: ISIPAG | E24: IPRAP | F24: System and Method for Secure Disbursement of Loans and Income-Based Advances with Biometric Consent and Configurable Repayment Orchestration | G24: Vashcorp Inc. | H24: varianchu@gmail.com | J24: STARTUP
A25: 24 | B25: 2025 | C25: NA | D25: ISIPAG | E25: IPRAP | F25: The Process Of Making An AI-Driven Farm Management Module And Agricultural Monitoring System (NPE - Japan) | G25: Waste4Good Technologies a.k.a. GreenVisionsPh | H25: mari@rezbin.ph, hello@rezbin.ph 639178920234 | J25: STARTUP | K25: ONGOING
A26: 25 | B26: 2025 | C26: NA | D26: PROMOTION | E26: EIPRAP | F26: Enhancement, Market Validation and Pilot Production of AI-Driven Farm Management Module (AID-FMM) | G26: Waste4good Research and Experimental Development in Engineering and Technology | H26: lurelynpablo@gmail.com lorilyn.daquioag@eee.upd.edu.ph 639385504997 | I26: 2384720 | J26: STARTUP | K26: ONGOING | L26: Market Intelligence under IMPAKT
A27: 26 | B27: 2025 | C27: NA | D27: PROMOTION | E27: EIPRAP | F27: A System and Method for Managing Healthcare Services and Networks | G27: SeeYouDoc Corporation | H27: noel@seeyoudoc.com | I27: 2332760.9 | J27: STARTUP | K27: ONGOING | L27: IEIG 2025, PHILIPPiNEXT
A28: 27 | B28: 2025 | C28: NA | D28: PROMOTION | E28: GALING | F28: Fabrication, and Installation of a 50W LED Flood Light Post with Integration of Small-scale Savonius-Type Helical Vertical Axis Wind Turbine (VAWT) and Solar Panel | G28: Engr. Jose Luis L. Villalon | H28: louie.vdaliinnovations@gmail.com +63 915 126 5571 | I28: 358538 | J28: STARTUP | K28: ONGOING
A29: 28 | B29: 2022 | C29: NA | D29: PAC | E29: TECHNICOM | F29: Commercialization of the 4Gives System | G29: Mr. Varian Sherwin Chu Vashcorp, Inc. | H29: varianchu@gmail.com | I29: 5867730.2 | J29: STARTUP | K29: ONGOING
A30: 29 | B30: 2023 | C30: 2023-79 | D30: APPROVAL | E30: GALING | F30: Improved KoolGear | G30: Mr. Ivan Brent Nara Bldg. 23, UP Bliss, Diliman, Quezon City | H30: naraivanbrent@gmail 09751905598 | I30: 96107 | J30: STARTUP | K30: ONGOING
A31: 30 | B31: 2023 | C31: 2023-66 | D31: APPROVAL | E31: GALING | F31: Foldable Water Tank with Zeramic Filter | G31: Ms. Eleanor M. Olegario | H31: eleanor.olegario@gmail.com 09209129187 | I31: 191500 | J31: STARTUP | K31: COMPLETED
A32: 31 | B32: 2023 | C32: 2023-30 | D32: APPROVAL | E32: GALING | F32: Technology Validation of Pili Seal | G32: Engr. Mark Kennedy E. Bantugon | H32: markkennedy09bantugon@gmail.com andpili.adheseal@gmail.com | I32: 349799.56 | J32: STARTUP | K32: ONGOING
A33: 32 | B33: 2023 | C33: 2023-81 | D33: APPROVAL | E33: TECHNICOM | F33: Technology and business validation of an advanced web and mobile Point-of-Sale (POS) software-as-a-service (SAAS) application for Philippine micro and small retail businesses | G33: Renzo Navarro Ducusin Project Leader IOL, Inc. | H33: kevin@iolph.com 074-6209538 | I33: 2715682.8 | J33: STARTUP | K33: ONGOING
A34: 33 | B34: 2023 | C34: 2023-83 | D34: APPROVAL | E34: TECHNICOM | F34: Determining the Pesticide Residue Level of Mangoes using a smart metal oxide nanosensor for Post-Harvest Applications | G34: Ms. Normie Jean Sajor Lacubtan Project Leader | H34: njsajor@gmail.com f.normiejean.lacubtan@cmu.edu.ph | I34: 2398683 | J34: STARTUP | K34: ONGOING
A35: 34 | B35: 2023 | C35: PAC | D35: APPROVAL | E35: TECHNICOM | F35: Scaling Digital Clustering Solution for Enhanced Agri-Value Chain Integration of Farm Konek | G35: John Vincent Q. Gastanes Project Zacchaeus Marketing Cooperative | H35: gastanesjohnvincent@gmail.com 639177979073 | I35: 7936800 | J35: STARTUP | K35: ONGOING
A36: 35 | B36: 2023 | C36: NA | D36: PROMOTION | E36: GALING | F36: Improved KoolGear | G36: Mr. Ivan Brent Nara Bldg. 23, UP Bliss, Diliman, Quezon City | H36: naraivanbrent@gmail 09751905598 | I36: 96107 | J36: STARTUP | K36: ONGOING | L36: LUNDUYAN, Marketing Assistance Program
A37: 36 | B37: 2023 | C37: NA | D37: PROMOTION | E37: GALING | F37: Foldable Water Tank with Zeramic Filter | G37: Ms. Eleanor M. Olegario | H37: eleanor.olegario@gmail.com 09209129187 | I37: 191500 | J37: STARTUP | K37: COMPLETED | L37: Marketing Assistance Program, KIWIE
A38: 37 | B38: 2023 | C38: NA | D38: PROMOTION | E38: GALING | F38: Technology Validation of Pili Seal | G38: Engr. Mark Kennedy E. Bantugon | H38: markkennedy09bantugon@gmail.com andpili.adheseal@gmail.com | I38: 349799.56 | J38: STARTUP | K38: ONGOING | L38: PHILIPPiNEXT, Marketing Assistance Program, CES 2025, SIIF
A39: 38 | B39: 2023 | C39: NA | D39: PROMOTION | E39: TECHNICOM | F39: Technology and business validation of an advanced web and mobile Point-of-Sale (POS) software-as-a-service (SAAS) application for Philippine micro and small retail businesses | G39: Renzo Navarro Ducusin Project Leader IOL, Inc. | H39: kevin@iolph.com 074-6209538 | I39: 2715682.8 | J39: STARTUP | K39: ONGOING
A40: 39 | B40: 2023 | C40: NA | D40: PROMOTION | E40: TECHNICOM | F40: Determining the Pesticide Residue Level of Mangoes using a smart metal oxide nanosensor for Post-Harvest Applications | G40: Ms. Normie Jean Sajor Lacubtan Project Leader | H40: njsajor@gmail.com f.normiejean.lacubtan@cmu.edu.ph | I40: 2398683 | J40: STARTUP | K40: ONGOING
A41: 40 | B41: 2023 | C41: NA | D41: PROMOTION | E41: TECHNICOM | F41: Scaling Digital Clustering Solution for Enhanced Agri-Value Chain Integration of Farm Konek | G41: John Vincent Q. Gastanes Project Zacchaeus Marketing Cooperative | H41: gastanesjohnvincent@gmail.com 639177979073 | I41: 7936800 | J41: STARTUP | K41: ONGOING
A42: 41 | B42: 2024 | C42: 2024-89 | D42: APPROVAL | E42: GALING | F42: Marissa Turbine: Vertical-Axis Tidal Turbine | G42: Mr. Patrick Roland de Guzman 65 Lawa, Obando, Bulacan | H42: deguzmanpatrickroland@gmail.com 09974916634 | I42: 395212 | J42: STARTUP | K42: ONGOING
A43: 42 | B43: 2024 | C43: 2024-36 | D43: APPROVAL | E43: GALING | F43: Technology Validation of Unas Canvas (UnVas) | G43: Julienne Fabie-Agapin Lumbia District, Pagadian City | H43: juliennestephanie.agapin@wmsu.edu.ph 09362660139 | I43: 43250 | J43: STARTUP | K43: COMPLETED
A44: 43 | B44: 2024 | C44: 2024-54 | D44: APPROVAL | E44: GALING | F44: Technology Validation of IOT Artificial Intelligence-Based Dosing System in Greenhouse | G44: Mr. Alvin Phoebe Artemis A. Valdez Interior Fidelidad Street, Barangay 1, Balayan, Batagas 4213 | H44: alvinphoebeartemis@gmail.com +639918781878; +639916453232 | I44: 236341.77 | J44: STARTUP | K44: ONGOING
A45: 44 | B45: 2024 | C45: 2024-71 | D45: APPROVAL | E45: TECHNICOM | F45: Automated Coconut Sap Extraction: Enhancing Productivity and Quality Through Innovative Technology | G45: Luzmar M. Gabor KASAKA Agriventures, Inc. | H45: asaka@aim.edu 9175305742 | I45: 2998072 | J45: STARTUP | K45: ONGOING
A46: 45 | B46: 2024 | C46: 2024-78 | D46: APPROVAL | E46: TECHNICOM | F46: Enhancement and Market Validation of AI-Powered Property Management Solutions for the Philippines | G46: Mr. Jesehl Charles Basco Project Leader Collo/Proprty Technology Solutions Inc. | H46: jay@collo.ph 9178327166 | I46: 2911170 | J46: STARTUP | K46: ONGOING
A47: 46 | B47: 2024 | C47: 2024-82 | D47: APPROVAL | E47: TECHNICOM | F47: Enhancement, Market Validation, and Pilot Production of AI-Driven Farm Management Module (AID-FMM) | G47: Ms. Lorilyn P. Daquioag Project leader Waste4Good technologies | H47: lurelynpablo@gmail.com lorilyn.daquioag@eee.upd.edu.ph 639385504997 | I47: 2384720 | J47: STARTUP | K47: ONGOING
A48: 47 | B48: 2024 | C48: 2024-88 | D48: APPROVAL | E48: TECHNiCOM | F48: Improvement and Pilot Testing of Alerto PH AI-as-a-Service (AlaaS) | G48: Ms. Cristina Macaraig WiredField Philippines Inc. | H48: cristina@wiredfield.com | I48: 2975715 | J48: STARTUP | K48: ONGOING
A49: 48 | B49: 2024 | C49: 2024-74 | D49: APPROVAL | E49: TECHNICOM | F49: Market Testing of Online Residential Rental Marketplace for Filipino Students and Young Professionals | G49: Alyssa Casandra Wee Project Leader/ Krelio Technologies Inc. | H49: alyssa@dormy.ph, hello@dormy.ph 0992 681 6544 | I49: 2999945.7 | J49: STARTUP | K49: ONGOING
A50: 49 | B50: 2024 | C50: 2024-27 | D50: APPROVAL | E50: TECHNICOM | F50: Pilot Testing and Technology Validation of Fortified Powdered Coconut Milk as a Powdered Dairy Alternative to Lactose Intolerant and Nutrient Deficient Filipino Children and Adults | G50: Samuel Antonius De Chavez Tecuala Dehusk | H50: samuel.tecuala@dehusk.com.ph 09565734432 | I50: 2789556 | J50: STARTUP | K50: ONGOING
... A56: 55 | B56: 2024 | C56: 2024-87 | D56: APPROVAL | E56: EVFP | F56: Scale up of Fullmight Agricultural Corp. Operations and Product Certification | G56: Dr. Virginia M. Padilla Secretary and Treasurer Fullmight Agricultural Corp. | H56: Tel. no.: (049) 508-0557 CP no.: 0917-887-8542, 0917-179-8542 Email: padilla7.jaime@gmail.com, virgiem.padilla@gmail.com | I56: 4771250 | J56: STARTUP | K56: ONGOING
A57: 56 | B57: 2024 | C57: 2024-84 | D57: APPROVAL | E57: EVFP | F57: Scale-Up Assistance for WEHLO Technologies, Inc. under E-VFP | G57: Dr. Cris Edward Monjardin Chief Technology Technology WEHLO Resilience Technology Corporation Inc. | H57: 09692314619 cefmonjardin@mapua.edu.ph | I57: 4.975,000.00 | J57: STARTUP | K57: ONGOING
A58: 57 | B58: 2024 | C58: 2024-90 | D58: APPROVAL | E58: EVFP | F58: Scale-up Operational Assistance to Hiraya Technology Solutions, Inc. | G58: Mr. Stephen L. Larcia Chief Executive Officer Hiraya Technology Solutions, Inc. | H58: Cell No.: (02) 8826 6836 Email: stephen@hirayatech.ai; info@hirayatech.ai | I58: 4000000 | J58: STARTUP | K58: ONGOING
A59: 58 | B59: 2024 | C59: 2024-80 | D59: APPROVAL | E59: EVFP | F59: Scaleup of CHRG Inc. Operations and Product Certifications | G59: Engr. Leo Allen S. Tayo CEO and President CHRG Electric vehicle technologies Inc | H59: Engr. Leo Allen S. Tayo – 09272103449 Engr. Rovinna Janel Tayo – 09297193619 leo@chrg.tech / janel@chrg.tech | I59: 5000000 | J59: STARTUP | K59: ONGOING
A60: 59 | B60: 2024 | C60: 2024-57 | D60: APPROVAL | E60: EVFP | F60: Scaling up for Market Expansion and Customer Retention | G60: Ms. Ralen Rose Gloria L. Malatbalat COO, making.technology Manufacturing Corporation | H60: ralen@makingtech.co / inquire@makingtech.co | I60: 4668619.3 | J60: STARTUP | K60: ONGOING
A61: 60 | B61: 2024 | C61: 2024-51 | D61: PROMOTION | E61: EVFP | F61: Commercialization of Cerebro Plus: An Integrated School Management and Content Library System for k-12 Schools | G61: Jonald Justine U. Itugot Chief Executive Officer Cerebro Solutions, Inc. | H61: justine@cerebro.ph +63 917 886 5402 | I61: 3412000 | J61: STARTUP | K61: ONGOING
A62: 61 | B62: 2024 | C62: 2024-68 | D62: PROMOTION | E62: EVFP | F62: Enhance IP protection and Commercialization of Value-based Care Module of See You Doc Corp. under the Expanded VFP | G62: Mr. Noel Gary E. Del Castillo Founder and CEO | H62: noel@seeyoudoc.com | I62: 2332760.9 | J62: STARTUP | K62: ONGOING
A63: 62 | B63: 2024 | C63: 2024-58 | D63: PROMOTION | E63: EVFP | F63: Enhancement of BizKit (The First Local Centralized Business Suite) To Better Facilitate Cross-functional And Holistic Business Operations In The New Normal | G63: Marc Carlo Lijauco President BizKit Technologies Inc. | H63: mclijauco@bizkittechnologies.com | I63: 4000000 | J63: STARTUP | K63: ONGOING
A64: 63 | B64: 2024 | C64: 2024-87 | D64: PROMOTION | E64: EVFP | F64: Scale up of Fullmight Agricultural Corp. Operations and Product Certification | G64: Dr. Virginia M. Padilla Secretary and Treasurer Fullmight Agricultural Corp. | H64: Tel. no.: (049) 508-0557 CP no.: 0917-887-8542, 0917-179-8542 Email: padilla7.jaime@gmail.com, virgiem.padilla@gmail.com | I64: 4771250 | J64: STARTUP | K64: ONGOING
A65: 64 | B65: 2024 | C65: 2024-84 | D65: PROMOTION | E65: EVFP | F65: Scale-Up Assistance for WEHLO Technologies, Inc. under E-VFP | G65: Dr. Cris Edward Monjardin Chief Technology Technology WEHLO Resilience Technology Corporation Inc. | H65: 09692314619 cefmonjardin@mapua.edu.ph | I65: 4.975,000.00 | J65: STARTUP | K65: ONGOING | L65: CES 2025, Handa Pinas 2025
A66: 65 | B66: 2024 | C66: 2024-90 | D66: PROMOTION | E66: EVFP | F66: Scale-up Operational Assistance to Hiraya Technology Solutions, Inc. | G66: Mr. Stephen L. Larcia Chief Executive Officer Hiraya Technology Solutions, Inc. | H66: Cell No.: (02) 8826 6836 Email: stephen@hirayatech.ai; info@hirayatech.ai | I66: 4000000 | J66: STARTUP | K66: ONGOING | L66: WoSG, CES 2025, DOST-TAPI and APCTT event Sept 3-4, 2024 , Handa Pinas 2025
A67: 66 | B67: 2024 | C67: 2024-80 | D67: PROMOTION | E67: EVFP | F67: Scaleup of CHRG Inc. Operations and Product Certifications | G67: Engr. Leo Allen S. Tayo CEO and President CHRG Electric vehicle technologies Inc | H67: Engr. Leo Allen S. Tayo – 09272103449 Engr. Rovinna Janel Tayo – 09297193619 leo@chrg.tech / janel@chrg.tech | I67: 5000000 | J67: STARTUP | K67: ONGOING | L67: E-MarkET WoSG Market Intelligence, NICE, CES 2025, APCTT 2024 Exhibit, Philippinext
A68: 67 | B68: 2024 | C68: 2024-57 | D68: PROMOTION | E68: EVFP | F68: Scaling up for Market Expansion and Customer Retention | G68: Ms. Ralen Rose Gloria L. Malatbalat COO, making.technology Manufacturing Corporation | H68: ralen@makingtech.co / inquire@makingtech.co | I68: 4668619.3 | J68: STARTUP | K68: ONGOING
A69: 68 | B69: 2024 | C69: NA | D69: PROMOTION | E69: GALING | F69: Marissa Turbine: Vertical-Axis Tidal Turbine | G69: Mr. Patrick Roland de Guzman 65 Lawa, Obando, Bulacan | H69: deguzmanpatrickroland@gmail.com 09974916634 | I69: 395212 | J69: STARTUP | K69: ONGOING | L69: PHILIPPiNEXT
A70: 69 | B70: 2024 | C70: NA | D70: PROMOTION | E70: GALING | F70: Technology Validation of Unas Canvas (UnVas) | G70: Julienne Fabie-Agapin Lumbia District, Pagadian City | H70: juliennestephanie.agapin@wmsu.edu.ph 09362660139 | I70: 43250 | J70: STARTUP | K70: COMPLETED | L70: PHILIPPiNEXT, Marketing Assistance Program, KIWIE, LUNDUYAN
A71: 70 | B71: 2024 | C71: NA | D71: PROMOTION | E71: GALING | F71: Technology Validation of IOT Artificial Intelligence-Based Dosing System in Greenhouse | G71: Mr. Alvin Phoebe Artemis A. Valdez Interior Fidelidad Street, Barangay 1, Balayan, Batagas 4213 | H71: alvinphoebeartemis@gmail.com +639918781878; +639916453232 | I71: 236341.77 | J71: STARTUP | K71: ONGOING | L71: PHILIPPiNEXT
A72: 71 | B72: 2024 | C72: NA | D72: PROMOTION | E72: TECHNICOM | F72: Automated Coconut Sap Extraction: Enhancing Productivity and Quality Through Innovative Technology | G72: Luzmar M. Gabor KASAKA Agriventures, Inc. | H72: asaka@aim.edu 9175305742 | I72: 2998072 | J72: STARTUP | K72: ONGOING
A73: 72 | B73: 2024 | C73: NA | D73: PROMOTION | E73: TECHNICOM | F73: Enhancement and Market Validation of AI-Powered Property Management Solutions for the Philippines | G73: Mr. Jesehl Charles Basco Project Leader Collo/Proprty Technology Solutions Inc. | H73: jay@collo.ph 9178327166 | I73: 2911170 | J73: STARTUP | K73: ONGOING
A74: 73 | B74: 2024 | C74: NA | D74: PROMOTION | E74: TECHNICOM | F74: Enhancement, Market Validation, and Pilot Production of AI-Driven Farm Management Module (AID-FMM) | G74: Ms. Lorilyn P. Daquioag Project leader Waste4Good technologies | H74: lurelynpablo@gmail.com lorilyn.daquioag@eee.upd.edu.ph 639385504997 | I74: 2384720 | J74: STARTUP | K74: ONGOING
A75: 74 | B75: 2024 | C75: NA | D75: PROMOTION | E75: TECHNiCOM | F75: Improvement and Pilot Testing of Alerto PH AI-as-a-Service (AlaaS) | G75: Ms. Cristina Macaraig WiredField Philippines Inc. | H75: cristina@wiredfield.com | I75: 2975715 | J75: STARTUP | K75: ONGOING
A76: 75 | B76: 2024 | C76: NA | D76: PROMOTION | E76: TECHNICOM | F76: Market Testing of Online Residential Rental Marketplace for Filipino Students and Young Professionals | G76: Alyssa Casandra Wee Project Leader/ Krelio Technologies Inc. | H76: alyssa@dormy.ph, hello@dormy.ph 0992 681 6544 | I76: 2999945.7 | J76: STARTUP | K76: ONGOING
A77: 76 | B77: 2024 | C77: NA | D77: PROMOTION | E77: TECHNICOM | F77: Pilot Testing and Technology Validation of Fortified Powdered Coconut Milk as a Powdered Dairy Alternative to Lactose Intolerant and Nutrient Deficient Filipino Children and Adults | G77: Samuel Antonius De Chavez Tecuala Dehusk | H77: samuel.tecuala@dehusk.com.ph 09565734432 | I77: 2789556 | J77: STARTUP | K77: ONGOING
A78: 77 | B78: 2024 | C78: NA | D78: PROMOTION | E78: TECHNICOM | F78: Scaling up Testing of a Peer-to-Peer Car Sharing Marketplace for the Filipino Car Sharing Economy | G78: Mr. Miguel Locsin Project Leader DOON Transport Technologies Inc. | H78: miguel@doon.ph 09178076499 | I78: 2896644 | J78: STARTUP | K78: ONGOING
A79: 78 | B79: 2024 | C79: NA | D79: PROMOTION | E79: TECHNICOM | F79: The Scrapcycle PH field and Market Testing of Scrap Trading Dynamics Across Philippine Urban Landscapes | G79: Genevieve P. Navales/Female Project Leader, ScrapCycle PH | H79: vievenavales29@gmail.com 09952033203 | I79: 2785599 | J79: STARTUP | K79: ONGOING
A80: 79 | B80: 2024 | C80: 2024-79 | D80: APPROVAL | E80: EVFP | F80: Bio-Based Polyurethene Adhesive System for Coconut Coir Board Production | G80: Kenno Michael M. Uy CEO Lesstics Inc | H80: Cell No.: 0917-162-2127 Email: lesstics@gmail.com | I80: 4551960 | J80: STARTUP | K80: ONGOING
A81: 80 | B81: 2024 | C81: 2024-60 | D81: APPROVAL | E81: EVFP | F81: HOCLOMAC: Product Certification, Inventory, and Sales | G81: Dr. Francis Aldrine A. Uy President and CEO USHER Technologies, Inc. | H81: drfrancisuy@gmail.com | I81: 4143400.5 | J81: STARTUP | K81: ONGOING
A82: 81 | B82: 2024 | C82: 2024-79 | D82: PROMOTION | E82: EVFP | F82: Bio-Based Polyurethene Adhesive System for Coconut Coir Board Production | G82: Kenno Michael M. Uy CEO Lesstics Inc | H82: Cell No.: 0917-162-2127 Email: lesstics@gmail.com | I82: 4551960 | J82: STARTUP | K82: ONGOING | L82: IEIG 2025 / RSTW VIII
A83: 82 | B83: 2024 | C83: 2024-60 | D83: PROMOTION | E83: EVFP | F83: HOCLOMAC: Product Certification, Inventory, and Sales | G83: Dr. Francis Aldrine A. Uy President and CEO USHER Technologies, Inc. | H83: drfrancisuy@gmail.com | I83: 4143400.5 | J83: STARTUP | K83: ONGOING | L83: WoSG, CES 2025, E-MarkET Market Intelligence
A84: 83 | B84: 2024 & 2025 | D84: PROMOTION | E84: EIPRAP | F84: High-resolution 3D Geological Mapping with Ambient Electromagnetic Interferometry | G84: Emmanuel G. Ramos Mark Linus C. Ramos Rodolfo Alfonso R. Sabio | J84: STARTUP | K84: ONGOING | L84: WoSG, E-MarkET Market Intelligence, CES 2025
A85: 84 | B85: 2025 | C85: 2025-18 | D85: APPROVAL | E85: GALING | F85: Magicbag: Wireless slow cooker | G85: Ms. Rowena Faith Armeniana Sucalit 4423 Montojo St. Tejeros, Makati City | H85: weng747@yahoo.com 0916-777-8031 | I85: 229654 | J85: STARTUP | K85: ONGOING
A86: 85 | B86: 2025 | C86: NA | D86: PAC | E86: TECHNICOM | F86: Commercialization and Scaling of Duon’s Real-Time Indoor Navigation with Foot Traffic Behavioral Analysis and Prediction AI | G86: MR. GABRIEL ANTON D. ANGELES, Project Leader DUON TECHNOLOGIES INCORPORATED | H86: gda4993@gmail.com, admin@duon.ph 9773470628 | I86: 7175464 | J86: STARTUP | K86: ONGOING
A87: 86 | B87: 2025 | C87: NA | D87: PAC | E87: TECHNICOM | F87: COMMERCIAL PROTOTYPING OF SMART WATER (IOT) METER (SWIM) | G87: CONRADO D. CAMILON JR, Project Leader ALEXA’S ENGINEERING SERVICES | H87: cdcamilonjr@gmail.com 09224074861/049-501-4583 | I87: 4998689 | J87: STARTUP | K87: ONGOING
A88: 87 | B88: 2025 | C88: NA | D88: PAC | E88: TECHNICOM | F88: Rezbin: Business Model Validation and Market Acceptability Testing for Low Cost AI-powered Bins as an Alternative to Expensive Reverse Vending Machines in Metro Manila | G88: Matthew Cristi C. Martirez, Project Leader Rezbin Waste Technology Inc. | H88: mari@rezbin.ph, hello@rezbin.ph 639178920234 | I88: 4999988 | J88: STARTUP | K88: ONGOING
A89: 88 | B89: 2025 | C89: NA | D89: PAC | E89: TECHNICOM | F89: Technological Improvement and Field Testing of Bamboo-based Biodegradable Period Care | G89: Alexandra B. Jocom, Project Leader BioTerra Corp. (Halia) | H89: alexa@halia.co 639764896618 | I89: 5000000 | J89: STARTUP | K89: ONGOING
A90: 89 | B90: 2025 | C90: NA | D90: PAC | E90: TECHNICOM | F90: Scaling Up and Deployment of the Multi-Drum Chamber Carbonization System for Sustainable Charcoal Production in the Philippines | G90: Julieane M. Fernandez, Project Leader Eco-Uling by Project Lily Inc. | H90: ayafernandez.ecouling@gmail.com 0915-795-1534 | I90: 4884739 | J90: STARTUP | K90: ONGOING
A91: 90 | B91: 2025 | C91: NA | D91: PAC | E91: TECHNICOM | F91: Optimizing Bamboo Processing: 2-IN-1 Furnace For Pole Treatment and Valorization of Silica-Rich Bamboo Ash | G91: Anneth Rigon BAMBOO IMPACT LAB OPC | H91: anneth@bambooimpactlab.com 0919-999-0488 | I91: 4993468 | J91: STARTUP | K91: ONGOING
A92: 91 | B92: 2025 | C92: 2025-29 | D92: APPROVAL | E92: EVFP | F92: Commercialization of GradeChum: An AI-Powered Platform for Automatic Evaluation of Handwritten Activities | G92: MR. JEMAR JUDE A. MARANGA President and CEO CODECHUM SOFTWARE SOLUTIONS INC. | H92: jude@codechum.com 639959469610 | I92: 4500000 | J92: STARTUP | K92: ONGOING
A93: 92 | B93: 2025 | C93: 2025-29 | D93: PROMOTION | E93: EVFP | F93: Commercialization of GradeChum: An AI-Powered Platform for Automatic Evaluation of Handwritten Activities | G93: MR. JEMAR JUDE A. MARANGA President and CEO CODECHUM SOFTWARE SOLUTIONS INC. | H93: jude@codechum.com 639959469610 | I93: 4500000 | J93: STARTUP | K93: ONGOING
A94: 93 | B94: 2025 | C94: NA | D94: PROMOTION | E94: GALING | F94: Magicbag: Wireless slow cooker | G94: Ms. Rowena Faith Armeniana Sucalit 4423 Montojo St. Tejeros, Makati City | H94: weng747@yahoo.com 0916-777-8031 | I94: 229654 | J94: STARTUP | K94: ONGOING | L94: LUNDUYAN KIWIE, Marketing Assistance Program
A95: 94 | B95: 2025 | C95: NA | D95: PROMOTION | E95: TECHNICOM | F95: Commercialization and Scaling of Duon’s Real-Time Indoor Navigation with Foot Traffic Behavioral Analysis and Prediction AI | G95: MR. GABRIEL ANTON D. ANGELES, Project Leader DUON TECHNOLOGIES INCORPORATED | H95: gda4993@gmail.com, admin@duon.ph 9773470628 | I95: 7175464 | J95: STARTUP | K95: ONGOING
A96: 95 | B96: 2025 | C96: NA | D96: PROMOTION | E96: TECHNICOM | F96: COMMERCIAL PROTOTYPING OF SMART WATER (IOT) METER (SWIM) | G96: CONRADO D. CAMILON JR, Project Leader ALEXA’S ENGINEERING SERVICES | H96: cdcamilonjr@gmail.com 09224074861/049-501-4583 | I96: 4998689 | J96: STARTUP | K96: ONGOING | L96: PHILIPPiNEXT
A97: 96 | B97: 2025 | C97: NA | D97: PROMOTION | E97: TECHNICOM | F97: Rezbin: Business Model Validation and Market Acceptability Testing for Low Cost AI-powered Bins as an Alternative to Expensive Reverse Vending Machines in Metro Manila | G97: Matthew Cristi C. Martirez, Project Leader Rezbin Waste Technology Inc. | H97: mari@rezbin.ph, hello@rezbin.ph 639178920234 | I97: 4999988 | J97: STARTUP | K97: ONGOING | L97: PHILIPPiNEXT
A98: 97 | B98: 2025 | C98: NA | D98: PROMOTION | E98: TECHNICOM | F98: Technological Improvement and Field Testing of Bamboo-based Biodegradable Period Care | G98: Alexandra B. Jocom, Project Leader BioTerra Corp. (Halia) | H98: alexa@halia.co 639764896618 | I98: 5000000 | J98: STARTUP | K98: ONGOING
A99: 98 | B99: 2025 | C99: NA | D99: PROMOTION | E99: TECHNICOM | F99: Scaling Up and Deployment of the Multi-Drum Chamber Carbonization System for Sustainable Charcoal Production in the Philippines | G99: Julieane M. Fernandez, Project Leader Eco-Uling by Project Lily Inc. | H99: ayafernandez.ecouling@gmail.com 0915-795-1534 | I99: 4884739 | J99: STARTUP | K99: ONGOING
A100: 99 | B100: 2025 | C100: NA | D100: PROMOTION | E100: TECHNICOM | F100: Optimizing Bamboo Processing: 2-IN-1 Furnace For Pole Treatment and Valorization of Silica-Rich Bamboo Ash | G100: Anneth Rigon BAMBOO IMPACT LAB OPC | H100: anneth@bambooimpactlab.com 0919-999-0488 | I100: 4993468 | J100: STARTUP | K100: ONGOING

Sheet Copy of IDD_STARTUPS
A1: Year | B1: Resolution No: | C1: TYPE | D1: Program | E1: Approval Date | F1: Project Title | G1: Name of Proponent | H1: Address | I1: Contact Details | J1: Amount | K1: CLASS | L1: STATUS | M1: POSSIBLE FOLLOW UP ASSITANCE
A2: 2025 | B2: 2025-18 | C2: APPROVAL | D2: GALING | E2: 2025 | F2: Magicbag: Wireless slow cooker | G2: Ms. Rowena Faith Armeniana Sucalit 4423 Montojo St. Tejeros, Makati City | I2: weng747@yahoo.com 0916-777-8031 | J2: 229654 | K2: STARTUP | L2: ONGOING
A3: 2024 | B3: 2024-89 | C3: APPROVAL | D3: GALING | E3: 45625 | F3: Marissa Turbine: Vertical-Axis Tidal Turbine | G3: Mr. Patrick Roland de Guzman 65 Lawa, Obando, Bulacan | I3: deguzmanpatrickroland@gmail.com 09974916634 | J3: 395212 | K3: STARTUP | L3: ONGOING
A4: 2024 | B4: 2024-36 | C4: APPROVAL | D4: GALING | E4: 45469 | F4: Technology Validation of Unas Canvas (UnVas) | G4: Julienne Fabie-Agapin Lumbia District, Pagadian City | I4: juliennestephanie.agapin@wmsu.edu.ph 09362660139 | J4: 43250 | K4: STARTUP | L4: COMPLETED | M4: Endorsed to NDC
A5: 2024 | B5: 2024-54 | C5: APPROVAL | D5: GALING | E5: 45544 | F5: Technology Validation of IOT Artificial Intelligence-Based Dosing System in Greenhouse | G5: Mr. Alvin Phoebe Artemis A. Valdez Interior Fidelidad Street, Barangay 1, Balayan, Batagas 4213 | I5: alvinphoebeartemis@gmail.com +639918781878; +639916453232 | J5: 236341.77 | K5: STARTUP | L5: ONGOING | M5: Endorsed to NDC
A6: 2023 | B6: 2023-79 | C6: APPROVAL | D6: GALING | E6: 45225 | F6: Improved KoolGear | G6: Mr. Ivan Brent Nara Bldg. 23, UP Bliss, Diliman, Quezon City | I6: naraivanbrent@gmail 09751905598 | J6: 96107 | K6: STARTUP | L6: ONGOING
A7: 2023 | B7: 2023-66 | C7: APPROVAL | D7: GALING | E7: 45154 | F7: Foldable Water Tank with Zeramic Filter | G7: Ms. Eleanor M. Olegario | H7: 17 Cavite Street, Bonifacio Village, Brgy. Pasong Tamo, Quezon City | I7: eleanor.olegario@gmail.com 09209129187 | J7: 191500 | K7: STARTUP | L7: COMPLETED
A8: 2023 | B8: 2023-30 | C8: APPROVAL | D8: GALING | E8: 45086 | F8: Technology Validation of Pili Seal | G8: Engr. Mark Kennedy E. Bantugon | I8: markkennedy09bantugon@gmail.com andpili.adheseal@gmail.com | J8: 349799.56 | K8: STARTUP | L8: ONGOING
A9: 2025 | B9: 2025-17 | C9: APPROVAL | D9: GALING | F9: Fabrication, and Installation of a 50W LED Flood Light Post with Integration of Small-scale Savonius-Type Helical Vertical Axis Wind Turbine (VAWT) and Solar Panel | G9: Engr. Jose Luis L. Villalon | H9: 25 Mercury, Zytek-Riosa, Brgy. Pasong Tamo, Quezon City, 1107 | I9: louie.vdaliinnovations@gmail.com +63 915 126 5571 | J9: 358538 | K9: STARTUP | L9: ONGOING
A10: 2025 | B10: NA | C10: PAC | D10: TECHNICOM | E10: 2025 | F10: Commercialization and Scaling of Duon’s Real-Time Indoor Navigation with Foot Traffic Behavioral Analysis and Prediction AI | G10: MR. GABRIEL ANTON D. ANGELES, Project Leader DUON TECHNOLOGIES INCORPORATED | H10: 7F, Panorama Tower 34th Street, corner Lane A, Taguig, 1634 Metro Manila | I10: gda4993@gmail.com, admin@duon.ph 9773470628 | J10: 7175464 | K10: STARTUP | L10: ONGOING
A11: 2025 | B11: NA | C11: PAC | D11: TECHNICOM | E11: 2025 | F11: COMMERCIAL PROTOTYPING OF SMART WATER (IOT) METER (SWIM) | G11: CONRADO D. CAMILON JR, Project Leader ALEXA’S ENGINEERING SERVICES | I11: cdcamilonjr@gmail.com 09224074861/049-501-4583 | J11: 4998689 | K11: STARTUP | L11: ONGOING
A12: 2025 | B12: NA | C12: PAC | D12: TECHNICOM | E12: 2025 | F12: Rezbin: Business Model Validation and Market Acceptability Testing for Low Cost AI-powered Bins as an Alternative to Expensive Reverse Vending Machines in Metro Manila | G12: Matthew Cristi C. Martirez, Project Leader Rezbin Waste Technology Inc. | I12: mari@rezbin.ph, hello@rezbin.ph 639178920234 | J12: 4999988 | K12: STARTUP | L12: ONGOING | M12: For endorsement to NDC
A13: 2025 | B13: NA | C13: PAC | D13: TECHNICOM | E13: 2025 | F13: Technological Improvement and Field Testing of Bamboo-based Biodegradable Period Care | G13: Alexandra B. Jocom, Project Leader BioTerra Corp. (Halia) | I13: alexa@halia.co 639764896618 | J13: 5000000 | K13: STARTUP | L13: ONGOING
A14: 2025 | B14: NA | C14: PAC | D14: TECHNICOM | E14: 2025 | F14: Scaling Up and Deployment of the Multi-Drum Chamber Carbonization System for Sustainable Charcoal Production in the Philippines | G14: Julieane M. Fernandez, Project Leader Eco-Uling by Project Lily Inc. | I14: ayafernandez.ecouling@gmail.com 0915-795-1534 | J14: 4884739 | K14: STARTUP | L14: ONGOING
A15: 2025 | B15: NA | C15: PAC | D15: TECHNICOM | E15: 2025 | F15: Optimizing Bamboo Processing: 2-IN-1 Furnace For Pole Treatment and Valorization of Silica-Rich Bamboo Ash | G15: Anneth Rigon BAMBOO IMPACT LAB OPC | I15: anneth@bambooimpactlab.com 0919-999-0488 | J15: 4993468 | K15: STARTUP | L15: ONGOING
A16: 2024 | B16: 2024-71 | C16: APPROVAL | D16: TECHNICOM | E16: 45574 | F16: Automated Coconut Sap Extraction: Enhancing Productivity and Quality Through Innovative Technology | G16: Luzmar M. Gabor KASAKA Agriventures, Inc. | I16: asaka@aim.edu 9175305742 | J16: 2998072 | K16: STARTUP | L16: ONGOING | M16: Endorsed to NDC
A17: 2024 | B17: 2024-78 | C17: APPROVAL | D17: TECHNICOM | E17: 45581 | F17: Enhancement and Market Validation of AI-Powered Property Management Solutions for the Philippines | G17: Mr. Jesehl Charles Basco Project Leader Collo/Proprty Technology Solutions Inc. | I17: jay@collo.ph 9178327166 | J17: 2911170 | K17: STARTUP | L17: ONGOING
A18: 2024 | B18: 2024-82 | C18: APPROVAL | D18: TECHNICOM | E18: 45601 | F18: Enhancement, Market Validation, and Pilot Production of AI-Driven Farm Management Module (AID-FMM) | G18: Ms. Lorilyn P. Daquioag Project leader Waste4Good technologies | I18: lurelynpablo@gmail.com lorilyn.daquioag@eee.upd.edu.ph 639385504997 | J18: 2384720 | K18: STARTUP | L18: ONGOING
A19: 2024 | B19: 2024-88 | C19: APPROVAL | D19: TECHNiCOM | E19: 45609 | F19: Improvement and Pilot Testing of Alerto PH AI-as-a-Service (AlaaS) | G19: Ms. Cristina Macaraig WiredField Philippines Inc. | I19: cristina@wiredfield.com | J19: 2975715 | K19: STARTUP | L19: ONGOING
A20: 2024 | B20: 2024-74 | C20: APPROVAL | D20: TECHNICOM | E20: 45574 | F20: Market Testing of Online Residential Rental Marketplace for Filipino Students and Young Professionals | G20: Alyssa Casandra Wee Project Leader/ Krelio Technologies Inc. | I20: alyssa@dormy.ph, hello@dormy.ph 0992 681 6544 | J20: 2999945.7 | K20: STARTUP | L20: ONGOING
A21: 2024 | B21: 2024-27 | C21: APPROVAL | D21: TECHNICOM | E21: 45441 | F21: Pilot Testing and Technology Validation of Fortified Powdered Coconut Milk as a Powdered Dairy Alternative to Lactose Intolerant and Nutrient Deficient Filipino Children and Adults | G21: Samuel Antonius De Chavez Tecuala Dehusk | H21: Martel Bldg. Verdon Parc, Unit 716 Ecoland Drive, Talomo, Bucana, Davao Del Sur, Davao City, 8000 | I21: samuel.tecuala@dehusk.com.ph 09565734432 | J21: 2789556 | K21: STARTUP | L21: ONGOING
A22: 2024 | B22: 2024-31 | C22: APPROVAL | D22: TECHNICOM | E22: 45448 | F22: Scaling up Testing of a Peer-to-Peer Car Sharing Marketplace for the Filipino Car Sharing Economy | G22: Mr. Miguel Locsin Project Leader DOON Transport Technologies Inc. | H22: Unit 302, 5048 P. Burgos Street, Draper Startup House for Entrepreneurs, Brgy. Poblacion, Makati City, Fourth District, NCR 1210 / | I22: miguel@doon.ph 09178076499 | J22: 2896644 | K22: STARTUP | L22: ONGOING
A23: 2024 | B23: 2024-26 | C23: APPROVAL | D23: TECHNICOM | E23: 45441 | F23: The Scrapcycle PH field and Market Testing of Scrap Trading Dynamics Across Philippine Urban Landscapes | G23: Genevieve P. Navales/Female Project Leader, ScrapCycle PH | I23: vievenavales29@gmail.com 09952033203 | J23: 2785599 | K23: STARTUP | L23: ONGOING
A24: 2023 | B24: 2023-81 | C24: APPROVAL | D24: TECHNICOM | E24: 45225 | F24: Technology and business validation of an advanced web and mobile Point-of-Sale (POS) software-as-a-service (SAAS) application for Philippine micro and small retail businesses | G24: Renzo Navarro Ducusin Project Leader IOL, Inc. | H24: Rm 404 Jose Miguel Bldg. Yandoc St., Baguio City. Philippines | I24: kevin@iolph.com 074-6209538 | J24: 2715682.8 | K24: STARTUP | L24: ONGOING
A25: 2023 | B25: 2023-83 | C25: APPROVAL | D25: TECHNICOM | E25: 45236 | F25: Determining the Pesticide Residue Level of Mangoes using a smart metal oxide nanosensor for Post-Harvest Applications | G25: Ms. Normie Jean Sajor Lacubtan Project Leader | I25: njsajor@gmail.com f.normiejean.lacubtan@cmu.edu.ph | J25: 2398683 | K25: STARTUP | L25: ONGOING
A26: 2023 | B26: PAC | C26: APPROVAL | D26: TECHNICOM | E26: 45275 | F26: Scaling Digital Clustering Solution for Enhanced Agri-Value Chain Integration of Farm Konek | G26: John Vincent Q. Gastanes Project Zacchaeus Marketing Cooperative | H26: Unit 1, CCT Building, Puerto Princesa City, Palawan, 5300/ MIMAROPA | I26: gastanesjohnvincent@gmail.com 639177979073 | J26: 7936800 | K26: STARTUP | L26: ONGOING
A27: 2022 | C27: PAC | D27: TECHNICOM | F27: Commercialization of the 4Gives System | G27: Mr. Varian Sherwin Chu Vashcorp, Inc. | I27: varianchu@gmail.com | J27: 5867730.2 | K27: STARTUP | L27: ONGOING | M27: EVFP
A28: 2019 | B28: NA | C28: PAC | D28: TECHNICOM 1.0 | F28: Product Design, Manufacturing and Field Scale Testing of StillFresh: Spoilage Monitoring Strip | G28: Mr. Joseph Christopher G. Doroja | I28: joseph.doroja@obf.ateneo.edu, etinhay@gmail.com | J28: 1636971 | K28: STARTUP
A29: 2019 | B29: NA | C29: PAC | D29: TECHNICOM 1.0 | F29: Integration of Data Science and Scaling Up of Payruler, a comprehensive Human Resource Management System (HRMS) | G29: Mr. Warlito Pio S. De Jesus | I29: jojo@geniihut.com, jojo@payruler.com, timmy@geniihut.com, timmy@payruler.com | J29: 3258768 | K29: STARTUP
A30: 2019 | B30: NA | C30: PAC | D30: TECHNICOM 1.0 | F30: Optimization of Virtual Reality Kit (VR Kit) for New Media Technology and Commercial Competitiveness | G30: Mr. Ryan Tan Yu | I30: ryan@mataverse.ph | J30: 4019382 | K30: STARTUP
A31: 2019 | B31: NA | C31: PAC | D31: TECHNICOM 1.0 | F31: Enhancement of the Micab Cab Hailing Engine thru Big Data Analytics | G31: Mr. Kenneth Baylosis | J31: 3135851.2 | K31: STARTUP
A32: 2019 | B32: NA | C32: PAC | D32: TECHNICOM 1.0 | F32: Scale-up Manufacturing of Biotek-M Diagnostic Kits and Post Marketing for Third Party Evaluation | G32: Dr. Raul V. Destura Denise Lacuna | I32: rvdestura@up.edu.ph jadelacuna12@gmail.com | J32: 16926594 | K32: STARTUP
A33: 2019 | B33: NA | C33: PAC | D33: TECHNICOM 1.0 | F33: Technology Enhancement and Commercialization of Exora Intellex as an Energy Analytics Machine Learning Platform for Industrial Smart Energy Management and Electricity Cost Reduction | G33: Mr. Sergius Angelo Santos Exora Technologies, Inc. | I33: sergius@exora.ph | J33: 4394800 | K33: STARTUP
A34: 2018 | B34: NA | C34: PAC | D34: TECHNICOM 1.0 | F34: Optimization of an Industry Grade Prototype of Po Lite Products | G34: Dr. Ria Liza Canlas | I34: riadear21@yahoo.com | J34: 4999045 | K34: STARTUP
A35: 2018 | B35: NA | C35: PAC | D35: TECHNICOM 1.0 | F35: Pilot Testing of a Deepwater Operation 3D Visual Mapping and Inspection System (PD-DOMAINS) | G35: Mr. Francis James Corpuz ANTIPARA Exploration Inc. | I35: franciscorpuz@gmail.com | J35: 3058155.2 | K35: STARTUP
A36: 2018 | B36: NA | C36: PAC | D36: TECHNICOM 1.0 | F36: Development of an Alternative Credit Scoring Model applying Machine Learning in Financing Farmers | G36: Mr. Ruel T. Amparo Cropital Enterprises Corporation | I36: ruel@cropital.com | J36: 3551018 | K36: STARTUP
A37: 2017 | B37: NA | C37: PAC | D37: TECHNICOM 1.0 | F37: Enhancement of Prototype and Market Readiness of R-TAP (an advanced pressure management system for water utilities) | G37: Mr. Stephen Larcia Hiraya Technology Solutions, Inc. | I37: stephen@hirayatech.ai; info@hirayatech.ai (02) 8826 6836 | J37: 4294326.4 | K37: STARTUP
A38: 2017 | B38: NA | C38: PAC | D38: TECHNICOM 1.0 | F38: Field Testing and Technology Validation of the E-Procurement Sytem (ePS) for Government Agencies | G38: Engr. Jose Rizaldy G. Harder Infodynamics Technologies | I38: (033) 321 0928 rizaldyharder@yahoo.com | J38: 1892235 | K38: STARTUP
A39: 2016 | B39: NA | C39: PAC | D39: TECHNICOM 1.0 | F39: Cost Efficient and High Quality Accelerograph for Disaster Preparedness in Buildings | G39: Mr. Rodolfo Alfonso (Ryan) Sabio Tekton Geometrix, Inc. | I39: 437-7001/ 0915 256 3355 | J39: 4736242.4 | K39: STARTUP
A40: 2025 | B40: NA | C40: NA | D40: EIPRAP | F40: Enhancement, Market Validation and Pilot Production of AI-Driven Farm Management Module (AID-FMM) | G40: Waste4good Research and Experimental Development in Engineering and Technology | I40: lurelynpablo@gmail.com lorilyn.daquioag@eee.upd.edu.ph 639385504997 | K40: STARTUP
A41: 2025 | B41: NA | C41: NA | D41: EIPRAP | F41: High-resolution 3D Geological Mapping with Ambient Electromagnetic Interferometry | G41: Emmanuel G. Ramos Mark Linus C. Ramos Rodolfo Alfonso R. Sabio | K41: STARTUP
A42: 2025 | B42: NA | C42: NA | D42: EIPRAP | F42: A System and Method for Managing Healthcare Services and Networks | G42: SeeYouDoc Corporation | I42: noel@seeyoudoc.com | K42: STARTUP
A43: 2021 | B43: 2021-46 | C43: APPROVAL | D43: IBED | F43: PIlot Scale Production of Cooked Balut in Shell with Commercially Acceptable Shelf-life for Feasibility and Marketing Testing | G43: Ambrocio Kerwin A. Perez | H43: 349800 | I43: - | J43: 349800 | K43: STARTUP
A44: 2020 | B44: 2020-07-memo | C44: APPROVAL | D44: IBED | F44: Pilot Production of " Snap On and Off Handle for a Five-Gallon Bottle Container" | G44: Mr. Carlos N. Detalo Jr. | H44: 409314 | I44: - | J44: 409314 | K44: STARTUP
A45: 2018 | D45: IPRAP | F45: Bicycle Frame with Wheel Size Adaptable Geometry | G45: Rurok Industries | I45: -
A46: 2019 | D46: IPRAP | F46: Biologically Active Plant Extracts as Dietary Supplements | G46: Pascual Laboratories, Inc. | I46: -
A47: 2020 | D47: IPRAP | F47: Standardized Tawa-tawa Capsule | G47: Herbanext Laboratories, Inc. | I47: -
A48: 2020 | D48: IPRAP | F48: Composition Of Herbal Medicine | G48: Pharmalytics Corporation | I48: -
A49: 2020 | D49: IPRAP | F49: Wall Garden | G49: Dok Alternatibo Brotherhood with Inventors Guild Consumers Cooperative (DABIGCCO) | I49: -
A50: 2020 | D50: IPRAP | F50: Sanisafe Disinfection System | G50: Sanisafe Utility Projects Construction | I50: -
A51: 2021 | D51: IPRAP | F51: TELLA | G51: Joeus Event Supplies Corporation | I51: -
A52: 2024 | D52: IPRAP | F52: E VitalBotApp Vital Signs Monitoring and Medicine Kit Robot with Mobile Application | G52: Erovoutika Enterprises | I52: -
A53: 2025 | D53: IPRAP | F53: A System and Method for Managing Healthcare Services and Networks (NPE - South Korea) | G53: SeeYouDoc Corporation | I53: noel@seeyoudoc.com | K53: STARTUP
A54: 2025 | D54: IPRAP | F54: System and Method for Secure Disbursement of Loans and Income-Based Advances with Biometric Consent and Configurable Repayment Orchestration | G54: Vashcorp Inc. | I54: varianchu@gmail.com | K54: STARTUP
A55: 2025 | D55: IPRAP | F55: The Process Of Making An AI-Driven Farm Management Module And Agricultural Monitoring System (NPE - Japan) | G55: Waste4Good Technologies a.k.a. GreenVisionsPh | I55: mari@rezbin.ph, hello@rezbin.ph 639178920234 | K55: STARTUP

Sheet IDD-Projects (2018-2025)
A1: Year | B1: Resolution No: | C1: Type | D1: Program | E1: Project Title | F1: Name of Proponent | G1: Amount of Investment
A2: 2025 | B2: 45901 | C2: APPROVAL | D2: GALING | E2: Flamethrower Device As Insects, Pests, Diseases, And Weed Controller | F2: MR. PHILIP G. CHAN 13 Rimando Road, Baguio City philipchan5762@gmail.com 09854791420 | G2: 81439.68
A3: 2025 | B3: 45931 | C3: APPROVAL | D3: ISP | E3: Invent School™ Program Seminar-Workshop for High School Students of Allen National High School | F3: Allen National High School, Allen Northern Samar | G3: 110000
A4: 2025 | B4: 45962 | C4: APPROVAL | D4: ISP | E4: Invent School™ Program Seminar-Workshop for Elementary Pupils of Paaralang Sentral ng Talaga | F4: DepEd City Schools Division of Tanuan | G4: 21000
A5: 2025 | B5: 2025-17 | C5: APPROVAL | D5: GALING | E5: Fabrication, and Installation of a 50W LED Flood Light Post with Integration of Small-scale Savonius-Type Helical Vertical Axis Wind Turbine (VAWT) and Solar Panel | F5: Engr. Jose Luis L. Villalon 25 Mercury, Zytek-Riosa, Brgy. Pasong Tamo, Quezon City, 1107 louie.vdaliinnovations@gmail.com +63 915 126 5571 | G5: 358538 | H5: STARTUP
A6: 2025 | B6: 2025-18 | C6: APPROVAL | D6: GALING | E6: Magicbag: Wireless slow cooker | F6: Ms. Rowena Faith Armeniana Sucalit 4423 Montojo St. Tejeros, Makati City weng747@yahoo.com 0916-777-8031 | G6: 229654 | H6: STARTUP
A7: 2025 | B7: 2025-19 | C7: APPROVAL | D7: ISP | E7: Invent School™ Program Seminar-Workshop for Grade 11 Students from De La Salle University- Dasmariñas High School | F7: De La Salle University- Dasmariñas High School | G7: 75000
A8: 2025 | B8: 2025-20 | C8: APPROVAL | D8: ISP | E8: Invent School™ Program Seminar-Workshop: DBTI Computer Society & EE-nnovators Club Members | F8: Don Bosco Technical Institute of Makati | G8: 65000
A9: 2025 | B9: 2025-21 | C9: APPROVAL | D9: ISP | E9: Invent School™ Program Seminar-Workshop for BaliwagHenyo Innovators | F9: BALHCEI Baliwag South Central School | G9: 75000
A10: 2025 | B10: 2025-26 | C10: APPROVAL | D10: GALING | E10: Market Validation of the Improved Cocoon and Other Materials Dryer | F10: First Road, Benin Lot 5, Pinsao Proper, Baguio City fiscar.cordillera@gmail.com 09065740108 | G10: 263282.5
A11: 2025 | B11: 2025-31 | C11: APPROVAL | D11: eIPRAP | E11: Internationally - Secured Patents for ASTI's Readiness on Commercialization (i-SPARC) 2025 | F11: DOST-ASTI | G11: 4990000
A12: 2025 | B12: 2025-32 | C12: APPROVAL | D12: GALING | E12: Technology Validation of Lapan Pork Sausage | F12: Dr. Marielle S. Dizon | G12: 197490.2
A13: 2024 | B13: 45444 | C13: APPROVAL | D13: ISP | E13: INVENT SCHOOL PROGRAM SEMINAR-WORKSHOP FOR COLLEGE STUDENTS IN SAINT LOUIS UNIVERSITY-MAIN CAMPUS,BAGUIO CITY ON JANUARY 27, 2024 | F13: SAIN LOUIS UNIVERSITY, BAGUIO CITY,BENGUET | G13: 18900
A14: 2024 | B14: 45505 | C14: APPROVAL | D14: ISP | E14: INVENT SHCOOL PROGRAM SEMINAR FOR COLLEGE STUDENTS IN CENTRAL MINDANAO UNIVERSITY (CMU)-MUSUAN, MARAMAG,BUKIDNON | F14: COLLEGE STUDENT IN CENTRAL MINDANAO UNIVERSITY(CMu) | G14: 122000
A15: 2024 | B15: 45536 | C15: APPROVAL | D15: ISP | E15: INVENT SCHOOL PROGRAM SEMINAR FOR JUNIOR AND SENIOR HIGH SCHOOL STUDENT OF IMUS INSTITUTE OF SCIENCE AND TECHNOLOGY AT IMUS CAVITE | F15: IMUS INSTITUTE OF SCIENCE AND TECHNOLOGY(IIST) | G15: 8000
A16: 2024 | B16: 45566 | C16: APPROVAL | D16: GALING | E16: TECHNOLOGY VALIDATION OF PORTABLE ABACA FIBER STRIPPING MACHINE | F16: MR. RAMON T. MANLOLO | G16: 227925
A17: 2024 | B17: 45597 | C17: APPROVAL | D17: ISP | E17: Invent School Program Seminar for College Students in the Selected Province of Pampanga | F17: DOST III PSTO-Pampanga | G17: 77500
A18: 2024 | B18: 45627 | C18: APPROVAL | D18: ISP | E18: Invent School Program Seminar-Workshop High School Level for Bolbok Integrated National High School | F18: DOST PSTO-BATANGAS | G18: 51300
A19: 2024 | B19: 2024-14 | C19: APPROVAL | D19: GALING | E19: Improved Cocoon and Other Materials Drye | F19: MR. GLEN M. PORTUGAL First Road, Benin Lot 5, Pinsao Proper, Baguio City 09065740108 fiscar.cordillera@gmail.com | G19: 32252
A20: 2024 | B20: 2024-16 | C20: APPROVAL | D20: ISP | E20: Invent School Program Seminar for College Students of Marikina Polytechnic College | F20: Marikina Polytechnic College | G20: 60000
A21: 2024 | B21: 2024-17 | C21: APPROVAL | D21: GALING | E21: Technology Validation of Carrot Smoothies with Blue Ternate Flower Infusion - GALING Program | F21: MS. LINA T. CODILLA B3, L5, Alta Tierra, Napolan, Pagadian City, Zamboanga Del Sur 09460668556 ltcodilla2018@gmail.com | G21: 71385
A22: 2024 | B22: 2024-21 | C22: APPROVAL | D22: ISP | E22: ISP in Eastern Samar | F22: Eastern Samar State University | G22: 76000
A23: 2024 | B23: 2024-22 | C23: APPROVAL | D23: ISP | E23: Invent School Program - Palawan | F23: Schools Division of Puerto Princesa City -Puerto Princesa City National Science High Schoolversity | G23: 111000
A24: 2024 | B24: 2024-36 | C24: APPROVAL | D24: GALING | E24: Technology Validation of Unas Canvas (UnVas) | F24: Julienne Fabie-Agapin Lumbia District, Pagadian City juliennestephanie.agapin@wmsu.edu.ph 09362660139 | G24: 43250 | H24: STARTUP
A25: 2024 | B25: 2024-42 | C25: APPROVAL | D25: ISP | E25: Invent School Program Seminar-Workshop for Selected Junior and Senior High School Students of Ateneo de Davao University | F25: Ateneo de Davao University-School of Engineering and Architecture | G25: 112800
A26: 2024 | B26: 2024-53 | C26: APPROVAL | D26: GALING | E26: Technology Validation of USB Port with Mounting Holder | F26: Mr. Alphy C. Ferraren Purok 4, Brgy.Gumaga, Libungan, North Cotabato bukid_31@yahoo.com 0970895069 | G26: 57667.56
A27: 2024 | B27: 2024-54 | C27: APPROVAL | D27: GALING | E27: Technology Validation of IOT Artificial Intelligence-Based Dosing System in Greenhouse | F27: Mr. Alvin Phoebe Artemis A. Valdez Interior Fidelidad Street, Barangay 1, Balayan, Batagas 4213 alvinphoebeartemis@gmail.com +639918781878; +639916453232 | G27: 236341.77 | H27: STARTUP
A28: 2024 | B28: 2024-55 | C28: APPROVAL | D28: Concept Proto | E28: Composing Machine with Rotary mixer | F28: Ms. Angelica A. Marcelino Topdac, Atok, Benguet 09384034199 angelicamarcelino49@gmail.com | G28: 186495.06
A29: 2024 | B29: 2024-56 | C29: APPROVAL | D29: Concept Proto | E29: Automated Air-reversible Agricultural Commodities Dryer | F29: Mr. Melvin B. Luteb Ampucao, Itogon, Benguet 09207160534/09926860643 luteb.melvin03@gmail.com | G29: 197182.36
A30: 2024 | B30: 2024-30 | C30: APPROVAL | D30: TECHNICOM | E30: Prototype Enhancement and Testing of Village-level Sago Pith Extracting Machine | F30: Engr. Aljon E. Bocobo Caraga State University | G30: 2344480 | H30: STARTUP
A31: 2024 | B31: 2024-71 | C31: APPROVAL | D31: TECHNICOM | E31: Automated Coconut Sap Extraction: Enhancing Productivity and Quality Through Innovative Technology | F31: Luzmar M. Gabor KASAKA Agriventures, Inc. | G31: 2998072 | H31: STARTUP
A32: 2024 | B32: 2024-78 | C32: APPROVAL | D32: TECHNICOM | E32: Enhancement and Market Validation of AI-Powered Property Management Solutions for the Philippines | F32: Mr. Jesehl Charles Basco Project Leader Collo/Proprty Technology Solutions Inc. | G32: 2911170 | H32: STARTUP
A33: 2024 | B33: 2024-63 | C33: APPROVAL | D33: ISP | E33: Invent School Program Seminar-Workshop for Elementary Pupils and Highschool Students in the Eastern Zone of Ilocos Norte | F33: DOST Regional Office I | G33: 119250
A34: 2024 | B34: 2024-64 | C34: APPROVAL | D34: GALING | E34: Technology Validation of Motorized Multi-Purpose Grater and Shredder | F34: Mr. Johnny D. Banez | G34: 105791
A35: 2024 | B35: 2024-82 | C35: APPROVAL | D35: TECHNICOM | E35: Enhancement, Market Validation, and Pilot Production of AI-Driven Farm Management Module (AID-FMM) | F35: Ms. Lorilyn P. Daquioag Project leader Waste4Good technologies | G35: 2384720 | H35: STARTUP
A36: 2024 | B36: 2024-38 | C36: APPROVAL | D36: TECHNICOM | E36: Field Testing and Market Validation of Cost-Efficient Solar-Power Navigating Paddle Wheel Aerotor System for Grow Out Farming | F36: JONELLE H. TABLADA / Male SOUTHEASTERN LEYTE STATEUNIVERSITY | G36: 2715984
A37: 2024 | B37: 2024-88 | C37: APPROVAL | D37: TECHNiCOM | E37: Improvement and Pilot Testing of Alerto PH AI-as-a-Service (AlaaS) | F37: Ms. Cristina Macaraig WiredField Philippines Inc. | G37: 2975715 | H37: STARTUP
A38: 2024 | B38: 2024-72 | C38: APPROVAL | D38: GALING | E38: Technology Validation of Ship Anti-piracy Fence Apparatus” of Mr. Nestor V. Buencido | F38: MR. NESTOR V. BUENCIDO
A39: 2024 | B39: 2024-74 | C39: APPROVAL | D39: TECHNICOM | E39: Market Testing of Online Residential Rental Marketplace for Filipino Students and Young Professionals | F39: Alyssa Casandra Wee Project Leader/ Krelio Technologies Inc. | G39: 2999945.7 | H39: STARTUP
A40: 2024 | B40: 2024-75 | C40: APPROVAL | D40: EIPRAP | E40: Cross-Border IP: Global IP Assessment and Filing in Forest Products Research and Development Institute (FPRDI) | F40: DOST-FPRDI | G40: 4180264
A41: 2024 | B41: 2024-76 | C41: APPROVAL | D41: ISP | E41: Invent School Program Seminar-Workshop for Grades 9-11 Students of Minuyan, Norzagaray, Bulacan | F41: Minuyan National High School | G41: 231162.5
A42: 2024 | B42: 2024-77 | C42: APPROVAL | D42: ISP | E42: Invent School Program Seminar-Workshop for Senior High School Students of Basud National High School | F42: Basud National High School | G42: 36000
A43: 2024 | B43: 2024-27 | C43: APPROVAL | D43: TECHNICOM | E43: Pilot Testing and Technology Validation of Fortified Powdered Coconut Milk as a Powdered Dairy Alternative to Lactose Intolerant and Nutrient Deficient Filipino Children and Adults | F43: Samuel Antonius De Chavez Tecuala Dehusk | G43: 2789556 | H43: STARTUP
A44: 2024 | B44: 2024-31 | C44: APPROVAL | D44: TECHNICOM | E44: Scaling up Testing of a Peer-to-Peer Car Sharing Marketplace for the Filipino Car Sharing Economy | F44: Mr. Miguel Locsin Project Leader DOON Transport Technologies Inc. | G44: 2896644 | H44: STARTUP
A45: 2024 | B45: 2024-26 | C45: APPROVAL | D45: TECHNICOM | E45: The Scrapcycle PH field and Market Testing of Scrap Trading Dynamics Across Philippine Urban Landscapes | F45: Genevieve P. Navales/Female Project Leader, ScrapCycle PH 09952033203 | G45: 2785599 | H45: STARTUP
A46: 2024 | B46: 2024-83 | C46: APPROVAL | D46: ISP | E46: Invent School Program Seminar-Workshop for Selected BSIT and BSECE Students of University of Makati | F46: University of Makati - College of Computing and Information Services | G46: 115435
A47: 2024 | B47: 2024-89 | C47: APPROVAL | D47: GALING | E47: Marissa Turbine: Vertical-Axis Tidal Turbine | F47: Mr. Patrick Roland de Guzman | G47: 395212 | H47: STARTUP
A48: 2023 | B48: 2023-17 | C48: APPROVAL | D48: ISP | E48: ISP Seminar-Workshop for Highschool Students in Romblon | F48: DOST IV-B | G48: 101820 | H48: STARTUP
A49: 2023 | B49: 2023-18 | C49: APPROVAL | D49: ISP | E49: ISP Seminar-Workshop for High School Students and Elementary Students in Rapu-rapu, Albay | F49: DOST V | G49: 134575
A50: 2023 | B50: 2023-19 | C50: APPROVAL | D50: ISP | E50: Invent School Program Seminar-Workshop for High School and Elementary Students in the North Zone of Ilocos Norte | F50: DOST I
A51: 2023 | B51: 2023-21 | C51: APPROVAL | D51: ISP | E51: Invent School Program Seminar-Workshop for Elementary, High School and College Students in Masbate: Webinar Edition | F51: DOST V | G51: 26000
A52: 2023 | B52: 2023-28 | C52: APPROVAL | D52: GALING | E52: Market Validation of Heat Retaining Bag | F52: Ms. Rowena Faith A. Sucalit | G52: 185078
A53: 2023 | B53: 2023-29 | C53: APPROVAL | D53: GALING | E53: Innovation support for Pre-commercialization of Abaca Fiber Tiles: a locally developed product utilizing Abaca wastes | F53: Mr. Jay F. Sanchez | G53: 51292
A54: 2023 | B54: 2023-30 | C54: APPROVAL | D54: GALING | E54: Technology Validation of Pili Seal | F54: Engr. Mark Kennedy E. Bantugon | G54: 349799.56 | H54: STARTUP
A55: 2023 | B55: 2023-32 | C55: APPROVAL | D55: GALING | E55: Nano Foldable Crutch | F55: Mr. James Bryan Camacho | G55: 218000
A56: 2023 | B56: 2023-33 | C56: APPROVAL | D56: GALING | E56: Motorized Multi-Purpose Machine for Grater and Shredder | F56: Mr. Johnny Bañez | G56: 35620
A57: 2023 | B57: 2023-34 | C57: APPROVAL | D57: GALING | E57: Pilot scale production of unVAS (unas Canvas) | F57: Ms. Julienne Stephanie Fabie-Agapin | G57: 55730
A58: 2023 | B58: 2023-35 | C58: APPROVAL | D58: GALING | E58: An Improved Belt Conveyor | F58: Mr. Luder R. Zarate | G58: 99750
A59: 2023 | B59: 2023-36 | C59: APPROVAL | D59: GALING | E59: Unscreened Hammer Mill for Dried Root Crops | F59: Ms. Cynthia Zarate | G59: 94750
A60: 2023 | B60: 2023-37 | C60: APPROVAL | D60: TECHNICOM | E60: ParallaxEd: A Commecial-ready Prototype of an Engineering Simulation System using Mixed Reality | F60: Dr. Albertson De Chavez Amante Batangas State University | G60: 2518284
A61: 2023 | B61: 2023-40 | C61: APPROVAL | D61: Concept Proto | E61: Vortex Enhance Marine Propulsion | F61: Engr. El Arby Eledia | G61: 66200
A62: 2023 | B62: 2023-41 | C62: APPROVAL | D62: GALING | E62: Market validation and packaging of Organic Coffee | F62: Ms. Nanette D. Bilbao | G62: 142051
A63: 2023 | B63: 2023-42 | C63: APPROVAL | D63: GALING | E63: Machine for Collecting and Bagging of Rice Grains | F63: Mr. Orlie D. Panes | G63: 79200
A64: 2023 | B64: 2023-43 | C64: APPROVAL | D64: GALING | E64: Channel Multiplier Remote Control System – Prototype 3 | F64: Mr. Gibsonjis Rosales | G64: 170921.5
A65: 2023 | B65: 2023-44 | C65: APPROVAL | D65: GALING | E65: Greenleaf Essential Oils Formulation | F65: Mr. Jose Ingles | G65: 96088.5
A66: 2023 | B66: 2023-46 | C66: APPROVAL | D66: TECHNICOM | E66: Fabrication of a Commercial-ready Prototype of the Collapsible Solar Power Station for Farms | F66: Dr. Anton Louise de Ocampo Batangas State University | G66: 2743807.5
... A69: 2023 | B69: 2023-64 | C69: APPROVAL | D69: GALING | E69: Lanasug Cooking Oil | F69: Mr. Al-Anni A. Asgali | G69: 93350
A70: 2023 | B70: 2023-66 | C70: APPROVAL | D70: GALING | E70: Foldable Water Tank with Zeramic Filter | F70: Ms. Eleanor M. Olegario | G70: 191500 | H70: STARTUP
A71: 2023 | B71: 2023-67 | C71: APPROVAL | D71: GALING | E71: Refinement of EOS Juego De Tactica Board Game | F71: Mr. Rodney I. Ebrole | G71: 24450
A72: 2023 | B72: 2023-70 | C72: APPROVAL | D72: GALING | E72: Pastillas Tart with Squash Powder | F72: Ms. Ma. Monette DR. Tugay | G72: 104239
A73: 2023 | B73: 2023-71 | C73: APPROVAL | D73: Concept Proto | E73: Development of a Non-Biological Wastewater Treatment System for Efficient and Sustainable Water Reuse | F73: Mr. Rene Francis Dimalanta | G73: 162240
A74: 2023 | B74: 2023-72 | C74: APPROVAL | D74: ISP | E74: Invent School Seminar-Workshop for Elementary and High School Students from selected schools in Ormoc City, Leyte | F74: DOST-VIII | G74: 68450
A75: 2023 | B75: 2023-79 | C75: APPROVAL | D75: GALING | E75: Improved KoolGear | F75: Mr. Ivan Brent Nara | G75: 96107 | H75: STARTUP
A76: 2023 | B76: 2023-81 | C76: APPROVAL | D76: TECHNICOM | E76: Technology and business validation of an advanced web and mobile Point-of-Sale (POS) software-as-a-service (SAAS) application for Philippine micro and small retail businesses | F76: IOL Inc. | G76: 2715682.8 | H76: STARTUP
A77: 2023 | B77: 2023-83 | C77: APPROVAL | D77: TECHNICOM | E77: Determining the Pesticide Residue Level of Mangoes using a smart metal oxide nanosensor for Post-Harvest Applications | F77: Ms. Normie Jean Sajor Lacubtan Project Leader | G77: 2398683 | H77: STARTUP
A78: 2023 | C78: APPROVAL | D78: TECHNICOM | E78: Scaling Digital Clustering Solution for Enhanced Agri-Value Chain Integration of Farm Konek | G78: 7936800 | H78: STARTUP
A79: 2023 | C79: APPROVAL | D79: TECHNICOM | E79: Technology and business validation of an advanced web and mobile Point-of-Sale (POS) software-as-a-service (SAAS) application for Philippine micro and small retail businesses | G79: 2999996.3 | H79: STARTUP
A80: 2022 | B80: 44866 | C80: APPROVAL | D80: ISP | E80: 1. Webinar -Workshop on Intellectual Property and Innovation for Selected Grade 4-6 Pupils in San Isidro, Davao Oriental 2. Creativity Boost and Intellectual Property Basics For Selected High School Pupils in Davao Oriental 3. Creativity Boost and Intellectual Property Basics for Selected DORSU Students | F80: DOST Region XI | G80: 19000
A81: 2022 | B81: 44896 | C81: APPROVAL | D81: IP | E81: DOST-TAPI's Promotional Collaterals | F81: DOST-TAPI | G81: 345000
A82: 2022 | B82: 2022-100 | C82: APPROVAL | D82: TECHNICOM | E82: Pre-Commercialization of IOT-Based Monitoring System for Machine Shop | F82: Mr. Franz Joseph D. Libao | G82: 2353196
A83: 2022 | B83: 2022-16 | C83: APPROVAL | D83: ISP | E83: Invent School Program: Webinar Workshop for Selected Grade 5 and 6 Pupils in the 5 (Five) Provinces of Region II | F83: DOST Region II | G83: 20000
A84: 2022 | B84: 2022-17 | C84: APPROVAL | D84: IBED | E84: Pilot Production of Simplified Compact Tire Inventer Machine (1/2021/050414 | F84: Engr. Lester A. Quimpo | G84: 300700
A85: 2022 | B85: 2022-103 | C85: APPROVAL | D85: TESTING | E85: Adaptive Foldable Crutches (2-2017-001074) | F85: Mr. James Byran B. Camacho | G85: 17575
A86: 2022 | B86: 2022-104 | C86: APPROVAL | D86: TECHNICOM | E86: BTC Lab Kit: A Classroom Friendly Tissue Culture System for Instruction in Life Science course in Senior High School | F86: Dr. Carmen Lagman | G86: 2802604
A87: 2022 | B87: 2022-105 | C87: APPROVAL | D87: TECHNICOM | E87: Pre-commercialization of Low-Cost Phototherapy Light System | F87: Mr. Paul M. Cabacungan | G87: 2692520
A88: 2022 | B88: 2022-106 | C88: APPROVAL | D88: TECHNICOM | E88: Engineered Water Hyacinth Fiber Laminated Panel as Decorative Home Divider | F88: Ms. Yolanda A. Santorcas | G88: 1450894
A89: 2022 | B89: 2022-107 | C89: APPROVAL | D89: TECHNICOM | E89: Scale-up and Market Validation of Automated Industrial-type Compression Molding Machine for Bamboo Composite Products | F89: Engr. Dan William C. Martinez | G89: 1780736
A90: 2022 | B90: 2022-108 | C90: APPROVAL | D90: TECHNICOM | E90: Scaled-up Production and Technology Validation of DOST-ITDI's Ready-to-Eat Quail Eggs | F90: Ma. Bettina A. Macaraeg | G90: 2995096
A91: 2022 | B91: 2022-13 | C91: APPROVAL | D91: IP | E91: DOST-TAPI's Promotional Activities and Materials | F91: DOST-TAPI | G91: 1201148.9
A92: 2022 | B92: 2022-23 | C92: APPROVAL | D92: ISP | E92: Invention School Program: Webinar-Workshop for Primary to Tertiary Level in Different Provinces of BARMM | F92: Ministry of Science and Technology (MOST)-BARMM | G92: 38400
A93: 2022 | B93: 2022-31 | C93: APPROVAL | D93: ISP | E93: Support for the Development of Online Platform for Health Innovations through DOST-TAPI's ISP featuring Health Innovations | F93: IDD | G93: 419537.6
... A122: 2022 | B122: Approved by PAC | C122: APPROVAL | D122: TECHNICOM | E122: HR Lite | F122: Paul John M. Serrano,DOST-AST | G122: 4161535.6
A123: 2021 | B123: 44197 | C123: APPROVAL | D123: SC FOR RA7459 | E123: Operationalization of the screening committee for R.A no. 7459 | F123: Invention Development Division Technology Application and Promotion Institute | G123: 414900
A124: 2021 | B124: 44531 | C124: APPROVAL | D124: Concept Proto | E124: Collapsible Custom Built Modular Automatic Fruiting Cabinet (AUTOMUSHCAB) | F124: Ms. Fransicso J. Diaz | G124: 50735
A125: 2021 | B125: 2021-24 | C125: APPROVAL | D125: ISP | E125: Invent School Program Seminar-Workshop for Flora National Highschool Students-Webinar Edition | F125: DOST-CAR | G125: 9000
A126: 2021 | B126: 2021-25 | C126: APPROVAL | D126: ISP | E126: Invent School Program Seminar-Workshop: Webinar Edition for Elementary Pupils and Highschool Students In Masbate | F126: DOST Region V | G126: 20000
A127: 2021 | B127: 2021-28 | C127: APPROVAL | D127: TESTING | E127: An Obtain Aratiles Fruit Juice (1-2021-050167) | F127: Cageo D. Borongoy | G127: 28450
A128: 2021 | B128: 2021-29 | C128: APPROVAL | D128: IBED-I | E128: PIlot Production of "JERICHORD: A Three-Stringed Instrument" (UM 2-2019-000800 and ID 3-2019-00531 | F128: Jericho V. Castro | G128: 222750
A129: 2021 | B129: 2021-33 | C129: APPROVAL | D129: ISP | E129: Invent School Program: Webinar Edition For Elemntary Pupils in Davao Occidental | F129: DOST Region XI | G129: 8000
A130: 2021 | B130: 2021-34 | C130: APPROVAL | D130: TESTING | E130: A Compact Waste Water Treatment (2-2019-000733) | F130: Ivanuel Liguaton | G130: 8500
...

Sheet IBOD-Projects (2018-2025)
A1: Year | B1: Resolution No: | C1: Type | D1: Program | E1: Project Title | F1: Name of Proponent | G1: Amount of Investment
A2: 2025 | B2: 2025-13 | C2: APPROVAL | D2: I-TECH | E2: Expansion of the Commercialized Innovative Green Technology for Energy Conserving Industrial Oil Restoration Apparatus Services | F2: ENGR. REYNALDO RADEN ALDEPULLA Proprietor | G2: 4100000
A3: 2025 | B3: 2025-22 | C3: APPROVAL | D3: HIRANG 2.0 | E3: Concept Proposal for Cohort 3 for the HIRANG 2.0 Program Implementation | F3: Inventors and Startup beneficiaries of GALING and HEIs and SUC graduates of TECHNICOM | G3: 2500000
A4: 2025 | B4: 2025-29 | C4: APPROVAL | D4: eVFP | E4: Commercialization of GradeChum: An AI-Powered Platform for Automatic Evaluation of Handwritten Activities | F4: MR. JEMAR JUDE A. MARANGA President and CEO CODECHUM SOFTWARE SOLUTIONS INC. | G4: 4500000 | H4: STARTUP
A5: 2024 | B5: 2024-79 | C5: APPROVAL | D5: EVFP | E5: Bio-Based Polyurethene Adhesive System for Coconut Coir Board Production | F5: Kenno Michael M. Uy CEO Lesstics Inc | G5: 4551960 | H5: STARTUP
A6: 2024 | B6: 2024-51 | C6: APPROVAL | D6: EVFP | E6: Commercialization of Cerebro Plus: An Integrated School Management and Content Library System for k-12 Schools | F6: Jonald Justine U. Itugot Chief Executive Officer Cerebro Solutions, Inc. | G6: 3412000 | H6: STARTUP
A7: 2024 | B7: 2024-68 | C7: APPROVAL | D7: EVFP | E7: Enhance IP protection and Commercialization of Value-based Care Module of See You Doc Corp. under the Expanded VFP | F7: Mr. Noel Gary E. Del Castillo Founder and CEO | G7: 2332760.9 | H7: STARTUP
A8: 2024 | B8: 2024-58 | C8: APPROVAL | D8: EVFP | E8: Enhancement of BizKit (The First Local Centralized Business Suite) To Better Facilitate Cross-functional And Holistic Business Operations In The New Normal | F8: Marc Carlo Lijauco President BizKit Technologies Inc. | G8: 4000000 | H8: STARTUP
A9: 2024 | B9: 2024-60 | C9: APPROVAL | D9: EVFP | E9: HOCLOMAC: Product Certification, Inventory, and Sales | F9: Dr. Francis Aldrine A. Uy President and CEO USHER Technologies, Inc. | G9: 4143400.5 | H9: STARTUP
A10: 2024 | B10: 2024-87 | C10: APPROVAL | D10: EVFP | E10: Scale up of Fullmight Agricultural Corp. Operations and Product Certification | F10: Dr. Virginia M. Padilla Secretary and Treasurer Fullmight Agricultural Corp. | G10: 4771250 | H10: STARTUP
A11: 2024 | B11: 2024-84 | C11: APPROVAL | D11: EVFP | E11: Scale-Up Assistance for WEHLO Technologies, Inc. under E-VFP | F11: Dr. Cris Edward Monjardin Chief Technology Technology WEHLO Resilience Technology Corporation Inc. | H11: STARTUP
A12: 2024 | B12: 2024-35 | C12: APPROVAL | D12: HIRANG | E12: Honing Innovations, Research, Agreements and Negotiations of the Government - Funded Technologies* (HIRANG) 2.0 Program - Phase VI Implementation | F12: Technology generators, research, research teams, or TTBDOs of the DORT - RDI | G12: 705000
A13: 2024 | B13: 2024-90 | C13: APPROVAL | D13: EVFP | E13: Scale-up Operational Assistance to Hiraya Technology Solutions, Inc. | F13: Mr. Stephen L. Larcia Chief Executive Officer Hiraya Technology Solutions, Inc. | G13: 4000000 | H13: STARTUP
A14: 2024 | B14: 2024-45 | C14: APPROVAL | D14: HIRANG | E14: Concept Proposal for HIRANG 2.0 Cohort 2 Implementation | F14: Technology generators, researchers, research teams, or TTBDOs of the DOST-STS agencies, SUCs, and HEIs | G14: 2470750
A15: 2024 | B15: 2024-80 | C15: APPROVAL | D15: EVFP | E15: Scaleup of CHRG Inc. Operations and Product Certifications | F15: Engr. Leo Allen S. Tayo CEO and President CHRG Electric vehicle technologies Inc | G15: 5000000 | H15: STARTUP
A16: 2024 | B16: 2024-57 | C16: APPROVAL | D16: EVFP | E16: Scaling up for Market Expansion and Customer Retention | F16: Ms. Ralen Rose Gloria L. Malatbalat COO, making.technology Manufacturing Corporation | G16: 4668619.3 | H16: STARTUP
A17: 2024 | B17: 2024-59 | C17: APPROVAL | D17: HIRANG | E17: The PROPEL ENTERPRISE DEVELOPMENT Program | F17: DOST NCR DOST OASEC TTCC | G17: 5000000
A18: 2024 | B18: 2024-33 | C18: APPROVAL | D18: VFP | E18: Enhancing Manufacturing and Production Capacity through Raw Material Purchasing | F18: Charlou Delos Reyes Guion Proprietor CG Machine Shop | G18: 709948
A19: 2024 | B19: 2024-25 | C19: APPROVAL | D19: VFP | E19: Expanding Market Research-Enhancing Tonyts Food Products Growth with Strategic Raw Material Sourcing | F19: Ms. Antonitte C. Canda Proprietor Tonyts Food Products | G19: 333400
A20: 2024 | B20: 2024-50 | C20: APPROVAL | D20: VFP | E20: Purchase Order Financing for Danilyn's Enterprises, Inc.- Phase II | F20: Ms. Melinda C. Medallo Vice President/Marketing Head Danilyn's Enterprises, Inc. | G20: 1503651.6
A21: 2024 | B21: 2024-28 | C21: APPROVAL | D21: VFP | E21: Purchase Order Financing for Fondre Flavour Dynamics Vegetable Lumpiang Togue | F21: MR. GILBERT C. JIM CEO FONDRE FLAVOUR DYNAMICS, INC. | G21: 2000000
A22: 2024 | B22: 2024-70 | C22: APPROVAL | D22: VFP | E22: Strategic Raw Material Sourcing to Boost Manufacturing Efficiency for CAMPCO | F22: Mr. Noel B. Bacasnot Chairman CARAGA Adventists Multi-Purpose Cooperative (CAMPCO) | G22: 383657.4
A23: 2023 | B23: 45017 | C23: APPROVAL | D23: VFP | E23: PO Financing for Rockwell Enterprises for the delivery of DOST-ASTI Tsunami Early Warning System-Alerting Station Technology | F23: Mr. Alexis, Rellama, Rockwell Enterprises | G23: 380000
A24: 2023 | B24: 2023-20 | C24: APPROVAL | D24: VFP | E24: Purchase Order Financing for Danilyn’s’ Enterprises, Inc. | F24: Ms. Melinda C. Medallo Vice President/Marketing Head Danilyn’s Enterprises, Inc. | G24: 918215.51
A25: 2023 | B25: 2023-25 | C25: APPROVAL | D25: VFP | E25: PO Financing Program Support for Qualimeal Feedmills, Inc. | F25: Mr. Teotimo L. Reyes, Jr. President Qualimeal Feedmills, Inc. Banaybanay, San Vicente, Lipa City, Batangas | G25: 496800
A26: 2023 | B26: 2023-27 | C26: APPROVAL | D26: VFP | E26: Financing of Raw Materials Procurement of Ash Kitchen Trading and Marketing | F26: MS. GINA L. DELA CRUZ, Proprietor | G26: 556803.45
A27: 2023 | B27: 2023-31 | C27: APPROVAL | D27: VFP | E27: Venture Financing Program for Francis Jacob’s Gourmet Foods | F27: MS. IRENE D. HERRERO | G27: 1996038
A28: 2023 | B28: 2023-47 | C28: APPROVAL | D28: VFP | E28: Labo Progressive Multi-Purpose Cooperative Integrated Pineapple Processing and Marketing Enterprise (LPMPC-IPPME) QUEENCH Products Market Development and Productivity Enhancement | F28: Mr. Rey Ulysses L. Dimaano | G28: 163174.5
A29: 2023 | B29: 2023-49 | C29: APPROVAL | D29: VFP | E29: TAPI Purchase Order Financing Phase 1 for Mama Jita's Food Products | F29: Ms. Julieta Butalid-Dela Cerna | G29: 500000
A30: 2023 | B30: 2023-50 | C30: APPROVAL | D30: VFP | E30: Raw Materials for Continuous Disc Dryer | F30: Mr. Manuel P. Galut, Jr | G30: 1493838
A31: 2023 | B31: 2023-52 | C31: APPROVAL | D31: VFP | E31: Venture Financing Program Assistance for Soyuz Foods International Inc | F31: Ms. Helena H. Del Rosario | G31: 1240000
A32: 2023 | B32: 2023-53 | C32: APPROVAL | D32: VFP | E32: Venture Financing Program of RS Unitech Manufacturing and Trading Corporation | F32: Ms. Edralin Lagajino | G32: 249255
A33: 2023 | B33: 2023-55 | C33: APPROVAL | D33: VFP | E33: Venture Financing for Raw Materials of V. Weisz Synergy, Inc. | F33: Ms. Victoria Y. Bulan, President | G33: 1652388.5
A34: 2023 | B34: 2023-60 | C34: APPROVAL | D34: VFP | E34: Acquisition of Raw Materials to Enhance the Competitiveness and Sustainability of LNA DietCare’s Operation in Sibulan, Negros Oriental | F34: Ms. Leila N. Aclaro, RND Proprietor/Manager LNA DietCare | G34: 369166.12
A35: 2023 | B35: 2023-61 | C35: APPROVAL | D35: VFP | E35: Product Expansion of Affection8 Consumer Goods Trading through Acquisition of Venture Financing | F35: Ms. Monica Sandra Carino-Ronda | G35: 309847.12
... A40: 2022 | B40: 2022-34 | C40: APPROVAL | D40: VFP | E40: Commercialization of Hydrogen Fuel System | F40: KCH R&D Corporation | G40: 702000
A41: 2022 | B41: 2022-37 | C41: APPROVAL | D41: ITECH | E41: The Utilization of Calcium Hydroxide and Clinoptilolite Disinfectant PH12 of Hydrogen to Alleviate the Prevalence of Dengue in the Philippines | F41: Mr. Lyle Christian R. Herbosa
A42: 2022 | B42: 2022-45 | C42: APPROVAL | D42: VFP | E42: PO Financing Phase 2 for John N' Mico Food Productes | F42: Ms. Myra M. Bustillo, Owner/Manager | G42: 923252
A43: 2022 | B43: 2022-46 | C43: APPROVAL | D43: VFP | E43: PO Financing for La Paz Prime Foods Corporation | F43: Ms. Virgin Mary A. Nicolas, President | G43: 494868.75
A44: 2022 | B44: 2022-53 | C44: APPROVAL | D44: VFP | E44: PO Financing Assistance to SETUP assisted Kalinga Blend Roasted Ground Coffee Production" with "MAP Guidelines | F44: Ms. Grace B. Agtina, Owner | G44: 998550
A45: 2022 | B45: 2022-59 | C45: APPROVAL | D45: VFP | E45: Lactobiotics Worldwide Corporation Availment to Acquire Raw Materials though Purchase Order Financing Program of Technology Application and Promotion Institute (TAPI) | F45: Engr. Grecilda P. Sanches, President and CEO | G45: 1503212.5
A46: 2022 | B46: 2022-67 | C46: APPROVAL | D46: VFP | E46: PO Financing for Enhanced Nutribun Production by Esteems Industries, Inc. | F46: Engr. Grecilda P. Sanches, President and CEO | G46: 1000000
A47: 2022 | B47: 2022-73 | C47: APPROVAL | D47: YET | E47: Bamboo-Laminated Student Desk Production | F47: Romblon State University | G47: 225000
A48: 2022 | B48: 2022-78 | C48: APPROVAL | D48: YET | E48: Saint's Menthol Balm | F48: St. Agustin Institute of Technology (SAIT) | G48: 186356
A49: 2022 | B49: 2022-93 | C49: APPROVAL | D49: YET | E49: Labong Food Products | F49: Camarines Sur Polytechnic | G49: 50876.8
A50: 2022 | B50: 2022-96 | C50: APPROVAL | D50: VFP | E50: PO Financing for Malagos Agri-ventures Corporation | F50: Mr. Rex Victor P Puentespina, Director for Sales and Marketing | G50: 1534670
A51: 2021 | B51: 44378 | C51: APPROVAL | D51: VFP-PO | E51: Purchase Order Financing for SETUP Assisted Mica by the Sea company | F51: Arnulfo G. Singca President Mica By the Sea Company ( MBTSC) | G51: 1578099.2
A52: 2021 | B52: 2021-16 | C52: APPROVAL | D52: VFP-PO | E52: Purchase Order Financing Queenbee Enterprise Phase II | F52: Honeybee Y. Hicap Owner Queenbee Enterprises | G52: 1527776
A53: 2021 | B53: 2021-37 | C53: APPROVAL | D53: VFP-VFEST | E53: Adopting of Efficient and Sustainable Hybrid Solar Energy System for the Production of Cakes, Breads, Pastries in Chef Tobz RN Cakes and Pastries | F53: Tirso D. Tubog Owner/Manager Chef Tobz RN Cakes and Pastries | G53: 2880000
A54: 2021 | B54: 2021-48 | C54: APPROVAL | D54: VFP-PO | E54: Purchase Order Financing for Manna Shameyn Enterprises " | F54: Ramil R. Serrano Owner/Manager Manna Shameyn Enterprises | G54: 2928900.4
A55: 2021 | B55: 2021-50 | C55: APPROVAL | D55: VFP-PO | E55: Mica by the Sea Company (MBTSC) 2nd Availment of PO financing Assistance | F55: Arnulfo G. Singca President Mica By the Sea Company ( MBTSC) | G55: 4512920
A56: 2021 | B56: 2021-53 | C56: APPROVAL | D56: VFP-DOST-TECH | E56: Technology Upgrading on the Production Process and Commercialization of DOST-ITDI and USTP-NMFIC Developed Ready-To-Eat Nutritious Packs Technologies of Bestfriend Goodies in Cagayan De Oro City 1D | F56: Nenita M. Tan Chief Operating Officer Bestfriend Goodies | G56: 3300440
A57: 2021 | B57: 2021-59 | C57: APPROVAL | D57: VFP-LIGTAS COVID | E57: Support Assistance for Green Life Coco Products Philippines, Inc. under LIGTAS-COVID-19 | F57: Frances A. Rubio Corporate Secretary Green Life Coco Products | G57: 1000000
A58: 2021 | B58: 2021-64 | C58: APPROVAL | D58: VFP | E58: Installation of Standard Treatment Plant for Batangas Egg Producers Multi-Purpose Cooperative | F58: Victorino Michael I. Lescano Chairperson Batangas Egg Producers MPC | G58: 916956.36
A59: 2021 | B59: 2021-71 | C59: APPROVAL | D59: YET | E59: Production of Organically Grown Philippine Native Pig and Native Chicken | F59: Cagayan State University (CSU) | G59: 246099.46
A60: 2021 | B60: 2021-04-memo | C60: APPROVAL | D60: DATBED | E60: 1. Fruit Wine Production 2. One Campus One Product (OCOP) Baked Products Development 3. Processed Foods Production | F60: Isabela State University | G60: 114237.84
A61: 2021 | B61: 2021-01-adref | C61: APPROVAL | D61: DATBED | E61: Oyster Mushroom Production | F61: Maria Bernadette Navera Proprietor Exotic Organicum Mushroom Farm | G61: 246150 | H61: ACADEME
A62: 2020 | B62: 43862 | C62: APPROVAL | D62: VFP | E62: Venture- P.O Financing for NFMC Production of Rimo Blend Choco for DSWD Region VI | F62: Racky D. Doctor President Nutridense Food Manufacturing Corporation (NFMC) | G62: 2957181.7 | H62: MSME
A63: 2020 | B63: 44075 | C63: APPROVAL | D63: Ligtas Covid-19 | E63: Support Assistance for C and H Cosmetics Industry under Ligtas Covid-19 | F63: Henry V. Raca General Manager C and H Cosmetics Industry (CHCI) | G63: 1000000
A64: 2020 | B64: 44136 | C64: APPROVAL | D64: Ligtas Covid-19 | E64: Support Assistance for East L.A. Industry, Inc. under ligtas -Covid-19 | F64: Ernest Karl L. Chua President East L.A Industry , Inc. (ELII) | G64: 1000000
A65: 2020 | B65: 2020-14 | C65: APPROVAL | D65: Ligtas Covid-19 | E65: Support Assistance to Manna Shameyn Enterprises Under Ligtas-Covid 19 | F65: Ramil R. Serrano Owner/ Manager | G65: 1000000
A66: 2020 | B66: 2020-15 | C66: APPROVAL | D66: VFP | E66: Support Assistance for Pasciolco Agri Ventures for P.O Financing Facility | F66: Maura M. Pasciolco Owner/General Manager | G66: 2284150
A67: 2020 | B67: 2020-16 | C67: APPROVAL | D67: VFP | E67: Purchase Order Financing Assistance of SETUP- Assisted Cellokey Incorporated | F67: Loreto B. Tolentino President Cellokey Incorporated ( CI) | G67: 1621819.5
A68: 2020 | B68: 2020-17 | C68: APPROVAL | D68: VFP | E68: Purchase Order Financing Assistance to i-Provide Health Food Manufacturing | F68: Abelardo T. Balisi , Jr. Owner/Manager i-Provide Health Food Manufacturing | G68: 2382264
A69: 2020 | B69: 2020-09-memo | C69: APPROVAL | D69: VFP | E69: Purchase Order Financing Assistance of SETUP- Assisted | F69: Arnold Louie General Merchandise | G69: 140032
A70: 2020 | B70: 2020-02-ad referenda | C70: APPROVAL | D70: VFP | E70: Product and Process Improvement through the Adoption of Appropriate Technologies for RedSea Seafood Delights, Inc. | F70: Gerry Balingit | G70: 453820
A71: 2020 | B71: 2020-07-adref | C71: APPROVAL | D71: VFP | E71: Purchase order financing for Queenbee Enterprise | F71: Ms. Honeybee Y. Hicap | G71: 418714.15
A72: 2020 | B72: 2020-10-Ad ref | C72: APPROVAL | D72: VFP | E72: Production Facility of Fine Foods, Inc. | F72: Ms. Teresita S. Ladanga | G72: 1240490
A73: 2020 | B73: 2020-12-ad ref | C73: APPROVAL | D73: VFP | E73: Purchase Order Financing for Eggciting Products Manufacturing | F73: Ms. Ambrocio Kerwin A. Perez | G73: 495000
A74: 2020 | B74: 2020-14-ad ref | C74: APPROVAL | D74: VFP | E74: Adoption of Cahrcoal Briquetting technology to utilize Filo Handcrafts Wood Waste Into Another Product | F74: Mr. Victor B. Li | G74: 819000
A75: 2020 | B75: 2020-17-ad ref | C75: APPROVAL | D75: VFP | E75: Support Assistance for Prime Innov8 manufacturing Co. Under Ligtas Covid-19 | F75: Ms. Ma Celia G. Pajel | G75: 453346.5
A76: 2020 | B76: 2020-21a-ad ref | C76: APPROVAL | D76: DATBED | E76: Kabutehan ng mga estudyante: A Student Empowerment Project Venturi and Processing at CSU-Gonzaga, Cagayan | F76: Cagayan State University (CSU) | G76: 87475
... A83: 2019 | B83: 2019- 44 | C83: APPROVAL | D83: DATBED | E83: Upgrading of Goat Production Thru Artficial Insemination | F83: Isabela State University (ISU) | G83: 126407.57
A84: 2019 | B84: 2019-54 | C84: APPROVAL | D84: VFP | E84: Application for Local and International Certifications of Manila Healthtek, Inc. as a Manufacturing Company for Molecular-Based Diagnostic kits | F84: Dr. Raul V. Destura President/CEO Manila Healthtek , Inc. | G84: 3792164.9 | H84: STARTUP
A85: 2019 | B85: 2019-55 | C85: APPROVAL | D85: VFP | E85: Adoption of Charcoal Briquetting Technology to Utilize Fino Handicrafts Wood Waste into another Product | F85: Victor B. Li Owner/Manager | G85: 819000
A86: 2019 | B86: 2019-56 | C86: APPROVAL | D86: VFP | E86: PO financing Program Support for Kapfer and Rivera United, Inc. (KRUI) | F86: Atty. Maria Lourdes E. Rivera Corporate Secretary & Treasurer Kapfer and River United, Inc. | G86: 950981.8
A87: 2019 | B87: 2019-11-Ad ref | C87: APPROVAL | D87: DATBED | E87: Organic Chicken Production of Isabela State University under DATBED | F87: ISU | G87: 96071.35
A88: 2019 | B88: 2019-66 | C88: APPROVAL | D88: DATBED | E88: Mr. and Mrs. Verde | F88: University of Saint Louis-Tuguegarao City, Cagayan | G88: 92275.68
A89: 2019 | B89: 2019-69 | C89: APPROVAL | D89: VFP | E89: Expansion of Production of the Essential Fine Foods | F89: Ms. Teresita S. Ladanga | G89: 1717600
A90: 2019 | B90: 2019-73 | C90: APPROVAL | D90: VFP-PO | E90: Purchase Order Financing for Jamerika Enrterprise | F90: Mr. Jaime B. Memjie | G90: 468445.54
A91: 2019 | B91: 2019-74 | C91: APPROVAL | D91: VFP-PO | E91: PO financing program support to Eggciting products manufacturing | F91: Mr. Ambrocio Kerwin A. Perez | G91: 495000
A92: 2019 | B92: 2019-75 | C92: APPROVAL | D92: VFP-PO | E92: PO Financing Program Support to AIJUN Enterprises, Inc. | F92: Ms. Ailyn L. Magallanes | G92: 500000
A93: 2019 | B93: 2019-06-memo | C93: APPROVAL | D93: IBOD | E93: 45th Philippine Business Conference and Exposition (PBC&E) | F93: DOST-TAPI
A94: 2019 | B94: 2019-15-memo | C94: APPROVAL | D94: DATBED | E94: Forumlation and Utilization of Rations with Mungbean by-products | F94: ISU | G94: 16685
A95: 2019 | B95: 2019-15b-memo | C95: APPROVAL | D95: DATBED | E95: Duck Fattening Using Mungbean by-Products | F95: ISU | G95: 77500
A96: 2019 | B96: 2019-15c-memo | C96: APPROVAL | D96: DATBED | E96: Processing of Duck Meat into Longganiza | F96: ISU | G96: 110050
A97: 2019 | B97: 2019-27-memo | C97: APPROVAL | D97: DATBED | E97: Automative Multifunction Tester and Supply and admin Cost for DOST XI | F97: University of Mindanao | G97: 57545.95
A98: 2018 | B98: 43132 | C98: Approval | D98: VFP | E98: Purchase Order Financing for Endurance Technology Corporation | F98: Joseph Victor G. Joaquin President Endurance Technology Corporation | G98: 710458.07
A99: 2018 | B99: 43160 | C99: Approval | D99: VFP | E99: Production and Commercialization of Rice-Mongo Curls and Instant Blend Baby Food | F99: Anthony Nicanor Joaquin Bello President JND Manufacturing Industries, Inc. | G99: 2839000
A100: 2018 | B100: 2018-21 | C100: Approval | D100: VFP | E100: Calabash Bowl Production | F100: Ritchie R. Wagas Owner Wagas Crafts | G100: 1170000
A101: 2018 | B101: 2018-22 | C101: Approval | D101: VFP | E101: Purchase Order Financing for Detelia Aurora, Inc (Phase II) | F101: Raul B. Maloloy-on Vice President Detalia Aurora Incorporated | G101: 869853.5
A102: 2018 | B102: 2018-50 | C102: Approval | D102: VFP | E102: Purchase Order Financing for Jamerika Enterprises, Inc. | F102: Jaime B. Memije President Jamerika Enterprises Inc. | G102: 1405331.5
A103: 2018 | B103: 2018- 52 | C103: Approval | D103: VFP | E103: Upgrading the Micro-Propagation Capability of Masikhay Microplants Nursery | F103: Emmanuel L. Bernardo Owner Masikhay Microplants Nursery Unit 2, Lina's Orchard | G103: 493709
A104: 2018 | B104: 2018-54 | C104: Approval | D104: VFP | E104: TAPI Purchase Financing for John N' Mico Food Products | F104: Myra M. Bustillo Owner/Manager John N' Mico Food Products | G104: 594944
A105: 2018 | B105: 2018-62 | C105: Approval | D105: IBED II | E105: Commercialization of HP/HT Cremation/HP Recovering Machine Patent No. 1-2009-000260 | F105: Manuel M. Malonzo | G105: 1094960
A106: 2018 | B106: 2018-63 | C106: Approval | D106: IBED II | E106: Commercialization of "Power up Fuel Combustor" UM No. 2-2014-000500 | F106: George P. De Guzman Owner Smoke Belching Solution Center | G106: 672600
A107: 2018 | B107: 2018-64 | C107: Approval | D107: IBED II | E107: Commercialization of "Herbal Massage Oil" | F107: Roberto D. Osido Owner BDO Herbosido Herbal Products | G107: 831690
A108: 2018 | B108: 2018-65 | C108: Approval | D108: IBED II | E108: Purchase Order Financing for PhilTech Boat Designs and Fabrications | F108: Ronald P. Pagsanghan Owner Philtech Boat Designs and Fabrications | G108: 967500
A109: 2018 | B109: 2018-66 | C109: Approval | D109: VFP | E109: Expansion of Production Facility Essential Fine Foods, Inc. (EFFI) | F109: Teresita S. Ladanga Vice President/Treasurer Essential Fine Foods, Inc. (EFFI) | G109: 1717600
A110: 2018 | B110: 2018-71 | C110: Approval | D110: VFP | E110: Sustainability of Apple Cider VInegar Production of Double M. Merchandise | F110: Teresa S. Abaya Owner Double M. Merchandise | G110: 366000
...

Sheet Copy of TIPD_STARTUPS
A1: Year | B1: Resolution No: | C1: TYPE | D1: Program Applied | E1: PROMOTIONAL ASSISTANCE | F1: Approval Date | G1: Project Title | H1: Name of Proponent | I1: Address | J1: Contact Details | K1: Amount | L1: CLASS | M1: STATUS | N1: POSSIBLE FOLLOW UP ASSITANCE
A2: 2025 | C2: PROMOTION | D2: EIPRAP | E2: Market Intelligence under IMPAKT | F2: 2025 | G2: Enhancement, Market Validation and Pilot Production of AI-Driven Farm Management Module (AID-FMM) | H2: Waste4good Research and Experimental Development in Engineering and Technology | J2: lurelynpablo@gmail.com lorilyn.daquioag@eee.upd.edu.ph 639385504997 | L2: STARTUP | M2: ONGOING
A3: 2024 & 2025 | C3: PROMOTION | D3: EIPRAP | E3: WoSG, E-MarkET Market Intelligence, CES 2025 | F3: 2024 & 2025 | G3: High-resolution 3D Geological Mapping with Ambient Electromagnetic Interferometry | H3: Emmanuel G. Ramos Mark Linus C. Ramos Rodolfo Alfonso R. Sabio | L3: STARTUP | M3: ONGOING
A4: 2025 | C4: PROMOTION | D4: EIPRAP | E4: IEIG 2025, PHILIPPiNEXT | F4: 2025 | G4: A System and Method for Managing Healthcare Services and Networks | H4: SeeYouDoc Corporation | J4: noel@seeyoudoc.com | L4: STARTUP | M4: ONGOING
A5: 2025 | B5: 2025-29 | C5: PROMOTION | D5: EVFP | G5: Commercialization of GradeChum: An AI-Powered Platform for Automatic Evaluation of Handwritten Activities | H5: MR. JEMAR JUDE A. MARANGA President and CEO CODECHUM SOFTWARE SOLUTIONS INC. | I5: 753 Katipunan St., Tisa, Cebu City, Cebu, Philippines | J5: jude@codechum.com 639959469610 | K5: 4500000 | L5: STARTUP | M5: ONGOING
A6: 2024 | B6: 2024-79 | C6: PROMOTION | D6: EVFP | E6: IEIG 2025 / RSTW VIII | F6: 2025 | G6: Bio-Based Polyurethene Adhesive System for Coconut Coir Board Production | H6: Kenno Michael M. Uy CEO Lesstics Inc | I6: 0014 Matthew St. Bahayan, Luinab, Iligan City | J6: Cell No.: 0917-162-2127 Email: lesstics@gmail.com | K6: 4551960 | L6: STARTUP | M6: ONGOING
A7: 2024 | B7: 2024-60 | C7: PROMOTION | D7: EVFP | E7: WoSG, CES 2025, E-MarkET Market Intelligence | F7: 2024 | G7: HOCLOMAC: Product Certification, Inventory, and Sales | H7: Dr. Francis Aldrine A. Uy President and CEO USHER Technologies, Inc. | I7: 1409 Corporate 145, Mother Ignacia St., South Triangle, Quezon City | J7: drfrancisuy@gmail.com | K7: 4143400.5 | L7: STARTUP | M7: ONGOING
A8: 2024 | B8: 2024-51 | C8: PROMOTION | D8: EVFP | G8: Commercialization of Cerebro Plus: An Integrated School Management and Content Library System for k-12 Schools | H8: Jonald Justine U. Itugot Chief Executive Officer Cerebro Solutions, Inc. | J8: justine@cerebro.ph +63 917 886 5402 | K8: 3412000 | L8: STARTUP | M8: ONGOING
A9: 2024 | B9: 2024-68 | C9: PROMOTION | D9: EVFP | G9: Enhance IP protection and Commercialization of Value-based Care Module of See You Doc Corp. under the Expanded VFP | H9: Mr. Noel Gary E. Del Castillo Founder and CEO | J9: noel@seeyoudoc.com | K9: 2332760.9 | L9: STARTUP | M9: ONGOING
A10: 2024 | B10: 2024-58 | C10: PROMOTION | D10: EVFP | G10: Enhancement of BizKit (The First Local Centralized Business Suite) To Better Facilitate Cross-functional And Holistic Business Operations In The New Normal | H10: Marc Carlo Lijauco President BizKit Technologies Inc. | I10: 96 Burgos St. Pamplona Uno Las Piñas City 1740 | J10: mclijauco@bizkittechnologies.com | K10: 4000000 | L10: STARTUP | M10: ONGOING
A11: 2024 | B11: 2024-87 | C11: PROMOTION | D11: EVFP | G11: Scale up of Fullmight Agricultural Corp. Operations and Product Certification | H11: Dr. Virginia M. Padilla Secretary and Treasurer Fullmight Agricultural Corp. | I11: 6th Street, 1856 Hillside Village Subdivision, Brgy. Tuntungin-Putho, Los Baños Laguna | J11: Tel. no.: (049) 508-0557 CP no.: 0917-887-8542, 0917-179-8542 Email: padilla7.jaime@gmail.com, virgiem.padilla@gmail.com | K11: 4771250 | L11: STARTUP | M11: ONGOING
A12: 2024 | B12: 2024-84 | C12: PROMOTION | D12: EVFP | E12: CES 2025, Handa Pinas 2025 | F12: 2025 | G12: Scale-Up Assistance for WEHLO Technologies, Inc. under E-VFP | H12: Dr. Cris Edward Monjardin Chief Technology Technology WEHLO Resilience Technology Corporation Inc. | I12: Unit 1409, Corporate 145, 145 Mother Ignacia St., Brgy. South Triangle, Quezon City | J12: 09692314619 cefmonjardin@mapua.edu.ph | K12: 4.975,000.00 | L12: STARTUP | M12: ONGOING
A13: 2024 | B13: 2024-90 | C13: PROMOTION | D13: EVFP | E13: WoSG, CES 2025, DOST-TAPI and APCTT event Sept 3-4, 2024 , Handa Pinas 2025 | F13: 2024 & 2025 | G13: Scale-up Operational Assistance to Hiraya Technology Solutions, Inc. | H13: Mr. Stephen L. Larcia Chief Executive Officer Hiraya Technology Solutions, Inc. | I13: 502-503 Jocfer Building, Commonwealth Ave., Quezon City | J13: Cell No.: (02) 8826 6836 Email: stephen@hirayatech.ai; info@hirayatech.ai | K13: 4000000 | L13: STARTUP | M13: ONGOING
A14: 2024 | B14: 2024-80 | C14: PROMOTION | D14: EVFP | E14: E-MarkET WoSG Market Intelligence, NICE, CES 2025, APCTT 2024 Exhibit, Philippinext | F14: 2024 & 2025 | G14: Scaleup of CHRG Inc. Operations and Product Certifications | H14: Engr. Leo Allen S. Tayo CEO and President CHRG Electric vehicle technologies Inc | I14: 3F, Enterprise Incubation Room, National Engineering Center, Osmena Ave, UP Campus, Diliman, Quezon City. | J14: Engr. Leo Allen S. Tayo – 09272103449 Engr. Rovinna Janel Tayo – 09297193619 leo@chrg.tech / janel@chrg.tech | K14: 5000000 | L14: STARTUP | M14: ONGOING
A15: 2024 | B15: 2024-57 | C15: PROMOTION | D15: EVFP | G15: Scaling up for Market Expansion and Customer Retention | H15: Ms. Ralen Rose Gloria L. Malatbalat COO, making.technology Manufacturing Corporation | I15: UPSCALE G/F National Engineering Center, F. Agoncillo St., cor. Osmena Ave., U.P. Campus, Diliman, Quezon City, 1101 | J15: ralen@makingtech.co / inquire@makingtech.co | K15: 4668619.3 | L15: STARTUP | M15: ONGOING
A16: 2022 | B16: 2022-109 | C16: PROMOTION | D16: ITECH | E16: Marketing Assistance Program, SIIF | F16: 2024 | G16: Commercialization of Maker-scope | H16: MR. JEREMY C. DE LEON | J16: jeremycdeleon@gmail.com | K16: 1083679 | L16: STARTUP | M16: COMPLETED
A17: 2018 | C17: PROMOTION | D17: IBED | E17: Marketing Assistance Program, LUNDUYAN | F17: 2022 | G17: Alkaline Fuel Cell For Various Applications | H17: Roderick Nicolas | J17: hydrogenprolife@gmail.com | M17: COMPLETED
A18: 2018 | C18: PROMOTION | D18: IBID | E18: Marketing Assistance Program | F18: 2022 | G18: Foldable Crutch System | H18: James Bryan Camacho | J18: jabecmacho@gmail.com | M18: COMPLETED
A19: 2018 | C19: PROMOTION | D19: IBED-I | E19: Marketing Assistance Program | F19: 2022 | G19: Simplified Compact Tire Inverter Machine | H19: Lester A. Quimpo | J19: lesterquimpo@yahoo.com | M19: COMPLETED
A20: 2018 | C20: PROMOTION | D20: IBED-I | E20: Marketing Assistance Program | F20: 2022 | G20: Green Eco-Toilet System (GETS) | H20: Daniel A. Camacho | J20: greenway.ts@gmail.com | M20: COMPLETED
A21: 2025 | C21: PROMOTION | D21: GALING | E21: LUNDUYAN KIWIE, Marketing Assistance Program | F21: 2024 | G21: Magicbag: Wireless slow cooker | H21: Ms. Rowena Faith Armeniana Sucalit 4423 Montojo St. Tejeros, Makati City | J21: weng747@yahoo.com 0916-777-8031 | K21: 229654 | L21: STARTUP | M21: ONGOING | N21: GALING (Market Validation)
A22: 2024 | C22: PROMOTION | D22: GALING | E22: PHILIPPiNEXT | F22: 2025 | G22: Marissa Turbine: Vertical-Axis Tidal Turbine | H22: Mr. Patrick Roland de Guzman 65 Lawa, Obando, Bulacan | J22: deguzmanpatrickroland@gmail.com 09974916634 | K22: 395212 | L22: STARTUP | M22: ONGOING
A23: 2024 | C23: PROMOTION | D23: GALING | E23: PHILIPPiNEXT, Marketing Assistance Program, KIWIE, LUNDUYAN | F23: 2024 | G23: Technology Validation of Unas Canvas (UnVas) | H23: Julienne Fabie-Agapin Lumbia District, Pagadian City | J23: juliennestephanie.agapin@wmsu.edu.ph 09362660139 | L23: STARTUP | M23: COMPLETED
A24: 2024 | C24: PROMOTION | D24: GALING | E24: PHILIPPiNEXT | F24: 2025 | G24: Technology Validation of IOT Artificial Intelligence-Based Dosing System in Greenhouse | H24: Mr. Alvin Phoebe Artemis A. Valdez Interior Fidelidad Street, Barangay 1, Balayan, Batagas 4213 | J24: alvinphoebeartemis@gmail.com +639918781878; +639916453232 | K24: 236341.77 | L24: STARTUP | M24: ONGOING
A25: 2023 | C25: PROMOTION | D25: GALING | E25: LUNDUYAN, Marketing Assistance Program | F25: 2024 | G25: Improved KoolGear | H25: Mr. Ivan Brent Nara Bldg. 23, UP Bliss, Diliman, Quezon City | J25: naraivanbrent@gmail 09751905598 | K25: 96107 | L25: STARTUP | M25: ONGOING
A26: 2023 | C26: PROMOTION | D26: GALING | E26: Marketing Assistance Program, KIWIE | F26: 2024 | G26: Foldable Water Tank with Zeramic Filter | H26: Ms. Eleanor M. Olegario | I26: 17 Cavite Street, Bonifacio Village, Brgy. Pasong Tamo, Quezon City | J26: eleanor.olegario@gmail.com 09209129187 | K26: 191500 | L26: STARTUP | M26: COMPLETED
A27: 2023 | C27: PROMOTION | D27: GALING | E27: PHILIPPiNEXT, Marketing Assistance Program, CES 2025, SIIF | F27: 2024, 2025 | G27: Technology Validation of Pili Seal | H27: Engr. Mark Kennedy E. Bantugon | J27: markkennedy09bantugon@gmail.com andpili.adheseal@gmail.com | K27: 349799.56 | L27: STARTUP | M27: ONGOING
A28: 2025 | C28: PROMOTION | D28: GALING | G28: Fabrication, and Installation of a 50W LED Flood Light Post with Integration of Small-scale Savonius-Type Helical Vertical Axis Wind Turbine (VAWT) and Solar Panel | H28: Engr. Jose Luis L. Villalon | I28: 25 Mercury, Zytek-Riosa, Brgy. Pasong Tamo, Quezon City, 1107 | J28: louie.vdaliinnovations@gmail.com +63 915 126 5571 | K28: 358538 | L28: STARTUP | M28: ONGOING
A29: 2023 | C29: PROMOTION | D29: GALING | E29: Marketing Assistance Program, LUNDUYAN | F29: 2024 | G29: LanaSug Cooking Oil | H29: AL-ANNI A. ASGALI | J29: farshaniasgali@gmail.com | M29: ONGOING
A30: 2023 | C30: PROMOTION | D30: GALING | E30: Marketing Assistance Program, LUNDUYAN | F30: 2024 | G30: Motorized Multi-Purpose Machine | H30: Johnny Banez | J30: johnnybanez1@gmail.com | M30: ONGOING
A31: 2023 | C31: PROMOTION | D31: GALING | E31: Marketing Assistance Program, LUNDUYAN | F31: 2024 | G31: Technology Validation of Pili Seal | H31: Engr. Mark Kennedy E. Bantugon | J31: markkennedy09bantugon@gmail.com | L31: STARTUP | M31: ONGOING
A32: 2023 | C32: PROMOTION | D32: GALING | E32: Marketing Assistance Program, LUNDUYAN | F32: 2024 | G32: Channel Multiplier Remote Control System – Prototype 3 | H32: Mr. Gibsonjis Rosales | J32: gibsonjisrosales@gmail.com | M32: ONGOING
A33: 2023 | C33: PROMOTION | D33: GALING | E33: Marketing Assistance Program, LUNDUYAN | F33: 2024 | G33: Alpha Herbal Oil | H33: Ms. Mariecel A. Fuentes | J33: Mariecel.fuentes30@gmail.com
A34: 2023 | C34: PROMOTION | D34: GALING | E34: Marketing Assistance Program | F34: 2024 | G34: Improved KoolGear | H34: Mr. Ivan Brent Nara | J34: naraivanbrent@gmail.com | L34: STARTUP
A35: 2023 | C35: PROMOTION | D35: GALING | E35: Marketing Assistance Program, LUNDUYAN | F35: 2024 | G35: Innovation support for Pre-commercialization of Abaca Fiber Tiles: a locally developed product utilizing Abaca wastes | H35: Mr. Jay F. Sanchez | J35: jsanchez372000@yahoo.com
A36: 2023 | C36: PROMOTION | D36: GALING | E36: Marketing Assistance Program, LUNDUYAN | F36: 2024 | G36: Foldable Water Tank with Zeramic Filter | H36: Ms. Eleanor M. Olegario | J36: lithos.opc.2021@gmail.com | L36: STARTUP
A37: 2025 | C37: PROMOTION | D37: TECHNICOM | G37: Commercialization and Scaling of Duon’s Real-Time Indoor Navigation with Foot Traffic Behavioral Analysis and Prediction AI | H37: MR. GABRIEL ANTON D. ANGELES, Project Leader DUON TECHNOLOGIES INCORPORATED | I37: 7F, Panorama Tower 34th Street, corner Lane A, Taguig, 1634 Metro Manila | J37: gda4993@gmail.com, admin@duon.ph 9773470628 | K37: 7175464 | L37: STARTUP | M37: ONGOING
A38: 2025 | C38: PROMOTION | D38: TECHNICOM | E38: PHILIPPiNEXT | F38: 2025 | G38: COMMERCIAL PROTOTYPING OF SMART WATER (IOT) METER (SWIM) | H38: CONRADO D. CAMILON JR, Project Leader ALEXA’S ENGINEERING SERVICES | J38: cdcamilonjr@gmail.com 09224074861/049-501-4583 | K38: 4998689 | L38: STARTUP | M38: ONGOING
A39: 2025 | C39: PROMOTION | D39: TECHNICOM | E39: PHILIPPiNEXT | F39: 2025 | G39: Rezbin: Business Model Validation and Market Acceptability Testing for Low Cost AI-powered Bins as an Alternative to Expensive Reverse Vending Machines in Metro Manila | H39: Matthew Cristi C. Martirez, Project Leader Rezbin Waste Technology Inc. | J39: mari@rezbin.ph, hello@rezbin.ph 639178920234 | K39: 4999988 | L39: STARTUP | M39: ONGOING
A40: 2025 | C40: PROMOTION | D40: TECHNICOM | G40: Technological Improvement and Field Testing of Bamboo-based Biodegradable Period Care | H40: Alexandra B. Jocom, Project Leader BioTerra Corp. (Halia) | J40: alexa@halia.co 639764896618 | K40: 5000000 | L40: STARTUP | M40: ONGOING
A41: 2025 | C41: PROMOTION | D41: TECHNICOM | G41: Scaling Up and Deployment of the Multi-Drum Chamber Carbonization System for Sustainable Charcoal Production in the Philippines | H41: Julieane M. Fernandez, Project Leader Eco-Uling by Project Lily Inc. | J41: ayafernandez.ecouling@gmail.com 0915-795-1534 | K41: 4884739 | L41: STARTUP | M41: ONGOING
A42: 2025 | C42: PROMOTION | D42: TECHNICOM | G42: Optimizing Bamboo Processing: 2-IN-1 Furnace For Pole Treatment and Valorization of Silica-Rich Bamboo Ash | H42: Anneth Rigon BAMBOO IMPACT LAB OPC | J42: anneth@bambooimpactlab.com 0919-999-0488 | K42: 4993468 | L42: STARTUP | M42: ONGOING
A43: 2024 | C43: PROMOTION | D43: TECHNICOM | G43: Automated Coconut Sap Extraction: Enhancing Productivity and Quality Through Innovative Technology | H43: Luzmar M. Gabor KASAKA Agriventures, Inc. | J43: asaka@aim.edu 9175305742 | K43: 2998072 | L43: STARTUP | M43: ONGOING
A44: 2024 | C44: PROMOTION | D44: TECHNICOM | G44: Enhancement and Market Validation of AI-Powered Property Management Solutions for the Philippines | H44: Mr. Jesehl Charles Basco Project Leader Collo/Proprty Technology Solutions Inc. | J44: jay@collo.ph 9178327166 | K44: 2911170 | L44: STARTUP | M44: ONGOING
A45: 2024 | C45: PROMOTION | D45: TECHNICOM | G45: Enhancement, Market Validation, and Pilot Production of AI-Driven Farm Management Module (AID-FMM) | H45: Ms. Lorilyn P. Daquioag Project leader Waste4Good technologies | J45: lurelynpablo@gmail.com lorilyn.daquioag@eee.upd.edu.ph 639385504997 | K45: 2384720 | L45: STARTUP | M45: ONGOING
A46: 2024 | C46: PROMOTION | D46: TECHNiCOM | G46: Improvement and Pilot Testing of Alerto PH AI-as-a-Service (AlaaS) | H46: Ms. Cristina Macaraig WiredField Philippines Inc. | J46: cristina@wiredfield.com | K46: 2975715 | L46: STARTUP | M46: ONGOING
A47: 2024 | C47: PROMOTION | D47: TECHNICOM | G47: Market Testing of Online Residential Rental Marketplace for Filipino Students and Young Professionals | H47: Alyssa Casandra Wee Project Leader/ Krelio Technologies Inc. | J47: alyssa@dormy.ph, hello@dormy.ph 0992 681 6544 | K47: 2999945.7 | L47: STARTUP | M47: ONGOING
A48: 2024 | C48: PROMOTION | D48: TECHNICOM | G48: Pilot Testing and Technology Validation of Fortified Powdered Coconut Milk as a Powdered Dairy Alternative to Lactose Intolerant and Nutrient Deficient Filipino Children and Adults | H48: Samuel Antonius De Chavez Tecuala Dehusk | I48: Martel Bldg. Verdon Parc, Unit 716 Ecoland Drive, Talomo, Bucana, Davao Del Sur, Davao City, 8000 | J48: samuel.tecuala@dehusk.com.ph 09565734432 | K48: 2789556 | L48: STARTUP | M48: ONGOING
A49: 2024 | C49: PROMOTION | D49: TECHNICOM | G49: Scaling up Testing of a Peer-to-Peer Car Sharing Marketplace for the Filipino Car Sharing Economy | H49: Mr. Miguel Locsin Project Leader DOON Transport Technologies Inc. | I49: Unit 302, 5048 P. Burgos Street, Draper Startup House for Entrepreneurs, Brgy. Poblacion, Makati City, Fourth District, NCR 1210 / | J49: miguel@doon.ph 09178076499 | K49: 2896644 | L49: STARTUP | M49: ONGOING
A50: 2024 | C50: PROMOTION | D50: TECHNICOM | G50: The Scrapcycle PH field and Market Testing of Scrap Trading Dynamics Across Philippine Urban Landscapes | H50: Genevieve P. Navales/Female Project Leader, ScrapCycle PH | J50: vievenavales29@gmail.com 09952033203 | K50: 2785599 | L50: STARTUP | M50: ONGOING
A51: 2023 | C51: PROMOTION | D51: TECHNICOM | G51: Technology and business validation of an advanced web and mobile Point-of-Sale (POS) software-as-a-service (SAAS) application for Philippine micro and small retail businesses | H51: Renzo Navarro Ducusin Project Leader IOL, Inc. | I51: Rm 404 Jose Miguel Bldg. Yandoc St., Baguio City. Philippines | J51: kevin@iolph.com 074-6209538 | K51: 2715682.8 | L51: STARTUP | M51: ONGOING
A52: 2023 | C52: PROMOTION | D52: TECHNICOM | G52: Determining the Pesticide Residue Level of Mangoes using a smart metal oxide nanosensor for Post-Harvest Applications | H52: Ms. Normie Jean Sajor Lacubtan Project Leader | J52: njsajor@gmail.com f.normiejean.lacubtan@cmu.edu.ph | K52: 2398683 | L52: STARTUP | M52: ONGOING
A53: 2023 | C53: PROMOTION | D53: TECHNICOM | G53: Scaling Digital Clustering Solution for Enhanced Agri-Value Chain Integration of Farm Konek | H53: John Vincent Q. Gastanes Project Zacchaeus Marketing Cooperative | I53: Unit 1, CCT Building, Puerto Princesa City, Palawan, 5300/ MIMAROPA | J53: gastanesjohnvincent@gmail.com 639177979073 | K53: 7936800 | L53: STARTUP | M53: ONGOING

Sheet TIPD-Projects (2018-2025)
A1: Year | B1: Resolution No: | C1: Type | D1: Program | E1: Project Title | F1: Name of Proponent | G1: Amount of Investment
A2: 2025 | B2: 45778 | C2: APPROVAL | D2: IMPAKT | E2: 50th Geneva International Exhition of Inventions | F2: Identified 2024 NICE Winners, DOST-attached agencies, and DOST-funded/supported Startups and Universities | G2: 2535792
A3: 2025 | B3: 2025-23 | C3: APPROVAL | D3: LEAD | E3: 2025 MIMAROPA Regional Science, Technology, and Innovation Week Celebration | F3: DOST-MIMAROPA | G3: 200000
A4: 2025 | B4: 2025-25 | C4: APPROVAL | D4: IMPAKT | E4: Proposal for DOST-TAPI GFPS Promotional Campaign "Lahat tayo, POSIBLE" | F4: DOST-TAPI External Clients
A5: 2025 | B5: 2025-27 | C5: APPROVAL | D5: LEAD | E5: Conduct of the 2025 Clusterized Regional Invention Contest and Exhibits (ClusteRICE) | F5: DOST-Regional Offices and ClusteRICE participants, and stakeholders
A6: 2025 | B6: 2025-28 | C6: APPROVAL | D6: LEAD | E6: 2025 Regional Science Technology and Innovation Week (RSTiW) Celebration in the Cordillera Administrative Region | F6: DOST-Cordillera Administrative Region (DOST- CAR) | G6: 300000
A7: 2025 | B7: 2025-33 | C7: APPROVAL | D7: LEAD | E7: 2025 HANDA PILIPINAS SA BAGONG PILIPINAS: Innovations in Climate and Disaster Resilience Nationwide Exposition 2025 | F7: DOST-TAPI, LEAD Unit | G7: 1300000
A8: 2025 | B8: 2025-34 | C8: APPROVAL | D8: IMPAKT | E8: Indonesia Inventors’ Day 2025 | F8: NICE Winners and DOST-funded/supported Start-ups
A9: 2025 | B9: 2025-35 | C9: APPROVAL | D9: LEAD | E9: 2025 Regional Science, Technology, and Innovation Week Celebration in Bicol: "Building a Smart and Sustainable Communities | F9: DOST-Region V | G9: 300000
A10: 2025 | B10: 2025-37 | C10: APPROVAL | D10: IMPAKT | E10: 2025 Gawad Alunig x Dalumat | F10: DOST-TAPI TIPD
A11: 2025 | B11: 2025-38 | C11: APPROVAL | D11: LEAD | E11: 2025 Regional Science, Technology, and Innovation Week (RSTW) Celebration in the Region VII | F11: DOST-Region VIII | G11: 300000
A12: 2024 | B12: 2024-13 | C12: APPROVAL | D12: CIMU | E12: 49TH GENEVA INTERNATIONAL EXHIBITION OF INVENTIONS | F12: IDENTIFIED DOST-TAPI NICE WINNER AND DOST-ATTACHED AGENCIES | G12: 2865280
A13: 2024 | B13: 2024-18 | C13: APPROVAL | D13: CIMU | E13: WorldInvent Singapore 2024 | F13: Identified Filipino inventors and innovators,DOST RDIs and Technicom starup | G13: 1580913
A14: 2024 | B14: 2024-19 | C14: APPROVAL | D14: SCUPRU | E14: 2024 National Invention Contest and Exhibits (NICE) | F14: ISTE Program,TIPD DOST-TAPI Bicutan, Taguig | G14: 1307000
A15: 2024 | B15: 2024-20 | C15: APPROVAL | D15: ISTE | E15: 2024 Regional Science and Technology Week IVB | F15: DOST-MIMAROPA | G15: 200000
A16: 2024 | B16: 2024-29 | C16: APPROVAL | D16: ISTE | E16: 2024 Regional Science Technology and Innovation Week (RSTW) Celebration in Region I | F16: DOST Region I | G16: 300000
A17: 2024 | B17: 2024-32 | C17: APPROVAL | D17: ISTE | E17: 2024 Regional Science Technology and Innovation Week (2024 RSTW) | F17: DOST Region VIII | G17: 200000
A18: 2024 | B18: 2024-40 | C18: APPROVAL | D18: SCUPRU | E18: 2024 Gawad Alunig x Dalumat | F18: DOST-NCR | G18: 631500
A19: 2024 | B19: 2024-41 | C19: APPROVAL | D19: ISTE | E19: 2024 Regional Science Technology, and Innovation Week(RSTW) Celebration in the Cordillera Administrative Region | F19: DOST-CAR | G19: 300000
A20: 2024 | B20: 2024-43 | C20: APPROVAL | D20: CIMU | E20: National Science and Technology Fair (NSTF) Thailand 2024 | F20: Indentified Filipino Inventors and Innovators, DOST RDIs | G20: 266000
A21: 2024 | B21: 2024-44 | C21: APPROVAL | D21: ISTE | E21: Fabrication of Booth System for the Conduct of RSTiW | F21: DOST-II | G21: 300000
A22: 2024 | B22: 2024-47 | C22: APPROVAL | D22: ISTE | E22: Regional Forum on Innovative and Emerging Technologies to Address Climate Change and Workshop on Strategic Approaches to Assessing Market Potential for Technology Innovations | F22: UN-APCTT | G22: 1652500
... A27: 2024 | B27: 2024-67 | C27: APPROVAL | D27: ISTE | E27: Exhibit Space Registration for the Consumer Electronic Show (CES 2025) | F27: Consumer Technology Association, CES 2025 | G27: 4050000
A28: 2023 | B28: 44958 | C28: APPROVAL | D28: ACU-I | E28: ACU-i Campaign 2023 | F28: DOST ROs and Eligible Proponents | G28: 1835300
A29: 2023 | B29: 45078 | C29: APPROVAL | D29: ACU-N | E29: ACU-n's Marketing Campaign for DOST-TAPI's Technopreneurship Programs | F29: DOST ROs and Eligible Proponents | G29: 1500000
A30: 2023 | B30: 45139 | C30: APPROVAL | D30: ISTE | E30: International Ecotourism Travel Mart (IETM 2023) | F30: International School of Sustainable Tourism (ISST) | G30: 85000
A31: 2023 | B31: 45231 | C31: APPROVAL | D31: ACU-I | E31: Gawad Alunig x Dalumat for RICE | F31: DOST Regional Offices | G31: 2087500
A32: 2023 | B32: 2023-15 | C32: APPROVAL | D32: ISTE | E32: RSTW in DOST IV-B | F32: DOST IV-B | G32: 200000
A33: 2023 | B33: 2023-24 | C33: APPROVAL | D33: ISTE | E33: PUP ARAW 2023 | F33: PUP | G33: 50050
A34: 2023 | B34: 2023-39 | C34: APPROVAL | D34: ISTE | E34: 2023 Regional Science and Technology Week (RSTW) Celebration in Cagayan Valley | F34: DOST-Region II | G34: 200000
A35: 2023 | B35: 2023-68 | C35: APPROVAL | D35: ISTE | E35: Zamboanga Peninsula Regional Science, Technology, and Innovation Week 2023 (ZamPen RSTW 2023) | F35: DOST-IX | G35: 200000
A36: 2023 | B36: 2023-69 | C36: APPROVAL | D36: ISTE | E36: 2023 Regional Invention Contest and Exhibits by Cluster (ClusteRICE) in Northern Luzon | F36: DOST-Region I | G36: 355200
A37: 2023 | B37: 2023-73 | C37: APPROVAL | D37: ISTE | E37: 2023 Regional Invention Contest and Exhibits by Cluster (ClusteRICE) in Mindanao | F37: DOST X | G37: 225200
A38: 2023 | B38: 2023-74 | C38: APPROVAL | D38: ISTE | E38: 2023 Regional Science, Technology, and Innovation week (RSTW) in Region I | F38: DOST I | G38: 200000
A39: 2023 | B39: 2023-75 | C39: APPROVAL | D39: ISTE | E39: 2023 Regional Science, Technology, and Innovation week (RSTW) in Region 10 | F39: DOST X | G39: 200000
A40: 2023 | B40: 2023-76 | C40: APPROVAL | D40: ISTE | E40: Seoul International Invention Fair (SIIF 2023) | F40: DOST-TAPI | G40: 699920.26
A41: 2023 | B41: 2023-77 | C41: APPROVAL | D41: ISTE | E41: 2023 EVSTI | F41: DOST VIII | G41: 200000
A42: 2023 | B42: 2023-78 | C42: APPROVAL | D42: CCU | E42: Guidelines and Photography | F42: DOST-TAPI
A43: 2023 | B43: 2023-80 | C43: APPROVAL | D43: ISTE | E43: National Inventor's Week | F43: FIS, Inc. | G43: 772080
A44: 2022 | B44: 44562 | C44: APPROVAL | D44: ISTE-GENERAL | E44: Dubai Expo Science and Technology Forum/Webinar | F44: Institutional Support for Technology Exposition (ISTE) Program TIPD DOST-TAPI Bicutan, Taguig | G44: 393300
A45: 2022 | B45: 2022-22 | C45: APPROVAL | D45: ACU | E45: ACU-n's Communication Plan for the Technology Innovation for Commercialization (TECHNICOM) Program | F45: Applied Communications Unit | G45: 1203000
A46: 2022 | B46: 2022-38 | C46: APPROVAL | D46: ACU-N | E46: ACU-n's Call for Proposal | F46: DOST-TAPI | G46: 75130
A47: 2022 | B47: 2022-52 | C47: APPROVAL | D47: ISTE-RSTW | E47: 2022 Eastern Visayas Regional Science and Technology Week (RSTW) Celebration | F47: DOST VIII | G47: 200000
A48: 2022 | B48: 2022-56 | C48: APPROVAL | D48: ISTE-CARAVAN | E48: DOST Stakeholders' Forum and Caravan for Region IV-A | F48: DOST IV-A | G48: 300000
A49: 2022 | B49: 2022-58 | C49: APPROVAL | D49: ACU-N | E49: Technobyahe in Bohol Cum DOST-TAPI Milestone Event: Deed of Conveyance Signing Ceremony for JZ Jewelry Repair Shop | F49: DOST-TAPI
A50: 2022 | B50: 2022-61 | C50: APPROVAL | D50: ISTE-RSTW | E50: NSTW in CAR | F50: DOST CAR | G50: 200000
A51: 2022 | B51: 2022-62 | C51: APPROVAL | D51: ISTE-INV ORG | E51: 2022 Inventors Summit and Strategic Planning | F51: Rizal Inventors and Innovators Society, Inc. (RIISI) | G51: 350500
A52: 2022 | B52: 2022-63 | C52: APPROVAL | D52: ACU-N | E52: Addiotnal Budget Technobyahe in Bohol Cum DOST-TAPI Milestone Event: Deed of Conveyance Signing Ceremony for JZ Jewelry Repair Shop | F52: DOST-TAPI
A53: 2022 | B53: 2022-74 | C53: APPROVAL | D53: ISTE-CARAVAN | E53: DOST Stakeholders' Forum and Caravan for Region I | F53: DOST Region I | G53: 300000
A54: 2022 | B54: 2022-75 | C54: APPROVAL | D54: ISTE-RSTW | E54: National Science and Technology Week (NSTW) Celebration in Region I | F54: DOST Region I | G54: 200000
A55: 2022 | B55: 2022-84 | C55: APPROVAL | D55: ISTE-RSTW | E55: NSTW sa Amihanang Mindanao to Promote Science and Innovation in Region X | F55: DOST Region X | G55: 200000
A56: 2022 | B56: 2022-85 | C56: APPROVAL | D56: ISTE-INV ORG | E56: NIW 2022 | F56: FIS, Inc. | G56: 1720880
A57: 2022 | B57: 2022-97 | C57: APPROVAL | D57: ISTE-RSTW | E57: Stakeholders' Forum and Caravan in DOST Region IX | F57: DOST IX | G57: 300000
A58: 2021 | B58: 2021-17 | C58: APPROVAL | D58: ACU-I | E58: WACAS: Week-Long Accomplishment and Culminating Activity of Special Projects | F58: Technology Application and Promotion Institute (DOST-TAPI) | G58: 1232386.1
A59: 2021 | B59: 2021-27 | C59: APPROVAL | D59: ISTE-NSTW | E59: Promoition of DOST Technologies and DOST 7 Programs, Project & Services for the Celebration of the 2021 National Science and technology Week | F59: DOST Region VII | G59: 200000
A60: 2021 | B60: 2021-30 | C60: APPROVAL | D60: ISTE | E60: Online Ophir 2021: Outstanding Philippine Innovation Revolution | F60: Filipino Inventors Society, Inc. | G60: 394700
A61: 2021 | B61: 2021-32 | C61: APPROVAL | D61: ISTE | E61: 2021 National Science and Technology Week (NSTW) | F61: DOST Region 1 | G61: 200000
A62: 2021 | B62: 2021-35 | C62: APPROVAL | D62: ACU-I | E62: Gawad Alunig x Dalumag: Empowering Science Stories through Citizen Journalsim | F62: Applied Communications Unit ( ACU-i), TIPD | G62: 314417.48
A63: 2021 | B63: 2021-36 | C63: APPROVAL | D63: ACU-I | E63: i-NVENTS's Book: A collection of Real Stories of Real People | F63: Applied Communications Unit ( ACU-i), TIPD | G63: 509255
A64: 2021 | B64: 2021-38 | C64: APPROVAL | D64: ISTE | E64: 2021 National Science and Technology Week (NSTW) Celebrationin Bicol Region | F64: DOST Region V | G64: 200000
... A78: 2021 | B78: 2021-77 | C78: APPROVAL | D78: ACU-i | E78: Chapter Zero i-KNOW-vation Institutional Campaign | F78: Applied Communications Unit ( ACU-i), TIPD | G78: 2789448.9
A79: 2021 | B79: 2021-83 | C79: APPROVAL | D79: ACU-i | E79: Humans of TAPI | F79: DOST-TAPI
A80: 2020 | B80: 43983 | C80: APPROVAL | D80: ISTE | E80: Nationwide S&T Promotion and Exhibits in SM Supermalls (Part II) | F80: Technology Application and Promotion Institute | G80: 1000000
A81: 2020 | B81: 44013 | C81: APPROVAL | D81: ISTE | E81: Innovation on Disaster Preparedness and Response Expo | F81: Technology Application and Promotion Institute | G81: 2590000
A82: 2020 | B82: 2020-18 | C82: APPROVAL | D82: ACU-i | E82: i-Invent (Inventions' Innovation for a Noble Vision of an Entrepreneurial Nation for Tomorrow | F82: Applied Communications Unit for Inventors (ACU-i) Tachnology Information and Promotion DIvision (TIPD) DOST TAPI | G82: 1000000
A83: 2020 | B83: 2020-05-memo | C83: APPROVAL | D83: ACU | E83: Promotion of Assistance for the Commercialization of Technologies among Businesses (PACT-Biz) | F83: ACU for Micro, Small and Medium (ACU-msm) Enterprises | G83: 200000
A84: 2020 | B84: 2020-03-Ad referenda | C84: APPROVAL | D84: ACU-i | E84: I-Invent Marketing Plan | F84: ACU-I-DOST-TAPI | G84: 1000000
A85: 2019 | B85: 43647 | C85: APPROVAL | D85: ISTE | E85: 2019 Regional Science and Technology July 4-6, 2019 | F85: DOST REGION XI | G85: 200000
A86: 2019 | B86: 43678 | C86: APPROVAL | D86: ISTE | E86: 2019 DOST-NCR RSTW Exhibits Cum For in Promoting DOST Programs and Services October 2-4, 2019 | F86: DOST-National Capital Region Bicutan, Taguig City | G86: 200000
A87: 2019 | B87: 43709 | C87: APPROVAL | D87: ISTE | E87: Promotion of DOST Technologies and DOST VII Programs,Projects and Services for the Celebration of 2019 Regional Science and Technology Week August 14-16, 2019 | F87: DOST Region VII | G87: 200000
A88: 2019 | B88: 43739 | C88: APPROVAL | D88: ISTE | E88: Promotion of DOST CALABARZON's Program and Services in the 2019 Regional Science and Technology Week | F88: DOST IV-A CALABARZON | G88: 200000
A89: 2019 | B89: 43770 | C89: APPROVAL | D89: ISTE | E89: 2019 Regional Science and Technology November 11-15,2019 | F89: DOST-Cordillera Administrative | G89: 200000
A90: 2019 | B90: 43800 | C90: APPROVAL | D90: ISTE | E90: PCAARRD's Participation to the 2019 NSTW through Exhibits and Fora | F90: Philippine council of Agriculture, Aquatic and Natural Resources and Research Development | G90: 500000
A91: 2019 | B91: 2019-19 | C91: APPROVAL | D91: ISTE | E91: Orientation on WIPO Publications: "Intangible Capital in Global Value Chains" and GLobal Innovation Index 2019 Energizing the World with Innovation | F91: DOST-TAPI | G91: 130600
A92: 2019 | B92: 2019-50 | C92: APPROVAL | D92: ISTE | E92: National Inventors' Week Celebration in Region III | F92: Dr. Julius Caesar v. Sicat Regional Director DOST Region III | G92: 500000
A93: 2019 | B93: 2019-51 | C93: APPROVAL | D93: ISTE | E93: 2019 National Inventors' Week Celebration of Filipino Inventors Society, Inc. | F93: Filipino Inventors Society, Inc. | G93: 500000
A94: 2019 | B94: 2019-09-Ad ref | C94: APPROVAL | D94: ISTE | E94: Polcy Forum on the Increasing Public's Level of Awarnes on HIV/AIDS through Digitized Arts | F94: DOST-NRCP | G94: 100000
A95: 2019 | B95: 2019-12-Ad ref | C95: APPROVAL | D95: ISTE | E95: 1st Environmental Innovative Forum to Compliance, Part 1b | F95: Filipino Inventors and Innovators Society, Inc. | G95: 58000
A96: 2019 | B96: 2019-13-Ad ref | C96: APPROVAL | D96: ISTE | E96: Celebration of 2019 National Science and Technology Week in Region 1 | F96: DOST-Region 1 | G96: 200000
A97: 2019 | B97: 2019-14-Ad ref | C97: APPROVAL | D97: ISTE | E97: Regional Celebration of the 2019 NSTW | F97: DOST-Region 3 | G97: 200000
A98: 2019 | B98: 2019-15-Ad ref | C98: APPROVAL | D98: ISTE | E98: 2019 RSTW Celebration in Bicol Region | F98: DOST-Region 5 | G98: 200000
A99: 2019 | B99: 2019-16-Ad ref | C99: APPROVAL | D99: ISTE | E99: 2019 RSTW in Region VIII | F99: DOST-Region 8 | G99: 200000
A100: 2019 | B100: 2019-17-Ad ref | C100: APPROVAL | D100: ISTE | E100: 2019 RSTW in Region II | F100: DOST-Region 2 | G100: 200000
A101: 2019 | B101: 2019-18-Ad ref | C101: APPROVAL | D101: ISTE | E101: 2019 RSTW in MIMAROPA | F101: DOST-MIMAROPA | G101: 200000
A102: 2019 | B102: 2019-19-Ad ref | C102: APPROVAL | D102: ISTE | E102: 2019 RSTW in Region VI | F102: DOST-Region 6 | G102: 200000
... A127: 2019 | B127: 2019-72 | C127: APPROVAL | D127: ISTE | E127: National Inventors Week (NIW) 2019 CALABARZON | F127: Rizal Inventors and Innovators Society, Inc. (RIISI) | G127: 287052
A128: 2018 | B128: 43101 | C128: Approval | D128: ISTE | E128: 2018 National Invention Contest and Exhibits (NICE) | F128: Technology Application and Promotion Institute (TAPI) | G128: 2747800
A129: 2018 | B129: 43405 | C129: Approval | D129: ISTE | E129: 2018 Manila Science and Technology Fair and Exhibits (PAMAMASON Cluster S&T Fair) | F129: DOST- National Captial Region | G129: 200000
A130: 2018 | B130: 43435 | C130: Approval | D130: ISTE | E130: Celebration of 2018 National Science and Technology Week in Region I | F130: DOST Region I | G130: 200000
A131: 2018 | B131: 2018- 13 | C131: Approval | D131: ISTE | E131: 2018 Regional Science and Technology Week | F131: DOST Region II | G131: 200000
A132: 2018 | B132: 2018-14 | C132: Approval | D132: ISTE | E132: 2018 Regional Science and Technology Week | F132: DOST Region III | G132: 200000
A133: 2018 | B133: 2018-15 | C133: Approval | D133: ISTE | E133: 2018 Regional Science and Technology Week | F133: DOST Region IV-A (CALABARZON) | G133: 200000
A134: 2018 | B134: 2018-16 | C134: Approval | D134: ISTE | E134: 2018 Regional Science and Technology Week | F134: DOST MIMAROPA (IV-B) | G134: 200000
A135: 2018 | B135: 2018-17 | C135: Approval | D135: ISTE | E135: 2018 Regional Science and Technology Week Celebration | F135: DOST Region V | G135: 200000
A136: 2018 | B136: 2018-18 | C136: Approval | D136: ISTE | E136: Promotion of DOST 7-Assisted Projects and Technical Services for te Celebration of 2018 National Science and Technology Week | F136: DOST Region VII | G136: 200000
A137: 2018 | B137: 2018-19 | C137: Approval | D137: ISTE | E137: 2018 Regional S&T Fair and Exhibits | F137: DOST Region VIII | G137: 200000
A138: 2018 | B138: 2018-20 | C138: Approval | D138: ISTE | E138: 2018 Regional NSTW Celebration Caraga Region in Promoting | F138: DOST CARAGA | G138: 200000
A139: 2018 | B139: 2018-23 | C139: Approval | D139: ISTE | E139: Fabrication of FNRI Exhibit Materials for the 2018 National Science and Technology Week | F139: Food and Nutrition Research Institute (FNRI) DOST Compound | G139: 200000
A140: 2018 | B140: 2018-24 | C140: Approval | D140: ISTE | E140: Production and Fabricaton FPRDI Exhibits for the 2018 Department of Science and Technology's Annual Science and Technology Week Celebration | F140: Forest Products Research and Development Institute (FPRDI) | G140: 200000
A141: 2018 | B141: 2018-25 | C141: Approval | D141: ISTE | E141: Production of ITDI Exhibit Module for the 2018 National Science and Technology Week | F141: Industrial Technology Development Institute (ITDI) | G141: 200000
...

Sheet LU-STARTUPS
A1: Year | B1: Resolution No: | C1: TYPE | D1: Program | E1: Approval Date | F1: Project Title | G1: Name of Proponent | H1: Address | I1: Contact Details | J1: Amount | K1: CLASS | L1: STATUS | M1: POSSIBLE FOLLOW UP ASSITANCE

Sheet LEGAL-Projects (2018-2025)
A1: Year | B1: Resolution No: | C1: Type | D1: Program | E1: Project Title | F1: Name of Proponent | G1: Amount of Investment
A2: Year | B2: Resolution No: | C2: Type | D2: Program | E2: Project Title | F2: Name of Proponent | G2: Amount of Investment
A3: 2024 | B3: 2024-34 | C3: APPROVAL | D3: ACCREDITATION | E3: Innovation Drive | F3: Filipino Inventors Society Cordillera Administrative Region (FISCAR), inc. | G3: 100000
A4: 2024 | B4: 2024-48 | C4: APPROVAL | D4: ACCREDITATION | E4: Filipino Inventors' Organization Gathering: A Meeting of Innovative Minds | F4: FISPC | G4: 320000
A5: 2024 | B5: 2024-85 | C5: APPROVAL | D5: ACCREDITATION | E5: Stakeholders Meeting and Discussion on the Proposed Revision of RA 7459 IRR | F5: Filipino Inventors Society Producers Cooperative (FISPC) | G5: 100000
A6: 2024 | B6: 2024-86 | C6: APPROVAL | D6: ACCREDITATION | E6: Stakeholders Meeting and Discussion on the TAPI Administrative Order No. 004, Series of 2023 or the Revised Guidelines for the Expanded Inventors' Organization Accreditation Program | F6: Filipino Investors & Innovators (FIISI) Inc. | G6: 100000
A7: 2023 | B7: 2023-14 | C7: APPROVAL | D7: ACCREDITATION | E7: Approval of request of Travel Assistance for FIS, Inc.’s Participation in the IFIA 37th General Assembly | F7: FIS, Inc. | G7: 100000
A8: 2023 | B8: 2023-16 | C8: APPROVAL | D8: ACCREDITATION | E8: Deployment of FISCAR-developed technologies for use by Smith Valley Agriculture Cooperative | F8: FISCAR | G8: 100000
A9: 2023 | B9: 2023-22 | C9: APPROVAL | D9: ACCREDITATION | E9: Acquisition of Equipment to be used for AutoCAD 1-Design Projects for RISSI members | F9: Rizal Inventors and Innovators Society, Inc. (RIISI) | G9: 100000
A10: 2023 | B10: 2023-84 | C10: APPROVAL | D10: ACCREDITATION | E10: Capacity Building and Workshop for RISE, Inc. | F10: Researchers, Inventors, Scientists, Entrepreneurs of the Philippines, Inc. (RISE) | G10: 970480

Sheet CONSOLIDATED-ASSISTED STARTUP
A1: Year | B1: Resolution No: | C1: TYPE | D1: Program | E1: Approval Date | F1: Project Title | G1: Name of Proponent | H1: Address | I1: Contact Details | J1: Amount | K1: CLASS | L1: POSSIBLE FOLLOW UP ASSITANCE
A2: 2025 | B2: 2025-29 | C2: APPROVAL | D2: EVFP | E2: 45832 | F2: Commercialization of GradeChum: An AI-Powered Platform for Automatic Evaluation of Handwritten Activities | G2: MR. JEMAR JUDE A. MARANGA President and CEO CODECHUM SOFTWARE SOLUTIONS INC. | H2: 753 Katipunan St., Tisa, Cebu City, Cebu, Philippines | I2: jude@codechum.com 639959469610 | J2: 4500000 | K2: STARTUP
A3: 2024 | B3: 2024-79 | C3: APPROVAL | D3: EVFP | E3: 45586 | F3: Bio-Based Polyurethene Adhesive System for Coconut Coir Board Production | G3: Kenno Michael M. Uy CEO Lesstics Inc | H3: 0014 Matthew St. Bahayan, Luinab, Iligan City | I3: Cell No.: 0917-162-2127 Email: lesstics@gmail.com | J3: 4551960 | K3: STARTUP
A4: 2024 | B4: 2024-60 | C4: APPROVAL | D4: EVFP | E4: 45558 | F4: HOCLOMAC: Product Certification, Inventory, and Sales | G4: Dr. Francis Aldrine A. Uy President and CEO USHER Technologies, Inc. | H4: 1409 Corporate 145, Mother Ignacia St., South Triangle, Quezon City | I4: drfrancisuy@gmail.com | J4: 4143400.5 | K4: STARTUP
A5: 2024 | B5: 2024-51 | C5: APPROVAL | D5: EVFP | E5: 45544 | F5: Commercialization of Cerebro Plus: An Integrated School Management and Content Library System for k-12 Schools | G5: Jonald Justine U. Itugot Chief Executive Officer Cerebro Solutions, Inc. | I5: justine@cerebro.ph +63 917 886 5402 | J5: 3412000 | K5: STARTUP
A6: 2024 | B6: 2024-68 | C6: APPROVAL | D6: EVFP | E6: 45565 | F6: Enhance IP protection and Commercialization of Value-based Care Module of See You Doc Corp. under the Expanded VFP | G6: Mr. Noel Gary E. Del Castillo Founder and CEO | I6: noel@seeyoudoc.com | J6: 2332760.9 | K6: STARTUP | L6: Endorsed to NDC
A7: 2024 | B7: 2024-58 | C7: APPROVAL | D7: EVFP | E7: 45547 | F7: Enhancement of BizKit (The First Local Centralized Business Suite) To Better Facilitate Cross-functional And Holistic Business Operations In The New Normal | G7: Marc Carlo Lijauco President BizKit Technologies Inc. | H7: 96 Burgos St. Pamplona Uno Las Piñas City 1740 | I7: mclijauco@bizkittechnologies.com | J7: 4000000 | K7: STARTUP | L7: Endorsed to NDC
A8: 2024 | B8: 2024-87 | C8: APPROVAL | D8: EVFP | E8: 45609 | F8: Scale up of Fullmight Agricultural Corp. Operations and Product Certification | G8: Dr. Virginia M. Padilla Secretary and Treasurer Fullmight Agricultural Corp. | H8: 6th Street, 1856 Hillside Village Subdivision, Brgy. Tuntungin-Putho, Los Baños Laguna | I8: Tel. no.: (049) 508-0557 CP no.: 0917-887-8542, 0917-179-8542 Email: padilla7.jaime@gmail.com, virgiem.padilla@gmail.com | J8: 4771250 | K8: STARTUP | L8: Endorsed to NDC
A9: 2024 | B9: 2024-84 | C9: APPROVAL | D9: EVFP | E9: 45601 | F9: Scale-Up Assistance for WEHLO Technologies, Inc. under E-VFP | G9: Dr. Cris Edward Monjardin Chief Technology Technology WEHLO Resilience Technology Corporation Inc. | H9: Unit 1409, Corporate 145, 145 Mother Ignacia St., Brgy. South Triangle, Quezon City | I9: 09692314619 cefmonjardin@mapua.edu.ph | J9: 4.975,000.00 | K9: STARTUP | L9: Endorsed to NDC
A10: 2024 | B10: 2024-90 | C10: APPROVAL | D10: EVFP | E10: 45637 | F10: Scale-up Operational Assistance to Hiraya Technology Solutions, Inc. | G10: Mr. Stephen L. Larcia Chief Executive Officer Hiraya Technology Solutions, Inc. | H10: 502-503 Jocfer Building, Commonwealth Ave., Quezon City | I10: Cell No.: (02) 8826 6836 Email: stephen@hirayatech.ai; info@hirayatech.ai | J10: 4000000 | K10: STARTUP | L10: Endorsed to NDC
A11: 2024 | B11: 2024-80 | C11: APPROVAL | D11: EVFP | E11: 45595 | F11: Scaleup of CHRG Inc. Operations and Product Certifications | G11: Engr. Leo Allen S. Tayo CEO and President CHRG Electric vehicle technologies Inc | H11: 3F, Enterprise Incubation Room, National Engineering Center, Osmena Ave, UP Campus, Diliman, Quezon City. | I11: Engr. Leo Allen S. Tayo – 09272103449 Engr. Rovinna Janel Tayo – 09297193619 leo@chrg.tech / janel@chrg.tech | J11: 5000000 | K11: STARTUP | L11: Endorsed to NDC
A12: 2024 | B12: 2024-57 | C12: APPROVAL | D12: EVFP | E12: 45547 | F12: Scaling up for Market Expansion and Customer Retention | G12: Ms. Ralen Rose Gloria L. Malatbalat COO, making.technology Manufacturing Corporation | H12: UPSCALE G/F National Engineering Center, F. Agoncillo St., cor. Osmena Ave., U.P. Campus, Diliman, Quezon City, 1101 | I12: ralen@makingtech.co / inquire@makingtech.co | J12: 4668619.3 | K12: STARTUP | L12: Endorsed to NDC
A13: 2025 | B13: 2028-18 | C13: APPROVAL | D13: GALING | E13: 2025 | F13: Magicbag: Wireless slow cooker | G13: Ms. Rowena Faith Armeniana Sucalit 4423 Montojo St. Tejeros, Makati City | I13: weng747@yahoo.com 0916-777-8031 | J13: 229654 | K13: STARTUP
A14: 2024 | B14: 2024-89 | C14: APPROVAL | D14: GALING | E14: 45625 | F14: Marissa Turbine: Vertical-Axis Tidal Turbine | G14: Mr. Patrick Roland de Guzman 65 Lawa, Obando, Bulacan | I14: deguzmanpatrickroland@gmail.com 09974916634 | J14: 395212 | K14: STARTUP
A15: 2024 | B15: 2024-36 | C15: APPROVAL | D15: GALING | E15: 45469 | F15: Technology Validation of Unas Canvas (UnVas) | G15: Julienne Fabie-Agapin Lumbia District, Pagadian City | I15: juliennestephanie.agapin@wmsu.edu.ph 09362660139 | K15: STARTUP | L15: Endorsed to NDC
A16: 2024 | B16: 2024-54 | C16: APPROVAL | D16: GALING | E16: 45544 | F16: Technology Validation of IOT Artificial Intelligence-Based Dosing System in Greenhouse | G16: Mr. Alvin Phoebe Artemis A. Valdez Interior Fidelidad Street, Barangay 1, Balayan, Batagas 4213 | I16: alvinphoebeartemis@gmail.com +639918781878; +639916453232 | J16: 236341.77 | K16: STARTUP | L16: Endorsed to NDC
A17: 2023 | B17: 2023-79 | C17: APPROVAL | D17: GALING | E17: 45225 | F17: Improved KoolGear | G17: Mr. Ivan Brent Nara Bldg. 23, UP Bliss, Diliman, Quezon City | I17: naraivanbrent@gmail 09751905598 | J17: 96107 | K17: STARTUP
A18: 2023 | B18: 2023-66 | C18: APPROVAL | D18: GALING | E18: 45154 | F18: Foldable Water Tank with Zeramic Filter | G18: Ms. Eleanor M. Olegario | H18: 17 Cavite Street, Bonifacio Village, Brgy. Pasong Tamo, Quezon City | I18: eleanor.olegario@gmail.com 09209129187 | J18: 191500 | K18: STARTUP
A19: 2023 | B19: 2023-30 | C19: APPROVAL | D19: GALING | E19: 45086 | F19: Technology Validation of Pili Seal | G19: Engr. Mark Kennedy E. Bantugon | I19: markkennedy09bantugon@gmail.com andpili.adheseal@gmail.com | J19: 349799.56 | K19: STARTUP
A20: 2025 | B20: 2025-17 | C20: APPROVAL | D20: GALING | F20: Fabrication, and Installation of a 50W LED Flood Light Post with Integration of Small-scale Savonius-Type Helical Vertical Axis Wind Turbine (VAWT) and Solar Panel | G20: Engr. Jose Luis L. Villalon | H20: 25 Mercury, Zytek-Riosa, Brgy. Pasong Tamo, Quezon City, 1107 | I20: louie.vdaliinnovations@gmail.com +63 915 126 5571 | J20: 358538 | K20: STARTUP
A21: 2022 | B21: 2022-109 | C21: APPROVAL | D21: ITECH | E21: 29/12/2022 | F21: Commercialization of Maker-scope | G21: MR. JEREMY C. DE LEON | J21: 1083679 | K21: STARTUP | L21: The request was withdrawn during LANDBANK evaluation due to personal circumstances of the proponent; Invited to apply for I-TECH 2.0
A22: 2025 | B22: NA | C22: PAC | D22: TECHNICOM | E22: 2025 | F22: Commercialization and Scaling of Duon’s Real-Time Indoor Navigation with Foot Traffic Behavioral Analysis and Prediction AI | G22: MR. GABRIEL ANTON D. ANGELES, Project Leader DUON TECHNOLOGIES INCORPORATED | H22: 7F, Panorama Tower 34th Street, corner Lane A, Taguig, 1634 Metro Manila | I22: gda4993@gmail.com, admin@duon.ph 9773470628 | J22: 7175464 | K22: STARTUP
A23: 2025 | B23: NA | C23: PAC | D23: TECHNICOM | E23: 2025 | F23: COMMERCIAL PROTOTYPING OF SMART WATER (IOT) METER (SWIM) | G23: CONRADO D. CAMILON JR, Project Leader ALEXA’S ENGINEERING SERVICES | I23: cdcamilonjr@gmail.com 09224074861/049-501-4583 | J23: 4998689 | K23: STARTUP
A24: 2025 | B24: NA | C24: PAC | D24: TECHNICOM | E24: 2025 | F24: Rezbin: Business Model Validation and Market Acceptability Testing for Low Cost AI-powered Bins as an Alternative to Expensive Reverse Vending Machines in Metro Manila | G24: Matthew Cristi C. Martirez, Project Leader Rezbin Waste Technology Inc. | I24: mari@rezbin.ph, hello@rezbin.ph 639178920234 | J24: 4999988 | K24: STARTUP | L24: For endorsement to NDC
A25: 2025 | B25: NA | C25: PAC | D25: TECHNICOM | E25: 2025 | F25: Technological Improvement and Field Testing of Bamboo-based Biodegradable Period Care | G25: Alexandra B. Jocom, Project Leader BioTerra Corp. (Halia) | I25: alexa@halia.co 639764896618 | J25: 5000000 | K25: STARTUP
A26: 2025 | B26: NA | C26: PAC | D26: TECHNICOM | E26: 2025 | F26: Scaling Up and Deployment of the Multi-Drum Chamber Carbonization System for Sustainable Charcoal Production in the Philippines | G26: Julieane M. Fernandez, Project Leader Eco-Uling by Project Lily Inc. | I26: ayafernandez.ecouling@gmail.com 0915-795-1534 | J26: 4884739 | K26: STARTUP
A27: 2025 | B27: NA | C27: PAC | D27: TECHNICOM | E27: 2025 | F27: Optimizing Bamboo Processing: 2-IN-1 Furnace For Pole Treatment and Valorization of Silica-Rich Bamboo Ash | G27: Anneth Rigon BAMBOO IMPACT LAB OPC | I27: anneth@bambooimpactlab.com 0919-999-0488 | J27: 4993468 | K27: STARTUP
A28: 2024 | B28: 2024-71 | C28: APPROVAL | D28: TECHNICOM | E28: 45574 | F28: Automated Coconut Sap Extraction: Enhancing Productivity and Quality Through Innovative Technology | G28: Luzmar M. Gabor KASAKA Agriventures, Inc. | I28: asaka@aim.edu 9175305742 | J28: 2998072 | K28: STARTUP | L28: Endorsed to NDC
A29: 2024 | B29: 2024-78 | C29: APPROVAL | D29: TECHNICOM | E29: 45581 | F29: Enhancement and Market Validation of AI-Powered Property Management Solutions for the Philippines | G29: Mr. Jesehl Charles Basco Project Leader Collo/Proprty Technology Solutions Inc. | I29: jay@collo.ph 9178327166 | J29: 2911170 | K29: STARTUP
A30: 2024 | B30: 2024-82 | C30: APPROVAL | D30: TECHNICOM | E30: 45601 | F30: Enhancement, Market Validation, and Pilot Production of AI-Driven Farm Management Module (AID-FMM) | G30: Ms. Lorilyn P. Daquioag Project leader Waste4Good technologies | I30: lurelynpablo@gmail.com lorilyn.daquioag@eee.upd.edu.ph 639385504997 | J30: 2384720 | K30: STARTUP
A31: 2024 | B31: 2024-88 | C31: APPROVAL | D31: TECHNiCOM | E31: 45609 | F31: Improvement and Pilot Testing of Alerto PH AI-as-a-Service (AlaaS) | G31: Ms. Cristina Macaraig WiredField Philippines Inc. | I31: cristina@wiredfield.com | J31: 2975715 | K31: STARTUP
A32: 2024 | B32: 2024-74 | C32: APPROVAL | D32: TECHNICOM | E32: 45574 | F32: Market Testing of Online Residential Rental Marketplace for Filipino Students and Young Professionals | G32: Alyssa Casandra Wee Project Leader/ Krelio Technologies Inc. | I32: alyssa@dormy.ph, hello@dormy.ph 0992 681 6544 | J32: 2999945.7 | K32: STARTUP
A33: 2024 | B33: 2024-27 | C33: APPROVAL | D33: TECHNICOM | E33: 45441 | F33: Pilot Testing and Technology Validation of Fortified Powdered Coconut Milk as a Powdered Dairy Alternative to Lactose Intolerant and Nutrient Deficient Filipino Children and Adults | G33: Samuel Antonius De Chavez Tecuala Dehusk | H33: Martel Bldg. Verdon Parc, Unit 716 Ecoland Drive, Talomo, Bucana, Davao Del Sur, Davao City, 8000 | I33: samuel.tecuala@dehusk.com.ph 09565734432 | J33: 2789556 | K33: STARTUP
A34: 2024 | B34: 2024-31 | C34: APPROVAL | D34: TECHNICOM | E34: 45448 | F34: Scaling up Testing of a Peer-to-Peer Car Sharing Marketplace for the Filipino Car Sharing Economy | G34: Mr. Miguel Locsin Project Leader DOON Transport Technologies Inc. | H34: Unit 302, 5048 P. Burgos Street, Draper Startup House for Entrepreneurs, Brgy. Poblacion, Makati City, Fourth District, NCR 1210 / | I34: miguel@doon.ph 09178076499 | J34: 2896644 | K34: STARTUP
A35: 2024 | B35: 2024-26 | C35: APPROVAL | D35: TECHNICOM | E35: 45441 | F35: The Scrapcycle PH field and Market Testing of Scrap Trading Dynamics Across Philippine Urban Landscapes | G35: Genevieve P. Navales/Female Project Leader, ScrapCycle PH | I35: vievenavales29@gmail.com 09952033203 | J35: 2785599 | K35: STARTUP
A36: 2023 | B36: 2023-81 | C36: APPROVAL | D36: TECHNICOM | E36: 45225 | F36: Technology and business validation of an advanced web and mobile Point-of-Sale (POS) software-as-a-service (SAAS) application for Philippine micro and small retail businesses | G36: Renzo Navarro Ducusin Project Leader IOL, Inc. | H36: Rm 404 Jose Miguel Bldg. Yandoc St., Baguio City. Philippines | I36: kevin@iolph.com 074-6209538 | J36: 2715682.8 | K36: STARTUP
A37: 2023 | B37: 2023-83 | C37: APPROVAL | D37: TECHNICOM | E37: 45236 | F37: Determining the Pesticide Residue Level of Mangoes using a smart metal oxide nanosensor for Post-Harvest Applications | G37: Ms. Normie Jean Sajor Lacubtan Project Leader Anihan Technologies Inc. | I37: njsajor@gmail.com f.normiejean.lacubtan@cmu.edu.ph | J37: 2398683 | K37: STARTUP
A38: 2023 | B38: PAC | C38: APPROVAL | D38: TECHNICOM | E38: 45275 | F38: Scaling Digital Clustering Solution for Enhanced Agri-Value Chain Integration of Farm Konek | G38: John Vincent Q. Gastanes Project Zacchaeus Marketing Cooperative | H38: Unit 1, CCT Building, Puerto Princesa City, Palawan, 5300/ MIMAROPA | I38: gastanesjohnvincent@gmail.com 639177979073 | J38: 7936800 | K38: STARTUP
A39: 2022 | C39: PAC | D39: TECHNICOM | F39: Commercialization of the 4Gives System | G39: Mr. Varian Sherwin Chu Vashcorp, Inc. | I39: varianchu@gmail.com | J39: 5867730.2 | K39: STARTUP | L39: EVFP
A40: 2019 | B40: NA | C40: PAC | D40: TECHNICOM 1.0 | F40: Product Design, Manufacturing and Field Scale Testing of StillFresh: Spoilage Monitoring Strip | G40: Mr. Joseph Christopher G. Doroja | I40: joseph.doroja@obf.ateneo.edu, etinhay@gmail.com | J40: 1636971 | K40: STARTUP
A41: 2019 | B41: NA | C41: PAC | D41: TECHNICOM 1.0 | F41: Integration of Data Science and Scaling Up of Payruler, a comprehensive Human Resource Management System (HRMS) | G41: Mr. Warlito Pio S. De Jesus | I41: jojo@geniihut.com, jojo@payruler.com, timmy@geniihut.com, timmy@payruler.com | J41: 3258768 | K41: STARTUP
A42: 2019 | B42: NA | C42: PAC | D42: TECHNICOM 1.0 | F42: Optimization of Virtual Reality Kit (VR Kit) for New Media Technology and Commercial Competitiveness | G42: Mr. Ryan Tan Yu | I42: ryan@mataverse.ph | J42: 4019382 | K42: STARTUP
A43: 2019 | B43: NA | C43: PAC | D43: TECHNICOM 1.0 | F43: Enhancement of the Micab Cab Hailing Engine thru Big Data Analytics | G43: Mr. Kenneth Baylosis | J43: 3135851.2 | K43: STARTUP
A44: 2019 | B44: NA | C44: PAC | D44: TECHNICOM 1.0 | F44: Scale-up Manufacturing of Biotek-M Diagnostic Kits and Post Marketing for Third Party Evaluation | G44: Dr. Raul V. Destura Denise Lacuna | I44: rvdestura@up.edu.ph jadelacuna12@gmail.com | J44: 16926594 | K44: STARTUP
A45: 2019 | B45: NA | C45: PAC | D45: TECHNICOM 1.0 | F45: Technology Enhancement and Commercialization of Exora Intellex as an Energy Analytics Machine Learning Platform for Industrial Smart Energy Management and Electricity Cost Reduction | G45: Mr. Sergius Angelo Santos Exora Technologies, Inc. | I45: sergius@exora.ph | J45: 4394800 | K45: STARTUP
A46: 2018 | B46: NA | C46: PAC | D46: TECHNICOM 1.0 | F46: Optimization of an Industry Grade Prototype of Po Lite Products | G46: Dr. Ria Liza Canlas | I46: riadear21@yahoo.com | J46: 4999045 | K46: STARTUP
A47: 2018 | B47: NA | C47: PAC | D47: TECHNICOM 1.0 | F47: Pilot Testing of a Deepwater Operation 3D Visual Mapping and Inspection System (PD-DOMAINS) | G47: Mr. Francis James Corpuz ANTIPARA Exploration Inc. | I47: franciscorpuz@gmail.com | J47: 3058155.2 | K47: STARTUP
A48: 2018 | B48: NA | C48: PAC | D48: TECHNICOM 1.0 | F48: Development of an Alternative Credit Scoring Model applying Machine Learning in Financing Farmers | G48: Mr. Ruel T. Amparo Cropital Enterprises Corporation | I48: ruel@cropital.com | J48: 3551018 | K48: STARTUP
A49: 2017 | B49: NA | C49: PAC | D49: TECHNICOM 1.0 | F49: Enhancement of Prototype and Market Readiness of R-TAP (an advanced pressure management system for water utilities) | G49: Mr. Stephen Larcia Hiraya Technology Solutions, Inc. | I49: stephen@hirayatech.ai; info@hirayatech.ai (02) 8826 6836 | J49: 4294326.4 | K49: STARTUP
A50: 2017 | B50: NA | C50: PAC | D50: TECHNICOM 1.0 | F50: Field Testing and Technology Validation of the E-Procurement Sytem (ePS) for Government Agencies | G50: Engr. Jose Rizaldy G. Harder Infodynamics Technologies | I50: (033) 321 0928 rizaldyharder@yahoo.com | J50: 1892235 | K50: STARTUP
A51: 2016 | B51: NA | C51: PAC | D51: TECHNICOM 1.0 | F51: Cost Efficient and High Quality Accelerograph for Disaster Preparedness in Buildings | G51: Mr. Rodolfo Alfonso (Ryan) Sabio Tekton Geometrix, Inc. | I51: 437-7001/ 0915 256 3355 | J51: 4736242.4 | K51: STARTUP
A52: 2024 | B52: N/A | D52: Tax and Duty Exemption | F52: Makecroscope | G52: Mr. Jeremy C. Deleon, Jeremake Online Shop | I52: jeremycdeleon@gmail.com | J52: N/A | K52: STARTUP
A53: 2021 | B53: N/A | C53: APPROVAL | D53: IBED-I | F53: Pilot Scale Production of Cooked Balut in Shell with Commercially Acceptable Shelf-life | G53: Ambrocio Kerwin A. Perez | I53: akerwinperez@gmail.com | J53: P349,800 | K53: STARTUP
A54: 2020 | B54: N/A | C54: APPROVAL | D54: IBED-I | F54: Snap On and Off Handle for a Five-Gallon Bottle Container | G54: Carlos N. Detalo, Jr. | I54: carlsdet1201976@gmail.com | J54: 161600 | K54: STARTUP

Sheet Consolidated
A1: Year | B1: Resolution No: | C1: TYPE | D1: Program | E1: Sector | F1: AmountofInvestment | G1: Approval Date | H1: Project Title | I1: Name of Proponent | J1: Address | K1: Region | L1: Description of the Project/Technology | M1: Program
A2: 2022 | B2: 44682 | C2: Guidelines | D2: ACCREDITATION | E2: Government | F2: 680240 | G2: 44588 | H2: Inventors' Organization Accreditation Project | I2: Legal Unit, Office of the Director Technology Application and Promotion Institute (TAPI) | J2: DOST Bicutan Taguig | K2: NCR | L2: Aims to accredit and recognize inventors' organizations comprising of relatively an equal number of men and women, throughout their activities pursuant to Section 8.b, Article IV of Republic Act No. 7459. | M2: IOA
A3: 2022 | B3: 44713 | C3: APPROVAL | D3: IMPROVE | E3: Government | F3: 210000 | G3: 44614 | H3: Project DOST-IMPROVISE: IP Monitoring and Protection of Rights or Ownership Against Violations and Infringements Sustained or Envisioned | I3: Legal Unit, Office of the Director Technology Application and Promotion Institute (TAPI) | J3: DOST Bicutan Taguig | K3: NCR | L3: Spesifically this project would like to protect the gains obtained from the DOST-funded projects on commercialization. | M3: IMPROVE
A4: 2022 | B4: 44743 | C4: APPROVAL | D4: DOST-TAPI | E4: DOST | F4: 310057.2 | G4: 44594 | H4: ACU-n's Call for Proposal | I4: Applied Communication Unit TIPD, DOST-TAPI Bicutan, Taguig | J4: DOST-TAPI Bicutan Taguig | K4: NCR | L4: The ACU-n seeks to strengthen the Institute's communication endeavors in delivering audience-centric key messages by integrating and utilizing all possible and appropriate media platforms, particularly targeting the non-inventor clients composed of starups, micro, small and medium entrepreneurs (MSME), student technopreneurs, and professional organizations. | M4: DOST-TAPI
A5: 2022 | B5: 44774 | C5: APPROVAL | D5: GAD | E5: Government | F5: 25200 | G5: 44614 | H5: International Day of Women and Girls in Science | I5: Gender Focal Point System -Technical Working Group | J5: DOST-TAPI Bicutan Taguig | K5: NCR | L5: This celebration recognizes that equal access to and participation in science technology and innovations of women and girls is vital in achieving gender equality. The DOST-TAPI, as one of the institutions promoting science services, supports this advocacy through its Gender Focal Point System. | M5: GAD
A6: 2022 | B6: 44805 | C6: POLICY | D6: DOST-TAPI | E6: DOST | F6: 5300 | G6: 44602 | H6: Load allowance | I6: The Proposed Load Allowance of DOST-TAPI's | J6: DOST-TAPI Bicutan Taguig | K6: NCR | L6: Strengthening the communications and operations of the DOST-TAPI Finance and Administrative Division by Providing Communication (Load) Allowance for the Division Chief and Section Chiefs. | M6: DOST-TAPI
A7: 2022 | B7: 44835 | C7: APPROVAL | D7: DOST-TAPI | E7: Government | F7: 1831800 | G7: 44608 | H7: Promotion of DOST-TAPI Programs for Filipino Inventors for CY 2022 Implementation | I7: Applied Communications Unit | J7: DOST-TAPI Bicutan Taguig | K7: NCR | L7: ACU-i was created to facilitate the promotion of programs for Filipino inventors of the Institute. The unit oversees the implementation of various marketing strategies to better popularize DOST-TAPI programs for inventors to the general audience, as well as to targeted clients. | M7: DOST-TAPI
A8: 2022 | B8: 44866 | C8: APPROVAL | D8: ISP | E8: IDEATION | F8: 19000 | G8: 44608 | H8: 1. Webinar -Workshop on Intellectual Property and Innovation for Selected Grade 4-6 Pupils in San Isidro, Davao Oriental 2. Creativity Boost and Intellectual Property Basics For Selected High School Pupils in Davao Oriental 3. Creativity Boost and Intellectual Property Basics for Selected DORSU Students | I8: DOST Region XI | J8: Corner Friendship and Dumanlas Road, Bajada Davao City | K8: XI | L8: The Technology Application and Promotion institute is supporting the development of future inventors among the youth through the conduct of workshops. The lnvent school tm aims to inculcate creative thinking and bring about inventiveness enticing the male and female pupils which aims to stimulate the creativity and innovativeness of the students and promote awareness on intellectual property rights. | M8: ISP
A9: 2022 | B9: 44896 | C9: APPROVAL | D9: IP | E9: Government | F9: 345000 | G9: 44622 | H9: DOST-TAPI's Promotional Collaterals | I9: DOST-TAPI | J9: DOST Bicutan Taguig | K9: NCR | L9: Part of the Institute's promotional activities is the corporate branding defining the corporate voice and messaging, and working out the DOST-TAPI's visual identity, | M9: IP
A10: 2022 | B10: 2022-01 | C10: APPROVAL | D10: ISTE | E10: PROMO | F10: 393300 | G10: 44573 | H10: Dubai Expo Science and Technology Forum/Webinar | I10: Institutional Support for Technology Exposition (ISTE) Program TIPD DOST-TAPI Bicutan, Taguig | J10: DOST Bicutan Taguig | K10: NCR | L10: The project aims to promote local technologies not only in Dubai markets but in other participating countries; promote DOST-assisted SME products to a wider and diverse market group and create potential consumer/customers; and serve as an avenue to explore possible collaborations/linkages with UAE and other countries in the field of S&T; | M10: ISTE-GENERAL
A11: 2022 | B11: 2022-02 | C11: APPROVAL | D11: TAPI | E11: DOST | F11: 190300 | G11: 44573 | H11: Opening of the DOST-TAPI's 35th (milestone) Anniversary | I11: DOST-TAPI Bicutan, Taguig | J11: DOST-TAPI Bicutan Taguig | K11: NCR | L11: The celebration will be graced by the DOST Secretary, Prof. Fortunato T. De La Peña, and DOST Undersecretary for Research and Development, Dr. Rowena Cristina L. Guevara, with messages of support for the Institute; During the celebration, DOST-TAPI's new Director, Atty. Marion Ivy D. Decena, will also present her vision for the Institute. | M11: TAPI
A12: 2022 | B12: 2022-03 | C12: TERMINATION | D12: TAPI | E12: DOST | G12: 44588 | H12: Termination of the Invention-Based Enterprise Development Component II (IBED II) Program | I12: DOST-TAPI | J12: DOST-TAPI | K12: NCR | L12: The said program both aim to accelerate the commercialization of innovative technologies or inventions by providing the necessary funding support IP rights owner/Assignee or technology-based start-up project. | M12: TAPI
A13: 2022 | B13: 2022-04 | C13: APPROVAL | D13: TAPI | E13: DOST | F13: 544434 | G13: 44588 | H13: Operationalization of the Screening Committee for R.A No. 7459/Project Oscar | I13: TAPI | J13: TAPI | K13: NCR | L13: In view of the travel restriction in the region brought about by the pandemic, an honorarium shall be given to a DOST Regional/Provincial staff to compensate his/her efforts in the validation and the preparation of the corresponding report. | M13: TAPI
A14: 2022 | B14: 2022-100 | C14: APPROVAL | D14: TECHNICOM | E14: TECH DEV | F14: 2353196 | G14: 44881 | H14: Pre-Commercialization of IOT-Based Monitoring System for Machine Shop | I14: Mr. Franz Joseph D. Libao | J14: MIRDC, MIRDC Compound, Gen. Santos Ave., Bicutan, Taguig | K14: NCR | L14: The projects aims to achieve the following objectives; To fabricate five(5) modules of the machine monitoring system; to conduct field testing in the identified machince shop; to evaluate the performance of the machince shop monitoring system; To establish the marketability of the developed machince monitoring system. | M14: TECHNICOM
A15: 2022 | B15: 2022-101 | C15: APPROVAL | D15: CONCEPT PROTO | E15: IDEATION | F15: 199890 | G15: 44896 | H15: Method of Composting with Automation Features | I15: Mr. Luder R. Zarate | J15: AD157 Windy Hill, Buyagan, La Trinidad, Benguet | K15: CAR | L15: To provide financial assistance under the Industry-Based Invention Development (IBID) Program for the fabrication of the commercial prototype of “Method of Composting with Automation Features” with Utility Model Registration Number 2- 2022-050394. | M15: CONCEPT PROTO
A16: 2022 | B16: 2022-102 | C16: APPROVAL | D16: IBID | E16: TECH DEV | F16: 18425 | G16: 44896 | H16: Bright Lighted Helmet | I16: Ms. Ma. Dolores Cynthia C. Zarate | J16: AD157 Windy Hill, Buyagan, La Trinidad, Benguet | K16: CAR | L16: To provide financial assistance under the Industry-Based Invention Development (IBID) Program for the fabrication of the commercial prototype of “Bright Lighted Welding Helmet” with Utility Model Registration Number 2-2021051090. | M16: IBID
A17: 2022 | B17: 2022-103 | C17: MODIFICATION OF LIB | D17: TESTING | E17: TECH DEV | G17: 44907 | H17: Utilization of Unexpended Balance to Cover Additional Testing Assistance for the "Adaptive Foldable Crutches" | M17: TESTING
A18: 2022 | B18: 2022-103 | C18: APPROVAL | D18: TESTING | E18: TECH DEV | F18: 17575 | G18: 44886 | H18: Adaptive Foldable Crutches (2-2017-001074) | I18: Mr. James Byran B. Camacho | J18: 214 A Peart St. cor. Emerald St., Brgy. Dolores, Palmera 2 Taytay, Rizal | K18: IVA | L18: The subject technology is quick-fold underarm crutshes that can be collapsed with a push button, are lightweight, all-aluminum and easy to carry. upon recommendation of DOST-MIRDC Mr. Camacho requested additional funds for the testing of his technology and was approved under the invention Testing and Analyses Program. | M18: TESTING
A19: 2022 | B19: 2022-104 | C19: APPROVAL | D19: TECHNICOM | E19: TECH DEV | F19: 2995096 | G19: 44909 | H19: BTC Lab Kit: A Classroom Friendly Tissue Culture System for Instruction in Life Science course in Senior High School | I19: Ma. Bettina A. Macaraeg, DOST-ITDI | J19: DOST-ITDI | K19: NCR | L19: The DLSU Practical Genomics Laboratory (PGL), is a team of scientists and scientists in training who aim to develop molecular marker-based products for use by fishers, farmers and the general public. From 2014-2016, we ran a project that developed a DIY tissue culture kit for coffee as an extension of the USAID-STRIDE funded “Establishing a repository of Philippine coffee varieties and SNP markers for improved production”. Through this project the early stages of a DIY Tissue culture kit was developed. The Build Your Own Tissue Culture Kit (BTC Lab Kit) is composed of instructional and laboratory exercises on life sciences, bioenergetics, botany, genetics, and microbiology, among others, and will also include topics on physics and chemistry. The Kit will also include a Teacher’s Manual, Student’s Workbook, Powerpoint/Video Presentations, and a platform fortechnical support and main objective of the BTC Lab Kit TECHNICOM proposal is to produce, validate and optimize the BTC Lab kit and teaching materials at scale in a factory setting. | M19: TECHNICOM
A20: 2022 | B20: 2022-105 | C20: APPROVAL | D20: TECHNICOM | E20: TECH DEV | F20: 2692520 | G20: 44909 | H20: Pre-commercialization of low-Cost Phototherapy Light System | I20: Mr. Paul M. Cabacungan | J20: Ateneo de Manila University | K20: NCR | L20: TECHNiCOM Program aims to fast-track the market readiness of innovations for their eventual transfer and recommercialization. The phototherapy is the most frequently used treatment when serum bilirubin levels exceed physiological limits but due to its high procurement and maintenance, it may not be accessible to many people most especially in developing countries. | M20: TECHNICOM
A21: 2022 | B21: 2022-106 | C21: APPROVAL | D21: TECHNICOM | E21: TECH DEV | F21: 1450894 | G21: 14/14/2022 | H21: Engineered Water Hyacinth Fiber Laminated Panel as Decorative Home Divider | I21: Ms. Yolanda A. Santorcas | J21: Camarines Sur Polytechnic University | K21: V | L21: The projects aims to conduct pre-commercialization of the decorative engineered water hyacinth fiber laminated panels. The project aims to improve the quality and aesthetics of the developed engineered water hyacinth fiber laminated panels; Provide the necessary adjustments based on the performance assessments; Produce a predetermined quantity to supply the demand of the customers. | M21: TECHNICOM
A22: 2022 | B22: 2022-107 | C22: APPROVAL | D22: TECHNICOM | E22: TECH DEV | F22: 1780736 | G22: 14/14/2022 | H22: Scale-up and Market Validation of Automated Industrial-type Compression Molding Machine for Bamboo Composite Products | I22: Engr. Dan William C. Martinez | J22: Bataan Peninsula State University | K22: III | L22: The objective of the project aims to scale up the existing bamboo waste compression molding machine to a ready-to-transfer prototype to the local bamboo industry. The project highlights the development of the scaled-up bamboo waste compression molding machine that can be transferred to local bamboo processing industries in Bataan and potentially across the country. | M22: TECHNICOM
A23: 2022 | B23: 2022-108 | C23: APPROVAL | D23: TECHNICOM | E23: TECH DEV | F23: 2802604 | G23: 16/12/2022 | H23: Scaled-up Production and Technology Validation of DOST-ITDI's Ready-to-Eat Quail Eggs | I23: Dr. Carmen Lagman | J23: DSLU | K23: NCR | L23: To establish the process schedule for each RTE boiled quail egg product segmented in varying packaging materials; To produce RTE boiled quail eggs using varying packaging materials; and to communicate the results of the validation study to relevant stakeholders of the quail industry | M23: TECHNICOM
A24: 2022 | B24: 2022-109 | C24: APPROVAL | D24: ITECH | E24: COMM | F24: 1083679 | G24: 29/12/2022 | H24: Commercialization of Maker-scope | I24: MR. JEREMY C. DE LEON | J24: Jeremake Online Shop, Blk. 58 Lot 1 Palm cor. Dela Cruz St. Town and Country West, Molino III Bacoor City, Cavite (jeremycdeleon@gmail.com) | K24: IVA | L24: Jeremake Online Shop is a single proprietorship enterprise with business address at Blk. 58 Lot 1 Palm cor. Dela Cruz St., Town and Country West, Molino III, Bacoor City, Cavite. He was assisted by the Invention-Based Enterprise Development Program (IBED) of DOST-TAPI for the initial commercialization of the Make-roscope Keychains and IPRAP for the registration of Industrial Design; The ID Registration pertains to an ornamental design for a keychain with microscope | M24: ITECH
A25: 2022 | B25: 2022-109 | G25: 44924
A26: 2022 | B26: 2022-13 | C26: APPROVAL | D26: IP | E26: Government | F26: 1201148.9 | G26: 44622 | H26: DOST-TAPI's Promotional Activities and Materials | I26: DOST-TAPI | J26: DOST Bicutan Taguig | K26: NCR | L26: The institute aims to develop more promotional activities with the objectives to increase the Institute's visibilty, and positive image to its stakeholders and the general public as a whole. | M26: IP
A27: 2022 | B27: 2022-14 | C27: APPROVAL | D27: DOST-TAPI | E27: Government | F27: 389200 | G27: 44622 | H27: Awards and Recognition for DOST-TAPI's Internal and Exernal Partners | I27: DOST-TAPI | J27: DOST Bicutan Taguig | K27: NCR | L27: DOST-TAPI has created a Program on Awards and Incentives for Service Excellence (PRAISE) Comitee, and Awards and Recognition Commitee under the Steering cum Program Comiteed of the Institute's 35th Anniversary celebration to validate the performances of all aspiring and worthy internal and external awardees. | M27: DOST-TAPI
A28: 2022 | B28: 2022-15 | C28: APPROVAL | D28: DOST-TAPI | E28: Government | F28: 1381550 | G28: 44622 | H28: Launching of TAPI Roadmap and Stakeholders' Recognition | I28: DOST-TAPI | J28: DOST Bicutan Taguig | K28: NCR | L28: The activity held 13 May 2022 in a physical venue since the whole including its accomplishments and future plans. During its meeting on 02 March 2022 via Zoom application hereby resolved to approve the outlined activities and budgetary requirements. | M28: DOST-TAPI
A29: 2022 | B29: 2022-16 | C29: APPROVAL | D29: ISP | E29: IDEATION | F29: 20000 | G29: 44629 | H29: Invent School Program: Webinar Workshop for Selected Grade 5 and 6 Pupils in the 5 (Five) Provinces of Region II | I29: DOST Region II | J29: Dalan na Paccurofon, Corner Matunung St. Regional Government Center, Carig Sur | K29: II | L29: TheTechnology Application and Promotion Institute (TAPI-DOST) takes the lead in promoting and giving support to the development of future inventors among the youth through the conduct of workshops that teach them to craft solutions to solve the country’s pressing concerns. The Seminar-workshop module for elementary students is designed in order for them to create school-based experiences that will benefit their school with the new ideas, emerging research, cutting-edge tools and innovations. | M29: ISP
A30: 2022 | B30: 2022-17 | C30: APPROVAL | D30: IBED | E30: TECH DEV | F30: 300700 | G30: 44629 | H30: Pilot Production of Simplified Compact Tire Inventer Machine (1/2021/050414 | I30: Engr. Lester A. Quimpo | J30: Block 6, Lot 7, Ivy Street, PHHC Block 22, NHA 2, Mandurriao, Iloilo City | K30: VI | L30: The Compact Tire Inventer Machine (CTIM) gets rid of carcinogenic and mutagenic chemicals in discarding old tires. CTIM does not require burning of tires; minimizes throwing away of old tires in landfills and addresses issues on health hazards particularly the spread of dengus in an environment-friendly recycling and upcycling scrap tires. | M30: IBED
A31: 2022 | B31: 2022-18 | C31: APPROVAL | D31: GAD | E31: Government | F31: 121200 | G31: 44636 | H31: 2022 National Women's Month Celebration | I31: Gender Focal Point System -Technical Working Group | J31: DOS-TAPI Bicutan, Taguig | K31: NCR | L31: This year’s theme is “We Make Change Work for Women” with its sub-theme “Agenda ng Kababaihan Tungo sa Kaunlaran.” The celebration highlights the extra ordinary roles of ordinary Juanas in the society as trailblazers of change. It also highlights the gains achieved in promoting gender equality and sustaining them to ensure progress in empowering women. | M31: GAD
A32: 2022 | B32: 2022-19 | C32: REALIGNMENT | D32: ACU-I | G32: 44643 | H32: Realignment of Budget-Gawad Alunig Dalumat | I32: Empowering Science Stories through Citizen Journalism project under the Applied Communication Unit for Inventors ACU-i | L32: DOST-TAPI Executive Commitee during its Meeting on 22 September 2021 via virtual platform approved the budgetary requirements for the projects under ACU-i amounting to P484,917.48 | M32: ACU-I
A33: 2022 | B33: 2022-20 | C33: APPROVAL | D33: ISTE | E33: PROMO | F33: 749991.24 | G33: 44650 | H33: Support to the Promotion and Implementation of the 2022 National Inventors Week (NIW) Celebration Program | I33: DOST-TAPI | J33: TAPI Bldg. ,DOST Compound ,Bicutan Taguig City 1631 | K33: NCR | L33: The Department of Science and Technology through the Technology Application and Promotion Institute (TAPI) was tasked to implement Republic Act No. 7459 otherwise known as “Inventors and Invention Incentives Act of the Philippines” which provides assistance to Filipino inventors. The NIW serves as a venue for the exchange of ideas and information including facilitation of market opportunities to encourage the generation, promotion and development of Filipino inventive capabilities. It also features exhibits of inventions and various symposia. | M33: NIW
A34: 2022 | B34: 2022-21 | C34: APPROVAL | D34: ISTE | E34: PROMO | F34: 1302000 | G34: 44657 | H34: 2022 National Invention Contests and Exhibits (NICE) | I34: ISTE Program, TIPD | J34: Bicutan, Taguig | K34: NCR | L34: The Department of Science and Technology through the Technology Application and Promotion Institute (TAPI) was tasked to implement Republic Act No. 7459 otherwise known as “Inventors and Invention Incentives Act of the Philippines”. The Filipino inventors’ ingenuity and creativity are harnessed through comprehensive and strategic technical and financial support for the development of their inventions/innovations as stipulated in RA 7459. the National Invention Contest, is held to acknowledge and appreciate the crucial role of Filipino inventors in our country’s advancement and development. | M34: NICE
A35: 2022 | B35: 2022-22 | C35: APPROVAL | D35: ACU-I | F35: 1203000 | G35: 44664 | H35: ACU-n's Communication Plan for the Technology Innovation for Commercialization (TECHNICOM) Program | I35: Applied Communications Unit | J35: TIPD, DOST-TAPI Bicutan, Taguig | K35: NCR | L35: ACU-in's Call for proposals for the program aims to establish and generate awareness on TECHNicom through the Tatak PINOYpreneur campaign; and generate proposals from target clients of the program for CY 2022 funding. | M35: ACU
A36: 2022 | B36: 2022-23 | C36: APPROVAL | D36: ISP | E36: IDEATION | F36: 38400 | G36: 44633 | H36: Invention School Program: Webinar-Workshop for Primary to Tertiary Level in Different Provinces of BARMM | I36: Ministry of Science and Technology (MOST)-BARMM | J36: DOST-TAPI | K36: NCR | L36: The Ministry of Science and Technology (MOST) of the Bangsamoro Autonomous Region in Muslim Mindalnao (BARMM) submitted a proposal for the conduct of the invent School Program (ISP) webinar-workshop for selected elementary, high school, and college pupils in its provinces to inculate creative thinking and bring about inventiveness among male and female students to entice them to pursue activities leading to creativeness in solving problems in industrial applications and create student's awareness of intellectual Property Rights and Protection. Whereas, the proposal covers the request for funding assistance for the purchase of prepaid load for internet services of the student-participants during the seminar-workshops amounting to P38,400.00. | M36: ISP
A37: 2022 | B37: 2022-24 | C37: MOTHER PROPOSAL | D37: ISTE | E37: DOST-TAPI | F37: 2400000 | G37: 44671 | H37: lib Caravan | I37: DOST-TAPI | K37: NCR | L37: The ISTE Program is an excellent platform for the dissemination, sharing, and exchange of information and ideas involving S&T Fairs, local and international technology training/seminar/conference/fora/contest, and exhibits that may be beneficial to SMEs and industrial companies. | M37: ISTE
A38: 2022 | B38: 2022-24 | C38: MOTHER PROPOSAL | D38: ISTE | E38: DOST-TAPI | F38: 24000 | G38: 44671 | H38: DOST Stakeholders' Forum and Caravan: Bringing S&T Closer to the People " Lakbay Teknolohiya para kay Juan and Juana" | I38: DOST-TAPI | J38: Bicutan, Taguig | K38: NCR | L38: In the era of pandemic, the ILO op-ed pitched the “Better Normal,” while the World Economic Forum`s proposition was “The Great Reset.” How DOST would communicate its programs that will be good enough to change perception, and eventually translate to improved quality of life for the Filipinos` is set against the backdrop of these two pandemic-coined concepts and aspirations – the `better normal` and `great reset.` Connecting these concepts in promoting the S&T through DOST programs to achieve a “better normal,” previous promotion initiatives need not be abandoned, rather build upon from those previous gains. | M38: ISTE-CARAVAN
A39: 2022 | B39: 2022-25 | C39: APPROVAL | D39: DOST-TAPI | E39: DOST-TAPI | F39: 69200 | G39: 44678 | H39: Refresher Virtual Training on Quality Management System Compliant to ISO 9001:2015 (Awareness, Internal Audit and Documentation) | I39: DOST-TAPI | J39: Bicutan, Taguig | K39: NCR | L39: The objectives of the projects are Prepare key personnel, officers and staff of DOST-TAPI for the successful implementation and effective long-term maintenance of its Quality Management System (QMS) and Improve the process performance through formulations of appropriate corrective actions for continual improvement of the QMS. | M39: DOST-TAPI
A40: 2022 | B40: 2022-26 | C40: APPROVAL | D40: VFP | E40: COMM | F40: 1000000 | G40: 44685 | H40: Support Assistance for Compact Pharmaceuticals Corporation (CPC) under LIGTAS-COVID 19 | I40: Jose Vallerio A. Calleja President and CEO | J40: #17 Sta. Monica St., Malinta, Valenzuela City | K40: NCR | L40: This intervention by DOST-TAPI shall form part in the production of 12 million capsules of vitamins C or 120,000 boxes of the vitamins as per the purchase order of EM-CORE Dotnet and the current demand for vitamin C to help citizens boost their immune system to fight against COVID-19 shall be catered.. | M40: VFP
A41: 2022 | B41: 2022-27 | C41: Guidelines | D41: VFP | E41: MSME | F41: 1504308 | G41: 44706 | H41: Deferment of Payment-Mica by the Sea | I41: Arnulfo G. Singca President | J41: N4018 Centennial Road, Clark Freeport Zone, Pampanga | L41: The objective of the Project is to facilitate production of 2,900 cases of processed products such as: dried tawilis, dried tunsoy, dried galunggong, dried danggit, dried squid, dried bisugo, dried hasahasa, smoked galunggong, smoked tawilis, and smoked hasahasa in different sizes to serve the purchase order of Foremost Foods International Inc., USA; | M41: VFP-PO
A42: 2022 | B42: 2022-28 | D42: DOST-TAPI | G42: 44706 | H42: CCSS | L42: This refers to the draft Customer/Client Satisfaction Survey (CCSS) Form which has been routed to all Divisions for their comments. | M42: DOST-TAPI
A43: 2022 | B43: 2022-29 | C43: APPROVAL | D43: DOST-TAPI | E43: Government | F43: 53175 | G43: 44713 | H43: DOST-TAPI Preparatory Strategic Planning Cum CY 2022 Mid-Year Monitoring and Performance Review | I43: Planning Unit, OD | J43: DOST-TAPI Bicutan, Taguig | K43: NCR | L43: The successful implementation of any program or project is directly linked to proper planning and construction of strategies of the Top Management. The Execom Planning Workshop will be a preparatory activity for the strategic planning workshop. | M43: DOST-TAPI
A44: 2022 | B44: 2022-30 | C44: APPROVAL | D44: DOST-TAPI | E44: Government | F44: 400300 | G44: 44713 | H44: DOST-TAPI CY 2023 Strategic Planning Workshop | I44: Planning Unit, OD | J44: DOST-TAPI Bicutan, Taguig | K44: NCR | L44: The project aims to achieve th following objectives. To provide knowledge on NEDA's Priority Plan, and Ambisyon Natin 2024; To align DOST-TAPI's future programs and projects on the Ambisyon Natin 2040; To distinguish programs that will be included in the submission to NEDA's Program Priority Plan (PPP); To distinguish programs that will be included in the submission to NEDA's National Priority Plan (NPP); To provide the participants a clear understanding of the DBM's Program Expenditure Classification (PREXC) and of the Institute's identified outcome and output indicators; To provide the participants a clear understanding of the concept of the budget's Forward Estimates for proper program planning; and To discuss other concems and issues that may arise during the workshop. | M44: DOST-TAPI
A45: 2022 | B45: 2022-31 | C45: APPROVAL | D45: ISP | E45: IDEATION | F45: 419537.6 | G45: 44713 | H45: Support for the Development of Online Platform for Health Innovations through DOST-TAPI's ISP featuring Health Innovations | I45: IDD | J45: Bicutan, Taguig | K45: NCR | L45: The project also aims to train educators and Invent school trainers through a training-the-trainer scheme. The project's expected outputs are the web design for the online platform of the modules at all levels and the production of 100 printed copies of modules (35 copies for college level, 35 copies for high school level, and 30 copies for elementary level. ) | M45: ISP
A46: 2022 | B46: 2022-32 | C46: MOTHER PROPOSAL | D46: CCU | F46: 316600 | G46: 44720 | H46: Stakeholder's Forum | I46: CCU | L46: The forum aims to publish a Philippine agenda on technology transfer and commercialization that will identify the priority areas and gaps which can be used as a basis for interventions. In line with the DOST-TAPI Roadmap from 2023 to 2032 which was presented to the DOST Central Office through the Undersecretary for Research and Development. The information from the forum can also be used as a basis for the DOST-TAPI Agenda in preparation for the advent of a new government administration in the coming May 2022 elections. | M46: CCU
A47: 2022 | B47: 2022-33 | C47: Realignment | D47: ISTE | E47: Government | F47: 400300 | G47: 44720 | H47: Realignment of NICE | I47: DOST-TAPI | J47: Bicutan, Taguig | K47: NCR | M47: Institutional Support for Trade and Expositions (ISTE)
A48: 2022 | B48: 2022-34 | C48: APPROVAL | D48: VFP | E48: COMM | F48: 702000 | G48: 44720 | H48: Commercialization of Hydrogen Fuel System | I48: KCH R&D Corporation | J48: #18M Rufino St., Soriano Village Phase 1, BH Homes, Paranaque City/ Unit 2215 Medical Plaza Ortigas Bldg., San Miguel Avenue, Ortigas Center, Brgy. San Antonio, Pasig City | K48: NCR | L48: The KCH R&D Corp. is a company that is 60% Filipino-owned, established in 2018; it is chaired by Mr. Nam Chang Ho and currently has seven (7) workers. The technology "Hydrogen Fuel System (HFS)" was filed at the Intellectual Property Office of the Philippines with Registration No.: 2-2018 050367 and a device that is attached to a vehicle compartment that serves as both generator and converter for hydrogen to power up and accelerate automotive, cargo, etc., and its objective is to increase the company's job creation by 80% and introduce a technology that uses hydrogen as an alternative energy source and its applications combining characteristics to gain an anti-air pollution effect. | M48: VFP
A49: 2022 | B49: 2022-35 | C49: APPROVAL | D49: TECHNiCOM | E49: TECH DEV | F49: 2001920 | G49: 44727 | H49: Prototyping and Pilot Testing of Self-Propelled Riding Type Grain Collector (Bagger) for Solar Dried Grains | I49: Joel M. Alcarazy, Isabela State University | J49: PMCQ+FFF, 1, Echague, Isabela | K49: II | M49: TECHNiCOM
A50: 2022 | B50: 2022-36 | C50: APPROVAL | D50: TECHNiCOM | E50: TECH DEV | F50: 2435960 | G50: 44734 | H50: Pilot Testing of the Peanut Harvesting Technology - Peanut Digger in Top Peanut-Growing Areas in Northern Luzon | I50: Dr. Jose De Guzman Central State University | J50: 1400 Brush Row Rd, Wilberforce OH 45384 | K50: V | M50: TECHNiCOM
A51: 2022 | B51: 2022-37 | C51: APPROVAL | D51: ITECH | E51: COMM | F51: NA | G51: 44734 | H51: The Utilization of Calcium Hydroxide and Clinoptilolite Disinfectant PH12 of Hydrogen to Alleviate the Prevalence of Dengue in the Philippines | I51: Mr. Lyle Christian R. Herbosa | J51: Agro-chemical Manufacturing | K51: NCR | L51: L.H. Invention was founded in 2021 by Mr. Lyle Christian Herbosa, a Filipino inventor. The company’s registered business is located at 326 Masili, Calamba, Laguna. The present invention relates to the preparation of Calcium Hydroxide and Clinoptilolite in H2O base (liquid form) and its use as a potent mosquito larvicide. Mosquito larvicide comprising of Calcium Hydroxide and Clinoptilolite in H2O base (liquid form) aims to devise a suitable means of applying the mixture to locations which serve as larvae traps, and thus as an effective mosquito vector control. | M51: ITECH
A52: 2022 | B52: 2022-38 | C52: APPROVAL | D52: ACU-N | E52: TAPI | F52: 75130 | G52: 44734 | H52: ACU-n's Call for Proposal | I52: DOST-TAPI | J52: NA | K52: NCR | L52: DOST-TAPI offers programs of assistance for non-inventor innovators. By mounting the Call for Proposals for DOST-TAPI’s technopreneurship programs, ACU-n seeks to achieve three goals: (1) to establish awareness of DOST-TAPI’s non-inventor programs; (2) to educate DOST-TAPI’s audience of the requirements for DOST-TAPI’s non-inventor programs via call conferences, and; (3) to generate proposals for DOST-TAPI’s non-inventor programs. | M52: ACU-N
A53: 2022 | B53: 2022-39 | C53: MODIFICATION OF LIB | D53: ISTE | E53: TAPI | F53: 1186064 | G53: 44734 | H53: Changes on the Budgetary Requirement for the DOST-Stakeholder' Forum and Caravan: Bringing S&T Closer to the People ("Lakbay Teknolohiya para kay Juan at Juana") | I53: DOST-TAPI | J53: NA | K53: NCR | L53: The project aims to enchance institutional awareness on STI through the conduct of the stakeholder's forum and technology caravanin the Visayas regions (VI, VII, VIII).In ther era of pandemic, the ILO op-ed pitched the "Better Normal," while the World Economic Forum's proposition was " The Great reset". How DOST would communicate its programs that will be good enough to change perception, and eventually translate to improved quality of life for the Filipinos' is set against the backdrop of these two pandemic- coined concepts and aspirations - the "the great reset for the better normal.' | M53: ISTE
A54: 2022 | B54: 2022-40 | C54: PROGRAM TRANSFER | D54: YET | E54: TAPI | G54: 44734 | H54: Downloading of YET Program to the DOST-ROs | I54: DOST-TAPI | J54: NA | K54: NCR | L54: Yet Program aims to develop the entrepreneurial competencies among the youth by providing financial assistance to college students in selected academic institutions and young professionals with research projects viable for commercialization; The YET porgram supports income- generating projects with technological innovation, market potential, and technical viability when commercialized. | M54: YET
A55: 2022 | B55: 2022-41 | C55: TERMINATION OF PROGRAM | D55: VFP | E55: TAPI | G55: 44734 | H55: Termination of the Venture Financing Program (VFP) for Start-up and Technology-Based Projects | I55: DOST-TAPI | J55: NA | K55: NCR | L55: The VFP program both aim to accelerate the commercialization of innovative technologies or inventions by providing the necessary funding support to IP rights owner/ Assignee or technology-based start-up projects. | M55: VFP
A56: 2022 | B56: 2022-42 | C56: POLICY | D56: NA | E56: TAPI | G56: 44734 | H56: Approval of the Proposed Load Reimbursement of DOST-TAPI's Permanent Employees | I56: DOST-TAPI | J56: NA | K56: NCR | L56: Excutive Order No.128, The Technology Application and Promotion Institute (TAPI). headed by a Director who has the sole authority/discretion in project and policy apporvals, was creates and mandated as the implenting arm of the Department of Science and Technology (DOST) in promotinf the commercialization of technologies and marketing the services of other operating units and agencies of ther Department. | M56: NA
A57: 2022 | B57: 2022-43 | C57: MODIFICATION OF LIB | D57: NA | E57: TAPI | G57: 44736 | H57: Modification of the LIB of the Automushcab Project Under the Concept Prototyping Project | I57: DOST-TAPI | J57: NA | K57: NCR | L57: In 18 March 2022, the pre-commercialization specialists and Ms. Merlina F, Cortes-Acero condecuted a monitoring visit and tagging of equipment/device at the residence of Mr. Diaz in Baras, Rizal where the Automushcab is located. Mr. Diaz confirmed that the machine is already working. However, Mr. Diaz explained that he still making some improvements in the machine like putting curtains inside the cabinet to improve moisture inside, etc. | M57: NA
A58: 2022 | B58: 2022-44 | C58: DEFERMENT | D58: NA | E58: TAPI | G58: 44736 | H58: Approval of Deferment of 2nd Phase of PO Financing of Mica By the Sea Company | I58: DOST-TAPI | J58: NA | K58: NCR | L58: April 2021, the financial assistance granted to MTBC by the DOST-TAPI through the Purchase Order Financing facility of its Venture Financing Program has been fully paid on time without the proponent requesting a deferment or restructing of the said assistance. 28 October 2021, DOST-TAPI apporved MBTSC's request for financial assistance amounting to P4,512,920.00 with two (2) months garce period and three (3) months refund period under the PO Financing faciliy of the Venture Financing Program. The company refunded P3,008,612.00 leaving MBTSC an outstanding balance of P1,504,308.00. | M58: NA
A59: 2022 | B59: 2022-45 | C59: APPROVAL | D59: VFP | E59: COMM | F59: 923252 | G59: 44741 | H59: PO Financing Phase 2 for John N' Mico Food Productes | I59: Ms. Myra M. Bustillo, Owner/Manager | J59: John N' Mico Food Products #400 San Miguel, Mexico, Pampanga | K59: III | L59: The objective of this project is to augment the purchasing funds for raw materials and be able to serve the purchase orders within the timeframe of John N' Mico. The company is a beneficiary of the DOST'S MPEX Program in CY 2012 and was established in 2003. Last 2012 John N' Mico was provided financial assistance by TAPI amounting to P594,944. | M59: VFP
A60: 2022 | B60: 2022-46 | C60: APPROVAL | D60: VFP | E60: COMM | F60: 494868.75 | G60: 44748 | H60: PO Financing for La Paz Prime Foods Corporation | I60: Ms. Virgin Mary A. Nicolas, President | J60: La Paz Prime Foods Corporation, Cataguig Road, Brgy. Rizal, La Paz, Tarlac | K60: III | L60: To objectives for this project is to sustain the required raw materials for the production of processed meat products, o serve the existing purchase orders from Joe Kuan Food Corporation Warehouse for the production of a total of 20,250 packs of chorizo for delivery on August (10,125 packs) and September 2022 (10,125 packs) amounting to ₱1,761,750.00; To build external linkages and maintain company credibility; and To realize gross income amounting to ₱324,609.71 upon delivery of the PO. | M60: VFP
A61: 2022 | B61: 2022-47 | C61: CANCELLATION | D61: ACU-N | E61: TAPI | G61: 44748 | H61: Termination of ACU-n's Communication Plan for TECHNICOM Program | I61: DOST-TAPI | J61: NA | K61: NCR | L61: NOT APPLICABLE | M61: ACU-N
A62: 2022 | B62: 2022-48 | C62: CANCELLATION | D62: VFP | E62: PRIVATE | F62: 494868.75 | G62: 44755 | H62: Cancellation of DOST-TAPI Resolution 2022-46 | I62: Ms. Virgin Mary A. Nicolas, President | J62: La Paz Prime Foods Corporation, Cataguig Road, Brgy. Rizal, La Paz, Tarlac | K62: III | L62: NOT APPLICABLE | M62: VFP
A63: 2022 | B63: 2022-49 | C63: APPROVAL | E63: PRIVATE | F63: 494868.75 | G63: 44776 | H63: PO Financing for La Paz Prime Foods Corporation | I63: Ms. Virgin Mary A. Nicolas, President | J63: La Paz Prime Foods Corporation, Cataguig Road, Brgy. Rizal, La Paz, Tarlac | K63: III
A64: 2022 | B64: 2022-49 | D64: VFP | E64: PRIVATE | F64: 494868.75 | G64: 44755 | H64: DOST-TAPI Resolution 2022-46 | I64: Ms. Virgin Mary A. Nicolas, President | J64: La Paz Prime Foods Corporation, Cataguig Road, Brgy. Rizal, La Paz, Tarlac | K64: III | L64: NOT APPLICABLE | M64: VFP
A65: 2022 | B65: 2022-50 | C65: APPROVAL | D65: ISP | E65: IDEATION | F65: 0 | G65: 44776 | H65: Support for the Development of Online Platform for Health Innovations through DOST-TAPI's ISP featuring Health Innovations | I65: DOST-TAPI | J65: NA | K65: NCR | L65: The invent School Program (ISP) of the Invention Development Division (IDD), which leads the conduct of seminar-workshops in private and public schools in coorperation with inventors' groups, LGUs, and NGO, to stimulate students' interest in creativity and inventiveness and create awareness on Intellectual Property Rights (IPR) and Protectiom, has crafted a proposal for a special project entitled, "Support for the Development of Online Learning Platform for Health innovations through DOST-TAPI's Invent Shool Program Featuring Health Innovations" which aims to establish a partnership between DOST-TAPI and DOST-PCHRD on increasing public awareness on health innovations through the Program. | M65: ISP
A66: 2022 | B66: 2022-51 | C66: TERMINATION | D66: IBED II | E66: PRIVATE | G66: 44776 | H66: Termination of the Project "Commercialization of Grooved Perforated Carburator Nozzle" under IBED 2 | I66: Rommel Bernardo | J66: Smartcarb Enterprise, 174 E. Dela Paz St., San Roque, Marikina City | K66: NCR | L66: NOT-APPLICABLE | M66: IBED 2
A67: 2022 | B67: 2022-52 | C67: APPROVAL | D67: ISTE | E67: PROMO | F67: 200000 | G67: 44776 | H67: 2022 Eastern Visayas Regional Science and Technology Week (RSTW) Celebration | I67: DOST VIII | J67: Government Center, Palo, Candahug, Leyte | K67: VIII | L67: The aim of the events is to promote DOST products, services, innovations and technologies that can help boost the MSMEs sector. | M67: ISTE-RSTW
A68: 2022 | B68: 2022-52-A | C68: GUIDELINES | D68: NA | E68: TAPI | G68: 44776 | H68: MAP Guidelines | I68: DOST-TAPI | J68: NA | K68: NCR | L68: MAP was created by virtue of DOST-TAPI being the implementing arm of the Department of Science and Technology (DOST) in promoting the commercialization of technologies per Executive Order No. 128. The MAP covers financial and technical assistance to implement marketing activities that will asisst in the commercialization of locally developed technologies. | M68: NA
A69: 2022 | B69: 2022-53 | C69: APPROVAL | D69: VFP | E69: COMM | F69: 998550 | G69: 44783 | H69: PO Financing Assistance to SETUP assisted Kalinga Blend Roasted Ground Coffee Production" | I69: Ms. Grace B. Agtina, Owner | J69: Golden Berries Hotel and Convention Center, San Juan, Tabuk City, Kalinga | K69: CAR | L69: The project aims to continue the marketability of the products through the competitiveness of Kalinga Blend coffeeTo sustain the quality of ground coffee through the acquisition of grade A coffee beans,To provide safe and quality food products in conformity with food safety standards vis-a-vis FDA regulatory provisions through appropriate packaging and labeling materials;to increase the annual volume of production by at least 25%;To increase gross sales by at least 25% every year, To continue the coffee industry's competitive development and advocacy for Kalinga and/or Cordilleran coffee products. | M69: VFP
A70: 2022 | B70: 2022-54 | C70: APPROVAL | D70: CONCEPT PROTO | E70: IDEATION | F70: 174759.01 | G70: 44783 | H70: Development of a Three Phase to Single Back-to-Back Voltage Source Power Converter Prototype fo Squirrel Cage Induction Machine Drive and Grid Integration | I70: Mr. Leo Marcelo P. Villalba | J70: Zone 1A, Crossing Iponan, Cagayan de Oro City | K70: X | L70: The project's main objective is to create a working prototype of a grid-tied back-to-back VSC that interfaces three(3) phase electrical machines to the single-phase grid. The projects aims to Model,design and stimulate the proposed back-to-back VSC with three (3) phase Squirrel Cage Induction Machine (SCIM) including the design of grid filter; Tuning and discretization of the controllers; design of power module and signal adaption board to interfadce sensors with the micro-controller; Programming of the microcontroller; and testing of the prototype. | M70: CONCEPT PROTO
A71: 2022 | B71: 2022-55 | C71: APPROVAL | D71: CONCEPT PROTO | E71: IDEATION | F71: 60837.6 | G71: 44783 | H71: An Improved Roofing Tile | I71: Mr. Reynaldo P. Cruz | J71: No. 9m Jamaica St., Forrest Hills Subd., Sta. Monica, Novaliches, Quezon City | K71: NCR | L71: Mr.Cruz request for financial assistance of Fabrication of a Commercial Prototype of the UM for "An Improved Roofing Tile" which is distinctively different from his previous UM "A Roofing Tile" of the same technology he submitted for IBID Assistance. The committe recommended to apply his technology first to Concept Prototyping Assistance Program cosidering the absence of his prototype but has been recommended a financial assistance by the IATEC of P199,721.60. | M71: CONCEPT PROTO
A72: 2022 | B72: 2022-56 | C72: APPROVAL | D72: ISTE | E72: PROMO | F72: 300000 | G72: 44790 | H72: DOST Stakeholders' Forum and Caravan for Region IV-A | I72: DOST IV-A | K72: IVA | L72: Request for the inclusion in the agenda of DOST-TAPI EXECOM the approval of DOST IV-A’s project proposal for the DOST Stakeholders’ Forum and Caravan: "Bringing S&T Closer to the People: Lakbay Teknolohiya para kay Juan at Juana" to provide institutional awareness through the conduct of the stakeholders’ forum and technology caravan, to showcase DOST-generated technologies and its network including their available services and programs that may be beneficial to SMEs and industrial companies, and Conduct a stakeholders’ forum that will help publish a Philippine agenda on technology transfer and commercialization that will identify the priority areas and gaps which can be used as a basis for interventions. | M72: ISTE-CARAVAN
A73: 2022 | B73: 2022-57 | C73: APPROVAL | D73: CONCEPT PROTO | E73: IDEATION | F73: 31804.6 | G73: 44799 | H73: Automated Greenhouse Gardening System | I73: Mr. Mark Julius O. Bula | J73: Purok 6-Guava, Lanao, Kidapawan City, North Cotabato | K73: XII | L73: The projects aims to introduce robotics/ automation in agriculture to students and for possible adaption of the technology by communities. | M73: CONCEPT PROTO
A74: 2022 | B74: 2022-58 | C74: APPROVAL | D74: ACU-N | E74: TAPI | F74: 219320 | G74: 44782 | H74: Technobyahe in Bohol Cum DOST-TAPI Milestone Event: Deed of Conveyance Signing Ceremony for JZ Jewelry Repair Shop | I74: DOST-TAPI | J74: NA | K74: NCR | L74: The coverage of the said event through social media posts, press releases, and Audio-Visual Presentation (AVP) production will bring greater awareness about DOST-TAPI and its accomplishments, to promote DOST-TAPI’s Technopreneurship Programs catering to MSMEs, to increase the submission of proposals under the Tatak PINOYpreneur Campaign, and to forge linkages with PSTC-Bohol and LGU, among others. | M74: ACU-N
A75: 2022 | B75: 2022-59 | C75: APPROVAL | D75: VFP | E75: COMM | F75: 1503212.5 | G75: 44811 | H75: Lactobiotics Worldwide Corporation Availment to Acquire Raw Materials though Purchase Order Financing Program of Technology Application and Promotion Institute (TAPI) | I75: Engr. Grecilda P. Sanches, President and CEO | J75: GD Uy Fang Bldg., Sanciangko St., Cebu City | K75: VII | L75: The DOST-SETUP has provided a Water Purification and Filtration System for the company, the quality of the filtered water is below the standard requirement especially during the rainy season. | M75: VFP
A76: 2022 | B76: 2022-60 | C76: TERMINATION | D76: VFP | E76: PRIVATE | G76: 44818 | H76: Termination of Project " Commercialization of Herbal Massage Oil" under IBED II | I76: Roberto D. Osido | J76: Bagong Silang Street, Parang, Marikina | K76: NCR | L76: NOT-APPLICABLE | M76: VFP
A77: 2022 | B77: 2022-61 | C77: APPROVAL | D77: ISTE | E77: PROMO | F77: 200000 | G77: 44818 | H77: NSTW in CAR | I77: DOST CAR | J77: BSU Compound, KM. 6, La Trinidad, Benguet | K77: CAR | L77: The 2022 Hybrid NSTW celebration in CAR aims to strengthen the engagement of the public to science and technology; create science awareness among the public; promote new and appropriate technologies developed in the region; and promote S&T services in the region; Promote existing DOST programs and services in the region through the conduct of training and stakeholders’ forums; Increase awareness of the public on the generated technologies and its networking including their available services and programs which may be beneficial to MSMEs and industrial companies; and Provide a venue for the scientists, researchers, investors and communicators to meet and exchange ideas on the current S&T developments and technological needs of the industries. | M77: ISTE-RSTW
A78: 2022 | B78: 2022-62 | C78: APPROVAL | D78: ISTE | E78: PROMO | F78: 350500 | G78: 44818 | H78: 2022 Inventors Summit and Strategic Planning | I78: Rizal Inventors and Innovators Society, Inc. (RIISI) | K78: NCR | L78: The project aims to provide awareness of the benefits of an inventor based on RA No. 7459, to provide awareness of the privileges and benefits of DOST-TAPI accredited inventor organizations, and to develop strategies, procedures, and mechanisms to operationalize them. Identify and prioritize areas of cooperation and support for accredited inventors' organizations. to develop a specific proposal for TAPI's assistance for CY 2022–2023. Educate the inventor organizations about their benefits and assistance provided by different government agencies. Provide awareness of other inventor-related programs of assistance from other government agencies like IPOPHL and DTI. | M78: ISTE-INV ORG
A79: 2022 | B79: 2022-63 | C79: REALIGNMENT | D79: ACU-N | F79: NA | G79: 44818 | H79: Addiotnal Budget Technobyahe in Bohol Cum DOST-TAPI Milestone Event: Deed of Conveyance Signing Ceremony for JZ Jewelry Repair Shop | I79: DOST-TAPI | J79: NA | K79: NCR | L79: This pertains to the previously approved budget for the Milestone Activity on the Signing of the Deed of Conveyance for the account of JZ Jewelry Repair Shop in Bohol amounting to ₱219,320.00. The scope of this budget includes the airfare of five (5) DOST-TAPI personnel budgeted at ₱7,200.00 per pax. However, during our market scan, we determined that we would need a budget of ₱15,978.00 per pax. | M79: ACU-N
A80: 2022 | B80: 2022-64 | C80: APPROVAL | D80: TECHNICOM | E80: TECH DEV | F80: 2251504 | G80: 44825 | H80: Enhancement, Pilot Testing and Market Study of Biomass Fish Dryer | I80: Engr. Monalyn Oloroso Capiz State University (CSU) | J80: Capiz State University (CSU) | K80: VI | L80: The projects aims to develop the market viability of the biomass-fired fish dryer; Increase the capacity of the dryer from 20 kilograms; improve drying system efficienct to >50%; Conduct comparative analysis on the quality of dried fish output from the dryer and that of the sun-dying method in terms of moisture content and microbal load/content; Establish the market potential of the technology; and Conduct a market study | M80: TECHNICOM
A81: 2022 | B81: 2022-65 | C81: APPROVAL | D81: CONCEPT PROTO | E81: IDEATION | F81: 10160 | G81: 44825 | H81: Fabrication of Suman Molder Gardening System | I81: Engr. Renell Jay G. Villaluz | J81: Purok 3, Brgy. Bulao San Jorge, Samar | K81: VIII | L81: The project aims to develop a suman molder that can be used to produce the product more than the conventional way, uniform in shape, and most importantly minimize food contamination due to less, if not eliminate direct contact or use of hands. | M81: CONCEPT PROTO
A82: 2022 | B82: 2022-66 | D82: TESTING | E82: TECH DEV | F82: 17575 | G82: 44825 | H82: Adaptive Foldable Crutches | I82: Mr. James Bryan B. Camacho | J82: 214 A Pearl St., cor. Emerald St., Brgy. Dolores, Palmera 2, Taytay, Rizal | K82: IVA | L82: Mr. Camacho is resquesting testing assistance of his technology to undergo weight load and meterial tests at the Metal Industry Research and Development Center (DOST-MIRDC); the project proposal complied with the requirements of the Program's first satge coverage, and the test requested will contribute to the pre-commercialization of the product. | M82: TESTING
A83: 2022 | B83: 2022-67 | C83: APPROVAL | D83: VFP | E83: COMM | F83: 1000000 | G83: 44826 | H83: PO Financing for Enhanced Nutribun Production by Esteems Industries, Inc. | I83: Engr. Grecilda P. Sanches, President and CEO | J83: 58-60 Plaridel St., Cebu City and 694 Lower Calajoan, Minglanilla, Cebu | K83: VII | L83: Esteems Industries Incorporated started its operation in 2005 offering a variety of bread products that are produced massively. The Technology Licensing Agreement was executed on 18 December 2020 with effectivity for a period of 5 years from the date of signing. Hence, the agreement shall remain valid until 18 December 2025 and the project will sustain the required raw materials for the production of Nutribun, serve the existing purchase order from Bright Stars Industry Inc. for the production of 132,462 packs of Nutribun for the months of October and November 2022 for DSWD Region VIII for a total of 264,924 packs, build external linkages and maintain company credibility, and realize gross income amounting to ₱4,106,322.00 upon delivery of the P.Os. | M83: VFP
A84: 2022 | B84: 2022-68 | C84: APPROVAL | D84: CONCEPT PROTO | E84: IDEATION | F84: 199727 | G84: 44832 | H84: A Device for Wave and Salinity Power Generation (SaltPanel) | I84: Mr. Patrick Roland C. De Guzman | J84: 65 Lawa, Obando, Bulacan | K84: III | L84: The project aims provide clean, chaep and continuous electricy from the ocean by using saltwater. Embodiments of the Saltpanel technology generally relate to triboelectric nanogenerators and charge-trapping generators with a construck for harvesting mechanical energy and electrokinetic energy. The triboelectric nanogenerator includes a first component and the second component in contact with the first component to generate triboelec charges, and the charge-trapping generator includes a charge-trapping layer, a semiconducting layer, and an electrode. | M84: CONCEPT PROTO
A85: 2022 | B85: 2022-69 | C85: APPROVAL | D85: CONCEPT PROTO | E85: IDEATION | F85: 199950 | G85: 44832 | H85: Prototype Development of a Meat Tenderizing Machine | I85: Mr. Raul C. Mabitazan | J85: Lot 7B, Blk. 2, Lexberville, Balacbac Rd., Sto. Tomas Proper, Baguio City. | K85: CAR | L85: Mr. Raul C. Mabitazan is requesting financial assistance for the fabrication of one (1) working prototype of a meat tenderizer machine. The project aims to develop a meat tenderizing machine that not only utilizes automated mechanical pounding in tenderizing a meat but also added the marinating features in the process, and the proposed machine presents another option for tenderizing meat, and this will utilize an automated mechanical pnuematic pounding system. | M85: CONCEPT PROTO
A86: 2022 | B86: 2022-70 | C86: APPROVAL | D86: CONCEPT PROTO | E86: IDEATION | F86: 48250 | G86: 44832 | H86: Hydroponics Buckets with Basket Carriers | I86: Ms. Ma. Clarissa B. Mabitazan | J86: Lot 7B, Blk. 2, Lexberville, Balacbac Rd., Sto. Tomas Proper, Baguio City. | K86: CAR | L86: Project aims to develop a hydroponic bucket with basket carriers that could extend the shelf life or freshness of vegetables being sold to consumers. The days when vegetables are being bought in the markets or supermarket using plastic or paper bag which can only be kept for two to three days will no longer be practical. Hydroponics Bucket frame is made of light weight metal, such as aluminum alloy frame which makes the carrier sturdy and durable, and the bucket/s adopts an opaque material, which can effectively prevent the light from penetrating, thereby reducing the growth of algae in the nutrient solution. | M86: CONCEPT PROTO
A87: 2022 | B87: 2022-71 | C87: APPROVAL | D87: CONCEPT PROTO | E87: IDEATION | F87: 27532 | G87: 44832 | H87: Remote Controlled Safety Vest for Bikers | I87: Mr. Wringley S. Patio | J87: 229 Barangay Lourdes, Tarlac City, Tarlac | K87: III | L87: With the high demand for bicycles as a transportation option, along with the high rise in the number of accidents related to the use of bicycles On the road, this project, which is a biker safety vest, aims to provide the same protection.that the turn signals and hazard lights of motorcycles and cars give to their riders and passengers which is their visibility on the road primarily through their hazard lights, along with the predictability of their intended directions through the use of the turn signals. | M87: CONCEPT PROTO
A88: 2022 | B88: 2022-72 | C88: APPROVAL | D88: FAD | G88: 44832 | H88: 3-Day In-house Training on Basic Records and Archives Management | I88: DOST-TAPI | J88: NA | K88: NCR | L88: Training on basic records and archives management provides the participants with knowledge and skills, as well as the correct attitude towards a systematic and economical records management activity in the agency. It also provides participants with technical know-how necessary for the effective and efficient performance of their duties and responsibilities as records and document custodians, clerks, and secretaries. Proper records and archives management promotes organizational efficiency. Every organization deals with enormous amount of records. It is essential that those responsible for the custody of any type of records become familiar with the requirements and processes of record and archive management. | M88: FAD
A89: 2022 | B89: 2022-73 | C89: APPROVAL | D89: YET | E89: COMM | F89: 225000 | G89: 44832 | H89: Bamboo-Laminated Student Desk Production | I89: Romblon State University | J89: Liwanag, Odiongan, Romblon | K89: IVB | L89: The general objective of the project is to imbibe the culture of technopreneurship among students through the commercialization of students' research; Produce student desks with bamboo-laminated tabletops to be sold to other schools and HEI's in the province or in ther region; Involve students in production as valuated workforce for them to appreciate the value of hard-earned money as well as provide an appreciation of how an enterprise is run profitably; and Provide a workplace for encouraging inventiveness and creativity of students while at the same time serving as a labaratory for the course works. | M89: YET
A90: 2022 | B90: 2022-74 | C90: APPROVAL | D90: ISTE | E90: PROMO | F90: 300000 | G90: 44839 | H90: DOST Stakeholders' Forum and Caravan for Region I | I90: DOST Region I | J90: DMMSU-MLU Campus, San Fernando, La Union | K90: I | L90: The projects aims to institutionalize awareness through the conduct of the stakeholder's forum and technology caravan, which ties up with regional offices that may include previous initiatives and activities for the "new" or "better" normal. | M90: ISTE-CARAVAN
A91: 2022 | B91: 2022-75 | C91: APPROVAL | D91: ISTE | E91: PROMO | F91: 200000 | G91: 44839 | H91: National Science and Technology Week (NSTW) Celebration in Region I | I91: DOST Region I | J91: DMMSU-MLU Campus, San Fernando, La Union | K91: I | L91: The Departrnent of Science and Technology Region 1 (DOST-1 ) conducted the 2022 National Science and Technology last November 9-11,2022 and the celebration is presented through blended (limited face-to-face and virtual) activities to comply to current community quarantine protocols. It increase awareness, understanding and appreciation of STI to strengthen STI culture in all sectors in Region 1. the program promote DOST-TAPI programs and services, promote technologies that are funded and generated by the DOST system and the regional scientific communities provided a venue for scientists, researchers/inventors, investors, and communicators to meet and exchange ideas on the current S&T developments and technological needs of the industry, increase awareness and appreciation among the public for Science and Technology programs and projects through the conduct of trainings, seminars, and educational activities. | M91: ISTE-RSTW
